Workbook

Sheet Table Index
A1: Public expenditure on ECE: table index and finder | I1: About the data in this table
A3: Use the drop down arrows to choose (filter) what information you require, then click on the Worksheet link to go directly to the table
A4: Financial year | B4: Measurement | C4: Service type 13 | D4: Programme 14 | E4: NZ Deprivation Index 18 | F4: Funding band 19 | G4: Geographical breakdown | H4: Equity funding 5 | I4: Worksheet | J4: Table name
A5: 2002 - 2023 | B5: Government expenditure on ECE | I5: EXP1 | J5: Total government expenditure on early childhood education by Vote ($000, GST exclusive)
A6: 2002 - 2023 | B6: Government expenditure on ECE | I6: EXP2 | J6: Vote Education expenditure on early childhood by funding direction ($000, GST exclusive)
A7: 2002 - 2023 | B7: ECE expenditure per funded child hour | I7: EXP3 | J7: Government expenditure on early childhood education per funded child hour and per full-time equivalent (FTE) ($, GST exclusive)
A8: 2002 - 2023 | B8: ECE expenditure as a proportion of GDP | I8: EXP4 | J8: ECE expenditure on early childhood education as a proportion of GDP, Public expenditure on education and Total Core Crown expenses ($000, GST exclusive)
A9: 2002 - 2023 | B9: Entitlement funding, Equity funding and Targeted Funding for Disadvantage | C9: Yes | D9: Yes | I9: EXP5 | J9: Entitlement funding and equity funding and targeted funding for disadvantage by service type and programme ($000, GST exclusive)
A10: 2002 - 2023 | B10: Entitlement funding, Equity funding and Targeted Funding for Disadvantage | D10: Yes | G10: Regional Council | I10: EXP6 | J10: Entitlement funding, equity funding and targeted funding for disadvantage by Regional Council and programme ($000, GST exclusive)
A11: 2002 - 2023 | B11: Entitlement funding, Equity funding and Targeted Funding for Disadvantage | D11: Yes | G11: Territorial Authority, Auckland Local Board | I11: EXP7 | J11: Entitlement funding, equity funding and targeted funding for disadvantage by Territorial Authority, Auckland Local Board and programme ($000, GST exclusive)
A12: 2002 - 2023 | B12: Entitlement funding, Equity funding and Targeted Funding for Disadvantage | D12: Yes | G12: Education Area | I12: EXP8 | J12: Entitlement funding, equity funding and targeted funding for disadvantage by Education Area and programme ($000, GST exclusive)
A13: 2002 - 2023 | B13: Entitlement funding, Equity funding and Targeted Funding for Disadvantage | D13: Yes | E13: Yes | I13: EXP9 | J13: Entitlement funding, equity funding and targeted funding for disadvantage by New Zealand Index of Deprivation and programme ($000, GST exclusive)
A14: 2002 - 2023 | B14: Funding per funded child hour | C14: Yes | D14: Yes | I14: EXP10 | J14: Entitlement funding, equity funding and targeted funding for disadvantage per funded child hour by service type and programme ($, GST exclusive)
A15: 2002 - 2023 | B15: Funding per funded child hour | D15: Yes | G15: Regional Council | I15: EXP11 | J15: Entitlement funding, equity funding and targeted funding for disadvantage per funded child hour by Regional Council and programme ($, GST exclusive)
A16: 2002 - 2023 | B16: Funding per funded child hour | D16: Yes | G16: Territorial Authority, Auckland Local Board | I16: EXP12 | J16: Entitlement funding, equity funding and targeted funding for disadvantage per funded child hour by Territorial Authority, Auckland Local Board and programme ($, GST exclusive)
A17: 2002 - 2023 | B17: Funding per funded child hour | D17: Yes | G17: Education Area | I17: EXP13 | J17: Entitlement funding, equity funding and targeted funding for disadvantage per funded child hour by Education Area and programme ($, GST exclusive)
A18: 2002 - 2023 | B18: Funding per funded child hour | D18: Yes | E18: Yes | I18: EXP14 | J18: Entitlement funding, equity funding and targeted funding for disadvantage per funded child hour by New Zealand Index of Deprivation and programme ($, GST exclusive)
A19: 2002 - 2023 | B19: Funded child hour | C19: Yes | D19: Yes | I19: EXP15 | J19: Funded child hours by service type and programme
A20: 2002 - 2023 | B20: Funded child hour | D20: Yes | G20: Regional Council | I20: EXP16 | J20: Funded child hours by Regional Council and programme
A21: 2002 - 2023 | B21: Funded child hour | D21: Yes | G21: Territorial Authority, Auckland Local Board | I21: EXP17 | J21: Funded child hours by Territorial Authority, Auckland Local Board and programme
A22: 2002 - 2023 | B22: Funded child hour | D22: Yes | G22: Education Area | I22: EXP18 | J22: Funded child hours funding by Education Area and programme
A23: 2002 - 2023 | B23: Funded child hour | D23: Yes | E23: Yes | I23: EXP19 | J23: Funded child hours by New Zealand Index of Deprivation and programme
A24: 2002 - 2023 | B24: Equity funding component A, B, C and D | C24: Yes | E24: Yes | I24: EXP20 | J24: Equity funding by New Zealand Index of Deprivation, service type and funding component ($, GST exclusive)
A25: 2006 - 2023 | B25: Entitlement funding | D25: Yes | F25: Yes | I25: EXP21 | J25: Entitlement funding by funding band ($000, GST exclusive)
A26: 2005 - 2023 | B26: Subsidy rates | C26: Yes | D26: Yes | F26: Yes | I26: EXP22 | J26: Subsidy rates ($, GST inclusive)
A27: 2002 - 2023 | B27: Equity Funding rates | H27: Yes | I27: EXP23 | J27: Equity Funding rates ($, GST inclusive)

Sheet Table Notes
A1: About these statistics | G1: Table Index
A2: 1 | B2: ECE Expenditure | C2: ECE expenditure has been reported in more than one way in this worksheet: - Tabs EXP1 -4 report the published MOE Financial Annual Accounts data, which uses audited Ministry of Education financial data. - Tabs EXP5-16 use data from the Early Childhood Funding Claim Forms (RS7s) database. Notes on the tables: - Dollar amounts in these tables (except for Tables EXP22 and EXP23) are GST-exclusive. - In all tables, all years are July to June financial years. - All dollar figures are nominal dollars, except those in Table 1 EXP3, which have been adjusted using CPI to 2023 dollars. - Dollar amounts may not always add to totals due to calculation rounding.
A3: 2 | B3: Core Crown expenses | C3: Day-to-day spending of the Crown, departments, Offices of Parliament, the NZ Superannuation Fund and the Reserve Bank of New Zealand, as sourced from Treasury's Economic and Fiscal Updates.
A4: 3 | B4: Total Vote Education, Vote Education Review Office (ERO) and Vote Social Development (MSD) | C4: The total government expenditure on early childhood education through Ministry of Education, Ministry of Social Development and Education Review Office. "Votes" refer to groups of similar or related appropriations (e.g. Vote Education includes all education-related appropriations administered by the Ministry of Education). Vote education review office is excluded as from 2020/21 as ERO is no longer able to provide their figures regarding spending specifically on early childhood education. There are slight differences between the Vote Education expense in early childhood education and the Core Crown Education expenses in early childhood education due to differences in the composition of expenditure items that are included. For more information see:
C5: https://budget.govt.nz/budget/2024/by/vote/index.htm
A6: 4 | B6: Vote Education Early Childhood Education Appropriation | C6: The total expenditure on ECE as reported in the Ministry of Education's Annual Report.
A7: 5 | B7: Equity Funding | C7: Equity Funding is a targeted funding mechanism paid to eligible services in addition to the ECE entitlement funding. Its objectives are to reduce educational disparities between different groups in New Zealand communities, reduce barriers to participation faced by those groups that are under represented in ECE services and to support ECE services in raising their level of educational achievement. Eligibility for Components A and B of equity funding are based on the service's Equity Index (EQI), which measures the extent to which a service draws children from low socio-economic communities. Component C provides targeted funding to support those services that provide early childhood education in a language and culture other than English (including sign language) during more than half of the formal education and care programme while Component D recognises that isolated services will face higher costs when accessing goods and services and provides services with an isolation index of 1.65 or greater with additional funding (See note 20 for more information on isolation index). The Equity funding value shown includes targeted funding for disadvantage since January 2017 (which is the primary source of the $10m growth between 16/17 and 18/19).
A8: 6 | B8: Targeted Funding for Disadvantage | C8: Targeted Funding for Disadvantage (Targeted Funding) is a targeted funding mechanism for licensed early childhood education (ECE) services and ngā kōhanga reo (early learning services). Targeted Funding is paid to eligible early learning services in addition to the ECE Funding Subsidy, 20 Hours ECE and Equity Funding. The objective of Targeted Funding is to improve educational equity by improving the quality and affordability of early learning for children/tamariki from disadvantaged backgrounds. Targeted Funding must be spent on activities, staff or equipment that will benefit children/tamariki from disadvantaged background. Targeted Funding for Disadvantage was introduced in 2018.
A9: 7 | B9: 2020 Lockdown Data Collection | C9: Funded child hours collected during Alert Level 3 and 4 of the COVID-19 Alert System were based on the enrolments recorded at the beginning of the year. While no actual hours were being generated throughout this period, services continued to receive funding based on these enrolment hours.
A10: 8 | B10: In 2023 dollars | C10: The dollar values have been adjusted for inflation using the CPI 2023 June quarter, sourced from Statistics New Zealand.
A11: 9 | B11: Funded child hours (FCH) | C11: Funded child hours are the hours for which a service may claim funding and for this reason will exclude those hours where a child attends beyond 6 hours in a day, or 30 hours in a week. Funded child hours in these tables do not include hours from unlicensed services with the exception of unlicensed Kōhanga reo.
A12: 10 | B12: Full-time equivalent (FTE) | C12: Full-time equivalent is nominally defined as 1,000 funded child hours per year.
A13: 11 | B13: GDP | C13: GDP figures are nominal GDP sourced from Financial Statements of the Government of New Zealand.
A14: 12 | B14: Total public expenditure on education | C14: Total public expenditure on education includes ECE, primary and secondary schools and tertiary funding expenses, departmental expenses and other education expenses, as sourced from Treasury's Economic and Fiscal Updates.
A15: 13 | B15: Service type | C15: The type of ECE service; e.g. education & care service, kindergarten, home-based service, playcentre, Kōhanga reo, etc. For information on the different service types, see:
C16: https://www.education.govt.nz/parents-and-caregivers/early-learning/starting-early-learning/types-early-learning
A17: 14 | B17: Programme | C17: Describes the ECE subsidy funding that is being referred to (20 Hours ECE, 2 and over - non 20 Hours ECE, Under 2's and Equity funding).
A18: 15 | B18: Regional Council | C18: The regional council area the service is located in. Note, all current and past data involving geographic breakdowns are based on the latest boundaries.
A19: 16 | B19: Territorial Authority | C19: The territorial authority area the service is located in. Data for Auckland City incorporates the changes in 2010 to a single "super city". Because of its size, data for Auckland City also includes a breakdown by local board, sub-units of territorial authorities. Care should be taken when interpreting the geographic location of home-based services, as these have been assigned to the location of the co-ordinator, or local or national office. Note that territorial authorities do not always correspond to regional council borders. All current and past data involving geographic breakdowns are based on the latest boundaries.
A20: 17 | B20: Education area | C20: The education area that the ECE service is located in. These are twelve administrative areas created by the Ministry of Education.
A21: 18 | B21: NZDep2018 Index of Deprivation | C21: A measure of socio-economic deprivation produced by the Ministry of Health based on information from the 2018 Census. This index was used across the whole period, from 2000 onwards. The more deprived an area, the higher the NZ Deprivation Index. The NZDep decile used here relates to the NZDep decile of the census area unit the service is located in, rather than where the children live. Care should be taken when interpreting the geographic location of home-based services, as these have been assigned to the location of the co-ordinator, or local or national office. More information on the NZ Deprivation Index can be found in:
C22: https://www.otago.ac.nz/wellington/departments/publichealth/research/hirp/otago020194.html
A23: 19 | B23: Funding band | C23: Funding band is determined by the percentage of qualified teachers/parents or qualification criteria, and the level of the operating structure (all-day vs). The percentage figures in the funding band refer to the number of ‘Registered Teacher Hours’ a service has as a proportion of the total number of regulated (ratio) staff hours. For more information see Chapter 3 of the ECE Funding Handbook Changes to the funding bands: In February 2011, the 80-99% and 100% funding bands were removed and replaced with a single 80%+ band. The 80-99% and 100% funding bands were re-introduced in January 2021
C24: https://www.education.govt.nz/education-professionals/early-learning/funding-and-financials/ece-funding-handbook/chapter-3-the-ece-funding-subsidy
A25: 20 | B25: Isolation Index | C25: The Isolation Index is a measure calculated and used by the Ministry of Education to rate the 'relative isolation' of each service. This is determined by measuring a service’s distance to the nearest towns/cities with population sizes of 5,000, 20,000, and 100,000.
A26: 21 | B26: ECE Entitlement Funding | C26: The sum of 20 Hours ECE, 2 and over - non 20 Hours ECE, Under 2's using Ministry of Education financial accounts data.
A27: 22 | B27: Blank values | C27: Blank values are shown in cells where there is no applicable data.
A28: 23 | B28: Attestation level | C28: The level of pay parity for Education and Care services. The pay parity opt-in scheme is a funding scheme for education and care services, including hospital-based services. Services that opt in can access higher funding rates for paying their certificated teachers at or above certain minimum salary steps. There are four salary scales which are Base, Parity, Extended Parity, and Full Parity. More information can be found below:
C29: https://www.education.govt.nz/education-professionals/early-learning/funding-and-financials/pay-parity-opt-scheme-education-and-care-services

Sheet EXP1
A1: ='Table Index'!J5 -> Total government expenditure on early childhood education by Vote ($000, GST exclusive) | E1: About the data in this table | H1: Table Index
A3: Year | B3: Core Crown Education expenses in Early Childhood Education 2 | C3: Vote Education Early Childhood Education Appropriation 4 | D3: Vote Education Review Office (ERO) | E3: Vote Social Development (MSD) | F3: Vote Education, Vote Education Review Office (ERO) and Vote Social Development (MSD) 3
A4: 2001/02 | B4: 343000 | C4: 306753 | D4: 3049 | E4: 52688 | F4: 362490
A5: 2002/03 | B5: 373000 | C5: 341744 | D5: 3557 | E5: 53096 | F5: 398397
A6: 2003/04 | B6: 393000 | C6: 362957 | D6: 5828 | E6: 55383 | F6: 424168
A7: 2004/05 | B7: 444000 | C7: 414954 | D7: 6646 | E7: 74412 | F7: 496012
A8: 2005/06 | B8: 555000 | C8: 518795 | D8: 8320 | E8: 100501 | F8: 627616
A9: 2006/07 | B9: 617000 | C9: 584321 | D9: 8287 | E9: 125564 | F9: 718172
A10: 2007/08 | B10: 860000 | C10: 828521 | D10: 8672 | E10: 130684 | F10: 967877
A11: 2008/09 | B11: 1030000 | C11: 1011387 | D11: 9463 | E11: 134255 | F11: 1155105
A12: 2009/10 | B12: 1184000 | C12: 1166112 | D12: 9193 | E12: 149995 | F12: 1325300
A13: 2010/11 | B13: 1340000 | C13: 1325710 | D13: 9708 | E13: 156847 | F13: 1492265
A14: 2011/12 | B14: 1355000 | C14: 1325170 | D14: 9820 | E14: 154426 | F14: 1489416
A15: 2012/13 | B15: 1436000 | C15: 1410309 | D15: 9610 | E15: 148087 | F15: 1568006
... A22: 2019/20 | B22: 2007000 | C22: 1990222.8 | D22: 11905 | E22: 107434 | F22: 2109561.8
A23: 2020/21 | B23: 2132000 | C23: 2119894.7 | E23: 111312 | F23: 2231206.7
A24: 2021/22 | B24: 2247000 | C24: 2238026 | E24: 102889 | F24: 2340915
A25: 2022/23 | B25: 2355000 | C25: 2342383.3 | E25: 108366 | F25: 2450749.3

Sheet EXP2
A1: ='Table Index'!J6 -> Vote Education expenditure on early childhood by funding direction ($000, GST exclusive) | F1: About the data in this table | I1: Table Index
A3: Year | B3: Entitlement funding for 20 Hours ECE | C3: Entitlement funding for 2 and over non-20 Hours ECE | D3: Entitlement funding for Under 2's | E3: Equity funding 5 | F3: Other | G3: Vote Education Early Childhood Education Appropriation 4
A4: 2001/02 | B4: 0 | C4: 216714 | D4: 85039 | E4: 1778 | F4: 3222 | G4: 306753
A5: 2002/03 | B5: 0 | C5: 235947 | D5: 94418 | E5: 8648 | F5: 2731 | G5: 341744
A6: 2003/04 | B6: 0 | C6: 249620 | D6: 101124 | E6: 9528 | F6: 2685 | G6: 362957
A7: 2004/05 | B7: 0 | C7: 289405 | D7: 111977 | E7: 9609 | F7: 3963 | G7: 414954
A8: 2005/06 | B8: 0 | C8: 365533 | D8: 139149 | E8: 9653 | F8: 4460 | G8: 518795
A9: 2006/07 | B9: 0 | C9: 392975 | D9: 161994 | E9: 9911 | F9: 19441 | G9: 584321
A10: 2007/08 | B10: 366497 | C10: 239877 | D10: 188768 | E10: 10127 | F10: 23252 | G10: 828521
A11: 2008/09 | B11: 523554 | C11: 246375 | D11: 206360 | E11: 10955 | F11: 24143 | G11: 1011387
A12: 2009/10 | B12: 624171 | C12: 270024 | D12: 234189 | E12: 11910 | F12: 25818 | G12: 1166112
A13: 2010/11 | B13: 752650 | C13: 277212 | D13: 257965 | E13: 12302 | F13: 25581 | G13: 1325710
A14: 2011/12 | B14: 762464 | C14: 274593 | D14: 254934 | E14: 14926 | F14: 18253 | G14: 1325170
A15: 2012/13 | B15: 805568 | C15: 288337 | D15: 264642 | E15: 37387 | F15: 14375 | G15: 1410309
... A25: 2022/23 | B25: 1190820.9 | C25: 538379.97 | D25: 504784.24 | E25: 68681.405 | F25: 39716.75 | G25: 2342383.3

Sheet EXP3
A1: ='Table Index'!J7 -> Government expenditure on early childhood education per funded child hour and per full-time equivalent (FTE) ($, GST exclusive) | H1: About the data in this table | K1: Table Index
A3: In 2023 dollars 8
A4: Year | B4: Funded child hours (FCHs) 9 | C4: Full-time equivalents 9 (1 FTE = 1,000 FCHs) | D4: ECE entitlement funding (000) 21 | E4: ECE entitlement funding per FCH | F4: ECE entitlement funding per FTE | G4: Vote Education Early Childhood Education Appropriation 4 (000) | H4: Vote Education ECE funding per FCH | I4: Vote Education ECE funding per FTE | J4: Total government ECE expenditure (000) 3 | K4: Total government ECE expenditure per FCH | L4: Total government ECE expenditure per FTE
A5: 2001/02 | B5: 94494000 | C5: 94493.567 | D5: 505915 | E5: 5.35 | F5: 5354 | G5: 514298 | H5: 5.44 | I5: 5443 | J5: 607746 | K5: 6.43 | L5: 6432
A6: 2002/03 | B6: 103393000 | C6: 103393.22 | D6: 545814 | E6: 5.28 | F6: 5279 | G6: 564614 | H6: 5.46 | I6: 5461 | J6: 658213 | K6: 6.37 | L6: 6366
A7: 2003/04 | B7: 107967000 | C7: 107966.97 | D7: 566079 | E7: 5.24 | F7: 5243 | G7: 585790 | H7: 5.43 | I7: 5426 | J7: 684581 | K7: 6.34 | L7: 6341
A8: 2004/05 | B8: 110925000 | C8: 110925.23 | D8: 629873 | E8: 5.68 | F8: 5678 | G8: 651171 | H8: 5.87 | I8: 5870 | J8: 778372 | K8: 7.02 | L8: 7017
A9: 2005/06 | B9: 114888000 | C9: 114888.29 | D9: 761669 | E9: 6.63 | F9: 6630 | G9: 782969 | H9: 6.82 | I9: 6815 | J9: 947202 | K9: 8.24 | L9: 8245
A10: 2006/07 | B10: 118089000 | C10: 118089.28 | D10: 821140 | E10: 6.95 | F10: 6954 | G10: 864569 | H10: 7.32 | I10: 7321 | J10: 1062617 | K10: 9 | L10: 8998
A11: 2007/08 | B11: 129519000 | C11: 129518.87 | D11: 1131040 | E11: 8.73 | F11: 8733 | G11: 1178519 | H11: 9.1 | I11: 9099 | J11: 1376744 | K11: 10.63 | L11: 10630
A12: 2008/09 | B12: 138458000 | C12: 138458.38 | D12: 1363017 | E12: 9.84 | F12: 9844 | G12: 1412018 | H12: 10.2 | I12: 10198 | J12: 1612665 | K12: 11.65 | L12: 11647
A13: 2009/10 | B13: 147537000 | C13: 147537.41 | D13: 1549558 | E13: 10.5 | F13: 10503 | G13: 1601368 | H13: 10.85 | I13: 10854 | J13: 1819973 | K13: 12.34 | L13: 12336
A14: 2010/11 | B14: 157014000 | C14: 157013.66 | D14: 1679858 | E14: 10.7 | F14: 10699 | G14: 1729274 | H14: 11.01 | I14: 11014 | J14: 1946530 | K14: 12.4 | L14: 12397
A15: 2011/12 | B15: 162339000 | C15: 162339.28 | D15: 1669418 | E15: 10.28 | F15: 10284 | G15: 1712290 | H15: 10.55 | I15: 10548 | J15: 1924517 | K15: 11.85 | L15: 11855
A16: 2012/13 | B16: 169675000 | C16: 169675.41 | D16: 1743476 | E16: 10.28 | F16: 10275 | G16: 1809904 | H16: 10.67 | I16: 10667 | J16: 2012282 | K16: 11.86 | L16: 11860
... A26: 2022/23 | B26: 223603000 | C26: 223603.16 | D26: 2233985 | E26: 9.99 | F26: 9991 | G26: 2342383 | H26: 10.48 | I26: 10476 | J26: 2450749 | K26: 10.96 | L26: 10960
A28: In nominal dollars
A29: Year | B29: Funded child hours (FCHs) 9 | C29: Full-time equivalents 9 (1 FTE = 1,000 FCHs) | D29: ECE entitlement funding (000) 21 | E29: ECE entitlement funding per FCH | F29: ECE entitlement funding per FTE | G29: Vote Education Early Childhood Education Appropriation 4 (000) | H29: Vote Education ECE funding per FCH | I29: Vote Education ECE funding per FTE | J29: Total government ECE expenditure (000) 3 | K29: Total government ECE expenditure per FCH | L29: Total government ECE expenditure per FTE
A30: 2001/02 | B30: 94494000 | C30: 94493.567 | D30: 301753 | E30: 3.1933708 | F30: 3193 | G30: 306753 | H30: 3.2462845 | I30: 3246 | J30: 362490 | K30: 3.8361342 | L30: 3836
A31: 2002/03 | B31: 103393000 | C31: 103393.22 | D31: 330365 | E31: 3.1952289 | F31: 3195 | G31: 341744 | H31: 3.3052845 | I31: 3305 | J31: 398397 | K31: 3.8532218 | L31: 3853
A32: 2003/04 | B32: 107967000 | C32: 107966.97 | D32: 350744 | E32: 3.2486232 | F32: 3249 | G32: 362957 | H32: 3.3617411 | I32: 3362 | J32: 424168 | K32: 3.928683 | L32: 3929
A33: 2004/05 | B33: 110925000 | C33: 110925.23 | D33: 401382 | E33: 3.6184914 | F33: 3618 | G33: 414954 | H33: 3.740844 | I33: 3741 | J33: 496012 | K33: 4.4715885 | L33: 4472
A34: 2005/06 | B34: 114888000 | C34: 114888.29 | D34: 504682 | E34: 4.3928062 | F34: 4393 | G34: 518795 | H34: 4.5156473 | I34: 4516 | J34: 627616 | K34: 5.4628369 | L34: 5463
A35: 2006/07 | B35: 118089000 | C35: 118089.28 | D35: 554969 | E35: 4.6995712 | F35: 4700 | G35: 584321 | H35: 4.9481289 | I35: 4948 | J35: 718172 | K35: 6.0816018 | L35: 6082
A36: 2007/08 | B36: 129519000 | C36: 129518.87 | D36: 795142 | E36: 6.139198 | F36: 6139 | G36: 828521 | H36: 6.3969133 | I36: 6397 | J36: 967877 | K36: 7.4728646 | L36: 7473
A37: 2008/09 | B37: 138458000 | C37: 138458.38 | D37: 976289 | E37: 7.0511368 | F37: 7051 | G37: 1011387 | H37: 7.3046281 | I37: 7305 | J37: 1155105 | K37: 8.3426151 | L37: 8343
A38: 2009/10 | B38: 147537000 | C38: 147537.41 | D38: 1128384 | E38: 7.6481212 | F38: 7648 | G38: 1166112 | H38: 7.9038394 | I38: 7904 | J38: 1325300 | K38: 8.9828065 | L38: 8983
A39: 2010/11 | B39: 157014000 | C39: 157013.66 | D39: 1287827 | E39: 8.2020061 | F39: 8202 | G39: 1325710 | H39: 8.4432781 | I39: 8443 | J39: 1492265 | K39: 9.5040457 | L39: 9504
A40: 2011/12 | B40: 162339000 | C40: 162339.28 | D40: 1291991 | E40: 7.9585853 | F40: 7959 | G40: 1325170 | H40: 8.1629659 | I40: 8163 | J40: 1489416 | K40: 9.1747112 | L40: 9175
A41: 2012/13 | B41: 169675000 | C41: 169675.41 | D41: 1358547 | E41: 8.0067408 | F41: 8007 | G41: 1410309 | H41: 8.3118057 | I41: 8312 | J41: 1568006 | K41: 9.2412097 | L41: 9241
... A51: 2022/23 | B51: 223603000 | C51: 223603.16 | D51: 2233985.2 | E51: 9.9908481 | F51: 9991 | G51: 2342383.3 | H51: 10.475627 | I51: 10476 | J51: 2450749.3 | K51: 10.960263 | L51: 10960

Sheet EXP4
A1: ='Table Index'!J8 -> ECE expenditure on early childhood education as a proportion of GDP, Public expenditure on education and Total Core Crown expenses ($000, GST exclusive) | H1: About the data in this table | K1: Table Index
A3: Year | B3: GDP 11 | C3: Vote Education ECE funding as a proportion of GDP | D3: Total government expenditure on ECE as a proportion of GDP | E3: Total public expenditure on education 12 | F3: Vote Education ECE funding as a proportion of total public expenditure on education | G3: Total government expenditure on ECE as a proportion of total public expenditure on education | H3: Total Core Crown Expenses 2 | I3: Vote Education ECE funding as a proportion of total Core Crown Expenses | J3: Total government expenditure on ECE as a proportion of total Core Crown Expenses
A4: 2001/02 | B4: 127511000 | C4: 0.0024056983 | D4: 0.0028428136 | E4: 6473000 | F4: 0.047389618 | G4: 0.056000309 | H4: 37970000 | I4: 0.0080788254 | J4: 0.0095467474
A5: 2002/03 | B5: 135673000 | C5: 0.00251888 | D5: 0.0029364501 | E5: 7016000 | F5: 0.048709236 | G5: 0.056784065 | H5: 41749000 | I5: 0.0081856811 | J5: 0.0095426717
A6: 2003/04 | B6: 146387000 | C6: 0.0024794346 | D6: 0.0028975797 | E6: 7585000 | F6: 0.047851945 | G6: 0.055921951 | H6: 41608000 | I6: 0.0087232503 | J6: 0.010194386
A7: 2004/05 | B7: 157101000 | C7: 0.0026413199 | D7: 0.003157281 | E7: 7930000 | F7: 0.052327112 | G7: 0.062548802 | H7: 44660000 | I7: 0.0092914017 | J7: 0.011106404
A8: 2005/06 | B8: 165027000 | C8: 0.0031436977 | D8: 0.003803111 | E8: 9914000 | F8: 0.052329534 | G8: 0.063306032 | H8: 49084000 | I8: 0.010569534 | J8: 0.01278657
A9: 2006/07 | B9: 175047000 | C9: 0.0033380806 | D9: 0.0041027381 | E9: 9269000 | F9: 0.06304035 | G9: 0.077481066 | H9: 53764000 | I9: 0.010868258 | J9: 0.01335786
A10: 2007/08 | B10: 188147000 | C10: 0.0044035834 | D10: 0.0051442595 | E10: 9551000 | F10: 0.086747042 | G10: 0.10133777 | H10: 56753000 | I10: 0.014598717 | J10: 0.0170542
A11: 2008/09 | B11: 189554000 | C11: 0.0053356141 | D11: 0.0060938044 | E11: 11455000 | F11: 0.088292187 | G11: 0.1008385 | H11: 63711000 | I11: 0.015874606 | J11: 0.018130386
A12: 2009/10 | B12: 196734000 | C12: 0.0059273537 | D12: 0.0067365072 | E12: 11724000 | F12: 0.099463664 | G12: 0.11304162 | H12: 63554000 | I12: 0.018348365 | J12: 0.020853133
A13: 2010/11 | B13: 205876000 | C13: 0.0064393616 | D13: 0.0072483679 | E13: 11650000 | F13: 0.11379485 | G13: 0.12809142 | H13: 70099000 | I13: 0.018911967 | J13: 0.021287964
A14: 2011/12 | B14: 214977000 | C14: 0.0061642408 | D14: 0.0069282574 | E14: 11654000 | F14: 0.11370946 | G14: 0.12780299 | H14: 68939000 | I14: 0.019222356 | J14: 0.021604839
A15: 2012/13 | B15: 218838000 | C15: 0.0064445343 | D15: 0.007165145 | E15: 12504000 | F15: 0.11278863 | G15: 0.12540035 | H15: 69962000 | I15: 0.020158214 | J15: 0.022412252
... A25: 2022/23 | B25: 395896000 | C25: 0.0059166632 | D25: 0.0061903866 | E25: 18403000 | F25: 0.12728269 | G25: 0.13317118 | H25: 127574000 | I25: 0.018360977 | J25: 0.019210414

Sheet EXP5
A1: ='Table Index'!J9 -> Entitlement funding and equity funding and targeted funding for disadvantage by service type and programme ($000, GST exclusive) | M1: About the data in this table | P1: Table Index
A2: Note that for this table, Education & Care services includes both Casual Education & Care and Hospital-based services. Kōhanga reo includes unlicensed Kōhanga reo up to 2008.
A4: Click on arrow to select (filter) the information you need
A5: Service type 13 | B5: Programme 14 | C5: 2001/02 | D5: 2002/03 | E5: 2003/04 | F5: 2004/05 | G5: 2005/06 | H5: 2006/07 | I5: 2007/08 | J5: 2008/09 | K5: 2009/10 | L5: 2010/11 | M5: 2011/12 | N5: 2012/13 | O5: 2013/14 | P5: 2014/15 | Q5: 2015/16 | R5: 2016/17 | S5: 2017/18 | T5: 2018/19 | U5: 2019/20 | V5: 2020/21 | W5: 2021/22 | X5: 2022/23
A6: Education & Care | B6: 20 Hours ECE | C6: 0 | D6: 0 | E6: 0 | F6: 0 | G6: 0 | H6: 0 | I6: 222343.06 | J6: 342122.01 | K6: 417329.39 | L6: 471854.54 | M6: 508505.07 | N6: 550360.78 | O6: 601756.02 | P6: 647445.23 | Q6: 682799.74 | R6: 694187.8 | S6: 707888.05 | T6: 729497.47 | U6: 769860.59 | V6: 820559.74 | W6: 834522.28 | X6: 875048.6
A7: Education & Care | B7: Under 2's | C7: 57534.38 | D7: 60856.71 | E7: 68591.895 | F7: 79216.739 | G7: 102834.86 | H7: 119878.39 | I7: 144379.8 | J7: 163706.66 | K7: 182168.2 | L7: 187839.75 | M7: 191914.48 | N7: 201140.17 | O7: 219030.55 | P7: 229790.42 | Q7: 246861.62 | R7: 260956.86 | S7: 278573.75 | T7: 294461.51 | U7: 301498.69 | V7: 337604.39 | W7: 367034.44 | X7: 425089.92
A8: Education & Care | B8: 2 and over - non 20 Hours ECE | C8: 108092.62 | D8: 118903.16 | E8: 130228.02 | F8: 147006.33 | G8: 193303.63 | H8: 231756.26 | I8: 172599.72 | J8: 187362.07 | K8: 201943.9 | L8: 204971.11 | M8: 205910.79 | N8: 218237.26 | O8: 235372.9 | P8: 253997.02 | Q8: 270108.92 | R8: 291528 | S8: 307314.23 | T8: 326756.41 | U8: 342456.45 | V8: 355602.84 | W8: 380335.13 | X8: 412442.91
A9: Education & Care | B9: Equity | C9: 1118.0497 | D9: 2318.3732 | E9: 2395.9037 | F9: 2526.439 | G9: 2734.7008 | H9: 3023.743 | I9: 3250.3528 | J9: 3780.1861 | K9: 3910.5813 | L9: 4188.4669 | M9: 7794.3284 | N9: 13804.011 | O9: 21729.111 | P9: 24480.936 | Q9: 26895.82 | R9: 28790.269 | S9: 30292.558 | T9: 30901.279 | U9: 32363.996 | V9: 33131.183 | W9: 33804.414 | X9: 34286.359
A10: Education & Care | B10: Targeted Funding for Disadvantage | C10: 0 | D10: 0 | E10: 0 | F10: 0 | G10: 0 | H10: 0 | I10: 0 | J10: 0 | K10: 0 | L10: 0 | M10: 0 | N10: 0 | O10: 0 | P10: 0 | Q10: 0 | R10: 0 | S10: 2895.2497 | T10: 5697.801 | U10: 5826.9885 | V10: 6126.3149 | W10: 6125.1714 | X10: 6201.4536
A11: Education & Care | B11: Total | C11: 166745.05 | D11: 182078.24 | E11: 201215.82 | F11: 228749.51 | G11: 298873.19 | H11: 354658.4 | I11: 542572.94 | J11: 696970.92 | K11: 805352.08 | L11: 868853.87 | M11: 914124.68 | N11: 983542.22 | O11: 1077888.6 | P11: 1155713.6 | Q11: 1226666.1 | R11: 1275462.9 | S11: 1326963.8 | T11: 1387314.5 | U11: 1452006.7 | V11: 1553024.5 | W11: 1621821.4 | X11: 1753069.2
A12: Home-based | B12: 20 Hours ECE | C12: 0 | D12: 0 | E12: 0 | F12: 0 | G12: 0 | H12: 0 | I12: 19182.942 | J12: 26795.446 | K12: 31411.061 | L12: 34188.032 | M12: 36499.161 | N12: 37627.019 | O12: 38885.02 | P12: 39543.777 | Q12: 41205.398 | R12: 42089.094 | S12: 40401.127 | T12: 37343.841 | U12: 35313.174 | V12: 31543.444 | W12: 30072.62 | X12: 26831.52
A13: Home-based | B13: Under 2's | C13: 13625.756 | D13: 14401.603 | E13: 15705.489 | F13: 17102.098 | G13: 18364.58 | H13: 20160.513 | I13: 24500.882 | J13: 27201.165 | K13: 31083.618 | L13: 34770.669 | M13: 35097.57 | N13: 36396.035 | O13: 40238.995 | P13: 49139.83 | Q13: 56551.791 | R13: 53430.42 | S13: 54802.446 | T13: 51392.494 | U13: 44605.31 | V13: 39066.215 | W13: 38106.674 | X13: 34928.171
A14: Home-based | B14: 2 and over - non 20 Hours ECE | C14: 11334.13 | D14: 11851.419 | E14: 13041.235 | F14: 14443.85 | G14: 16089.074 | H14: 18231.912 | I14: 14874.655 | J14: 16413.532 | K14: 18287.19 | L14: 20431.6 | M14: 21831.193 | N14: 22754.551 | O14: 23695.991 | P14: 27011.843 | Q14: 31072.2 | R14: 32502.945 | S14: 33939.781 | T14: 33679.321 | U14: 31641.571 | V14: 27821.181 | W14: 25627.597 | X14: 23969.965
A15: Home-based | B15: Equity | C15: 68.75527 | D15: 112.49186 | E15: 108.55571 | F15: 89.888277 | G15: 83.809199 | H15: 80.335387 | I15: 124.14015 | J15: 176.70745 | K15: 170.35258 | L15: 168.54594 | M15: 644.48012 | N15: 1456.8393 | O15: 2833.8738 | P15: 3671.7006 | Q15: 4550.5193 | R15: 5501.2547 | S15: 6626.3609 | T15: 6635.2399 | U15: 6520.2773 | V15: 5338.2088 | W15: 4804.2376 | X15: 4218.6524
A16: Home-based | B16: Targeted Funding for Disadvantage | C16: 0 | D16: 0 | E16: 0 | F16: 0 | G16: 0 | H16: 0 | I16: 0 | J16: 0 | K16: 0 | L16: 0 | M16: 0 | N16: 0 | O16: 0 | P16: 0 | Q16: 0 | R16: 0 | S16: 533.83204 | T16: 1009.0491 | U16: 1006.6591 | V16: 940.17879 | W16: 864.36943 | X16: 707.78679
A17: Home-based | B17: Total | C17: 25028.641 | D17: 26365.513 | E17: 28855.279 | F17: 31635.836 | G17: 34537.463 | H17: 38472.761 | I17: 58682.619 | J17: 70586.85 | K17: 80952.221 | L17: 89558.847 | M17: 94072.404 | N17: 98234.445 | O17: 105653.88 | P17: 119367.15 | Q17: 133379.91 | R17: 133523.71 | S17: 136303.55 | T17: 130059.94 | U17: 119086.99 | V17: 104709.23 | W17: 99475.498 | X17: 90656.095
... A41: Total | B41: Total | C41: 302864.04 | D41: 344391.96 | E41: 373238.91 | F41: 411706.92 | G41: 496476.84 | H41: 564286.95 | I41: 817900.71 | J41: 1026788.4 | K41: 1169325 | L41: 1255904 | M41: 1305814.3 | N41: 1388788.3 | O41: 1508694.3 | P41: 1607689.9 | Q41: 1698932.7 | R41: 1753786.4 | S41: 1810524.3 | T41: 1869377.8 | U41: 1962027.7 | V41: 2096777.7 | W41: 2172070.9 | X41: 2316512.2

Sheet EXP6
A1: ='Table Index'!J10 -> Entitlement funding, equity funding and targeted funding for disadvantage by Regional Council and programme ($000, GST exclusive) | M1: About the data in this table | P1: Table Index
A3: Click on arrow to select (filter) the information you need
A4: Regional Council 15 | B4: Programme 14 | C4: 2001/02 | D4: 2002/03 | E4: 2003/04 | F4: 2004/05 | G4: 2005/06 | H4: 2006/07 | I4: 2007/08 | J4: 2008/09 | K4: 2009/10 | L4: 2010/11 | M4: 2011/12 | N4: 2012/13 | O4: 2013/14 | P4: 2014/15 | Q4: 2015/16 | R4: 2016/17 | S4: 2017/18 | T4: 2018/19 | U4: 2019/20 | V4: 2020/21 | W4: 2021/22 | X4: 2022/23
A5: Area outside regions | B5: 20 Hours ECE | C5: 0 | D5: 0 | E5: 0 | F5: 0 | G5: 0 | H5: 0 | I5: 6.41376 | J5: 52.176071 | K5: 49.490667 | L5: 42.750278 | M5: 54.611122 | N5: 37.866174 | O5: 34.909983 | P5: 59.211478 | Q5: 66.840261 | R5: 49.756696 | S5: 32.189565 | T5: 60.556991 | U5: 59.954765 | V5: 72.17713 | W5: 27.198322 | X5: 99.027757
A6: Area outside regions | B6: Under 2's | C6: 21.66112 | D6: 33.13856 | E6: 34.13296 | F6: 28.5152 | G6: 33.84736 | H6: 30.870187 | I6: 34.207253 | J6: 50.157707 | K6: 31.761739 | L6: 36.696261 | M6: 24.102783 | N6: 25.73687 | O6: 39.442852 | P6: 32.008487 | Q6: 28.180383 | R6: 25.366957 | S6: 24.997983 | T6: 33.442748 | U6: 60.192678 | V6: 78.0048 | W6: 19.983026 | X6: 17.444191
A7: Area outside regions | B7: 2 and over - non 20 Hours ECE | C7: 26.51488 | D7: 45.94432 | E7: 46.06848 | F7: 47.437867 | G7: 43.76288 | H7: 35.461333 | I7: 34.2328 | J7: 33.131609 | K7: 29.443555 | L7: 28.274157 | M7: 28.3138 | N7: 34.7168 | O7: 46.877217 | P7: 50.237635 | Q7: 44.048661 | R7: 46.284104 | S7: 42.963757 | T7: 41.993096 | U7: 57.631496 | V7: 85.034035 | W7: 160.69296 | X7: 115.26205
A8: Area outside regions | B8: Equity | C8: 2.1173333 | D8: 4.2346667 | E8: 4.2346667 | F8: 4.2346667 | G8: 4.2346667 | H8: 4.2346667 | I8: 4.2346667 | J8: 4.8714667 | K8: 4.8714589 | L8: 4.8713739 | M8: 4.8713739 | N8: 6.1597565 | O8: 7.3174957 | P8: 7.3174957 | Q8: 7.3174957 | R8: 7.3174957 | S8: 7.3174957 | T8: 7.3174957 | U8: 7.3833391 | V8: 7.5087652 | W8: 7.6137391 | X8: 7.7644174
A9: Area outside regions | B9: Targeted Funding for Disadvantage | C9: 0 | D9: 0 | E9: 0 | F9: 0 | G9: 0 | H9: 0 | I9: 0 | J9: 0 | K9: 0 | L9: 0 | M9: 0 | N9: 0 | O9: 0 | P9: 0 | Q9: 0 | R9: 0 | S9: 0 | T9: 0.44922609 | U9: 0.89845217 | V9: 0 | W9: 0.59543478 | X9: 2.0767826
A10: Area outside regions | B10: Total | C10: 50.293333 | D10: 83.317547 | E10: 84.436107 | F10: 80.187733 | G10: 81.844907 | H10: 70.566187 | I10: 79.08848 | J10: 140.33685 | K10: 115.56742 | L10: 112.59207 | M10: 111.89908 | N10: 104.4796 | O10: 128.54755 | P10: 148.7751 | Q10: 146.3868 | R10: 128.72525 | S10: 107.4688 | T10: 143.75956 | U10: 186.06073 | V10: 242.72473 | W10: 216.08348 | X10: 241.5752
A11: Auckland Region | B11: 20 Hours ECE | C11: 0 | D11: 0 | E11: 0 | F11: 0 | G11: 0 | H11: 0 | I11: 113998.8 | J11: 168692.43 | K11: 203363.98 | L11: 230164.97 | M11: 249196.73 | N11: 268516.8 | O11: 295831.36 | P11: 322235.06 | Q11: 339620.36 | R11: 342882.25 | S11: 348249.08 | T11: 353470.41 | U11: 368092.45 | V11: 387788.44 | W11: 389868 | X11: 403422.35
A12: Auckland Region | B12: Under 2's | C12: 26930.94 | D12: 28963.37 | E12: 32209.971 | F12: 35594.274 | G12: 43780.998 | H12: 50947.456 | I12: 61963.563 | J12: 68666.265 | K12: 75421.182 | L12: 78638.063 | M12: 80791.473 | N12: 86256.612 | O12: 96457.739 | P12: 110196.31 | Q12: 122756.65 | R12: 123540.69 | S12: 131388.82 | T12: 136558.28 | U12: 136255.47 | V12: 149301.91 | W12: 160653.23 | X12: 182345.52
A13: Auckland Region | B13: 2 and over - non 20 Hours ECE | C13: 66444.366 | D13: 73664.87 | E13: 79981.033 | F13: 88839.166 | G13: 107012.15 | H13: 123711.74 | I13: 79024.212 | J13: 84402.684 | K13: 90063.195 | L13: 91898.253 | M13: 93352.37 | N13: 98646.412 | O13: 107040.79 | P13: 119874.18 | Q13: 132926.97 | R13: 145005.9 | S13: 151324.47 | T13: 159929.02 | U13: 166317.12 | V13: 170655.84 | W13: 182163.11 | X13: 197494.89
A14: Auckland Region | B14: Equity | C14: 1096.0746 | D14: 2252.6137 | E14: 2272.4918 | F14: 2332.9614 | G14: 2394.6569 | H14: 2474.2246 | I14: 2586.1499 | J14: 3041.4109 | K14: 3083.4176 | L14: 3290.2907 | M14: 5020.5835 | N14: 8989.6508 | O14: 14205.827 | P14: 16218.631 | Q14: 18287.272 | R14: 19988.948 | S14: 21843.08 | T14: 22332.623 | U14: 22926.266 | V14: 22507.615 | W14: 23036.16 | X14: 23173.118
A15: Auckland Region | B15: Targeted Funding for Disadvantage | C15: 0 | D15: 0 | E15: 0 | F15: 0 | G15: 0 | H15: 0 | I15: 0 | J15: 0 | K15: 0 | L15: 0 | M15: 0 | N15: 0 | O15: 0 | P15: 0 | Q15: 0 | R15: 0 | S15: 1432.6327 | T15: 2764.6728 | U15: 2748.8357 | V15: 2808.5971 | W15: 2888.8915 | X15: 3012.2132
A16: Auckland Region | B16: Total | C16: 94471.381 | D16: 104880.85 | E16: 114463.5 | F16: 126766.4 | G16: 153187.81 | H16: 177133.42 | I16: 257572.73 | J16: 324802.79 | K16: 371931.78 | L16: 403991.58 | M16: 428361.16 | N16: 462409.47 | O16: 513535.71 | P16: 568524.18 | Q16: 613591.26 | R16: 631417.78 | S16: 654238.08 | T16: 675055.01 | U16: 696340.14 | V16: 733062.4 | W16: 758609.4 | X16: 809448.08
... A118: Total | B118: Total | C118: 302864.04 | D118: 344391.96 | E118: 373238.91 | F118: 411706.92 | G118: 496476.84 | H118: 564286.95 | I118: 817900.71 | J118: 1026788.4 | K118: 1169325 | L118: 1255904 | M118: 1305814.3 | N118: 1388788.3 | O118: 1508694.3 | P118: 1607689.9 | Q118: 1698932.7 | R118: 1753786.4 | S118: 1810524.3 | T118: 1869377.8 | U118: 1962027.7 | V118: 2096777.7 | W118: 2172070.9 | X118: 2316512.2

Sheet EXP7
A1: ='Table Index'!J11 -> Entitlement funding, equity funding and targeted funding for disadvantage by Territorial Authority, Auckland Local Board and programme ($000, GST exclusive) | M1: About the data in this table | P1: Table Index
A3: Click on arrow to select (filter) the information you need
A4: Territorial Authority with Auckland Local Boards 16 | B4: Programme 14 | C4: 2001/02 | D4: 2002/03 | E4: 2003/04 | F4: 2004/05 | G4: 2005/06 | H4: 2006/07 | I4: 2007/08 | J4: 2008/09 | K4: 2009/10 | L4: 2010/11 | M4: 2011/12 | N4: 2012/13 | O4: 2013/14 | P4: 2014/15 | Q4: 2015/16 | R4: 2016/17 | S4: 2017/18 | T4: 2018/19 | U4: 2019/20 | V4: 2020/21 | W4: 2021/22 | X4: 2022/23
A5: Ashburton District | B5: 20 Hours ECE | C5: 0 | D5: 0 | E5: 0 | F5: 0 | G5: 0 | H5: 0 | I5: 2296.3973 | J5: 3257.8284 | K5: 4216.4768 | L5: 4666.3239 | M5: 5595.6002 | N5: 5735.0774 | O5: 6156.7454 | P5: 6533.5046 | Q5: 6634.9328 | R5: 6598.0277 | S5: 6481.5036 | T5: 6594.0561 | U5: 7254.6708 | V5: 7498.9216 | W5: 7580.4521 | X5: 7692.5822
A6: Ashburton District | B6: Under 2's | C6: 307.78575 | D6: 328.49294 | E6: 319.53815 | F6: 339.17457 | G6: 450.06112 | H6: 590.9631 | I6: 647.44047 | J6: 949.97955 | K6: 1246.8987 | L6: 1332.6977 | M6: 1593.4135 | N6: 1529.3208 | O6: 1579.383 | P6: 1449.0101 | Q6: 1543.1482 | R6: 1780.1966 | S6: 1923.645 | T6: 1864.2111 | U6: 1949.8956 | V6: 2103.8207 | W6: 2410.9495 | X6: 2426.7238
A7: Ashburton District | B7: 2 and over - non 20 Hours ECE | C7: 1098.3943 | D7: 1159.9427 | E7: 1295.7525 | F7: 1428.3692 | G7: 1685.7782 | H7: 1855.4885 | I7: 657.95379 | J7: 1004.5344 | K7: 1351.9787 | L7: 1281.4912 | M7: 1399.1195 | N7: 1610.9926 | O7: 1650.8738 | P7: 1660.1883 | Q7: 1631.8798 | R7: 1706.7688 | S7: 1864.2585 | T7: 2066.1758 | U7: 2076.6151 | V7: 2156.4164 | W7: 2268.0591 | X7: 2552.671
A8: Ashburton District | B8: Equity | C8: 0 | D8: 0 | E8: 0 | F8: 0 | G8: 0 | H8: 0 | I8: 2.2096 | J8: 5.8510222 | K8: 6.0166564 | L8: 6.2254 | M8: 8.3900087 | N8: 26.090122 | O8: 50.188 | P8: 56.849157 | Q8: 61.25307 | R8: 59.875296 | S8: 52.396739 | T8: 51.214009 | U8: 54.524565 | V8: 54.88007 | W8: 67.627252 | X8: 63.616617
A9: Ashburton District | B9: Targeted Funding for Disadvantage | C9: 0 | D9: 0 | E9: 0 | F9: 0 | G9: 0 | H9: 0 | I9: 0 | J9: 0 | K9: 0 | L9: 0 | M9: 0 | N9: 0 | O9: 0 | P9: 0 | Q9: 0 | R9: 0 | S9: 13.651148 | T9: 23.796522 | U9: 19.767757 | V9: 24.11007 | W9: 20.349626 | X9: 18.125189
A10: Ashburton District | B10: Total | C10: 1406.18 | D10: 1488.4356 | E10: 1615.2906 | F10: 1767.5438 | G10: 2135.8393 | H10: 2446.4516 | I10: 3604.0012 | J10: 5218.1934 | K10: 6821.3708 | L10: 7286.7382 | M10: 8596.5232 | N10: 8901.4809 | O10: 9437.1902 | P10: 9699.5521 | Q10: 9871.2139 | R10: 10144.868 | S10: 10335.455 | T10: 10599.454 | U10: 11355.474 | V10: 11838.149 | W10: 12347.438 | X10: 12753.719
A11: Auckland: Albert-Eden | B11: 20 Hours ECE | C11: 0 | D11: 0 | E11: 0 | F11: 0 | G11: 0 | H11: 0 | I11: 7228.6484 | J11: 11598.916 | K11: 13429.694 | L11: 14450.494 | M11: 15108.889 | N11: 16320.092 | O11: 18099.242 | P11: 19746.589 | Q11: 20711.114 | R11: 20874.82 | S11: 20339.997 | T11: 20261.224 | U11: 20728.45 | V11: 21805.467 | W11: 20839.811 | X11: 20890.673
A12: Auckland: Albert-Eden | B12: Under 2's | C12: 2057.2629 | D12: 2101.5888 | E12: 2446.935 | F12: 2675.2059 | G12: 3399.5106 | H12: 3585.3077 | I12: 4463.7194 | J12: 5043.0848 | K12: 5544.7199 | L12: 5646.1843 | M12: 5648.8518 | N12: 6168.5022 | O12: 6662.4175 | P12: 9633.7947 | Q12: 10924.607 | R12: 9647.2893 | S12: 9673.0051 | T12: 9500.2322 | U12: 9516.9439 | V12: 10494.575 | W12: 10442.44 | X12: 11328.799
A13: Auckland: Albert-Eden | B13: 2 and over - non 20 Hours ECE | C13: 5127.5941 | D13: 5551.7282 | E13: 6007.5737 | F13: 6546.7572 | G13: 7952.923 | H13: 9193.2589 | I13: 6563.5696 | J13: 6950.4463 | K13: 6882.4832 | L13: 6806.4339 | M13: 6674.7113 | N13: 6740.3607 | O13: 7003.7975 | P13: 8030.4395 | Q13: 8638.5878 | R13: 9034.6593 | S13: 9043.8883 | T13: 9800.4551 | U13: 10314.04 | V13: 10653.291 | W13: 10573.897 | X13: 10977.985
A14: Auckland: Albert-Eden | B14: Equity | C14: 17.492348 | D14: 34.20395 | E14: 35.44926 | F14: 38.25338 | G14: 40.86544 | H14: 41.431973 | I14: 35.870667 | J14: 31.185467 | K14: 30.960136 | L14: 30.190113 | M14: 39.256089 | N14: 49.900812 | O14: 77.978991 | P14: 99.073609 | Q14: 126.69403 | R14: 135.78715 | S14: 140.59324 | T14: 139.48331 | U14: 144.78093 | V14: 153.1636 | W14: 142.73339 | X14: 159.21486
A15: Auckland: Albert-Eden | B15: Targeted Funding for Disadvantage | C15: 0 | D15: 0 | E15: 0 | F15: 0 | G15: 0 | H15: 0 | I15: 0 | J15: 0 | K15: 0 | L15: 0 | M15: 0 | N15: 0 | O15: 0 | P15: 0 | Q15: 0 | R15: 0 | S15: 13.098552 | T15: 23.916972 | U15: 21.267845 | V15: 25.561026 | W15: 35.359948 | X15: 50.328539
A16: Auckland: Albert-Eden | B16: Total | C16: 7202.3493 | D16: 7687.521 | E16: 8489.958 | F16: 9260.2165 | G16: 11393.299 | H16: 12819.999 | I16: 18291.808 | J16: 23623.633 | K16: 25887.857 | L16: 26933.303 | M16: 27471.708 | N16: 29278.856 | O16: 31843.436 | P16: 37509.897 | Q16: 40401.003 | R16: 39692.555 | S16: 39210.582 | T16: 39725.312 | U16: 40725.483 | V16: 43132.058 | W16: 42034.242 | X16: 43407
... A538: Total | B538: Total | C538: 302864.04 | D538: 344391.96 | E538: 373238.91 | F538: 411706.92 | G538: 496476.84 | H538: 564286.95 | I538: 817900.71 | J538: 1026788.4 | K538: 1169325 | L538: 1255904 | M538: 1305814.3 | N538: 1388788.3 | O538: 1508694.3 | P538: 1607689.9 | Q538: 1698932.7 | R538: 1753786.4 | S538: 1810524.3 | T538: 1869377.8 | U538: 1962027.7 | V538: 2096777.7 | W538: 2172070.9 | X538: 2316512.2

Sheet EXP8
A1: ='Table Index'!J12 -> Entitlement funding, equity funding and targeted funding for disadvantage by Education Area and programme ($000, GST exclusive) | M1: About the data in this table | P1: Table Index
A3: Click on arrow to select (filter) the information you need
A4: Education Area 17 | B4: Programme 14 | C4: 2001/02 | D4: 2002/03 | E4: 2003/04 | F4: 2004/05 | G4: 2005/06 | H4: 2006/07 | I4: 2007/08 | J4: 2008/09 | K4: 2009/10 | L4: 2010/11 | M4: 2011/12 | N4: 2012/13 | O4: 2013/14 | P4: 2014/15 | Q4: 2015/16 | R4: 2016/17 | S4: 2017/18 | T4: 2018/19 | U4: 2019/20 | V4: 2020/21 | W4: 2021/22 | X4: 2022/23
A5: Tai Tokerau | B5: 20 Hours ECE | C5: 0 | D5: 0 | E5: 0 | F5: 0 | G5: 0 | H5: 0 | I5: 12158.08 | J5: 19975.539 | K5: 22472.478 | L5: 23744.766 | M5: 25459.052 | N5: 26882.552 | O5: 29601.914 | P5: 31817.19 | Q5: 33646.945 | R5: 35112.508 | S5: 35298.304 | T5: 35787.297 | U5: 38157.615 | V5: 41818.909 | W5: 42404.646 | X5: 44980.595
A6: Tai Tokerau | B6: Under 2's | C6: 3098.4558 | D6: 3678.6106 | E6: 3732.136 | F6: 4015.8985 | G6: 4936.7206 | H6: 5795.6387 | I6: 6832.006 | J6: 7795.2452 | K6: 8180.3661 | L6: 8114.8495 | M6: 8560.0579 | N6: 8881.7464 | O6: 9682.9553 | P6: 10216.395 | Q6: 10825.129 | R6: 11973.261 | S6: 12678.265 | T6: 12376.747 | U6: 13074.321 | V6: 14791.591 | W6: 15781.172 | X6: 16893.74
A7: Tai Tokerau | B7: 2 and over - non 20 Hours ECE | C7: 7198.028 | D7: 8510.8417 | E7: 8915.5132 | F7: 9436.3789 | G7: 11234.881 | H7: 12677.402 | I7: 7856.1585 | J7: 8725.3828 | K7: 9427.5129 | L7: 9354.4181 | M7: 9032.6996 | N7: 9760.9301 | O7: 10359.38 | P7: 11610.018 | Q7: 12783.645 | R7: 13875.322 | S7: 14368.25 | T7: 15054.534 | U7: 16568.699 | V7: 17751.366 | W7: 19348.383 | X7: 20442.88
A8: Tai Tokerau | B8: Equity | C8: 420.69036 | D8: 845.44396 | E8: 816.44398 | F8: 769.34053 | G8: 798.00672 | H8: 767.16563 | I8: 750.67366 | J8: 888.95095 | K8: 883.73946 | L8: 930.85733 | M8: 1207.2758 | N8: 2003.5997 | O8: 2948.3643 | P8: 3168.8151 | Q8: 3351.5516 | R8: 3749.0302 | S8: 3978.5977 | T8: 4023.5771 | U8: 4180.2153 | V8: 4200.6642 | W8: 4174.1284 | X8: 4181.2546
A9: Tai Tokerau | B9: Targeted Funding for Disadvantage | C9: 0 | D9: 0 | E9: 0 | F9: 0 | G9: 0 | H9: 0 | I9: 0 | J9: 0 | K9: 0 | L9: 0 | M9: 0 | N9: 0 | O9: 0 | P9: 0 | Q9: 0 | R9: 0 | S9: 332.14417 | T9: 659.29702 | U9: 659.54064 | V9: 685.69166 | W9: 703.60782 | X9: 717.57158
A10: Tai Tokerau | B10: Total | C10: 10717.174 | D10: 13034.896 | E10: 13464.093 | F10: 14221.618 | G10: 16969.609 | H10: 19240.206 | I10: 27596.918 | J10: 37385.118 | K10: 40964.097 | L10: 42144.891 | M10: 44259.086 | N10: 47528.828 | O10: 52592.614 | P10: 56812.418 | Q10: 60607.271 | R10: 64710.121 | S10: 66655.56 | T10: 67901.451 | U10: 72640.391 | V10: 79248.222 | W10: 82411.938 | X10: 87216.04
A11: Tāmaki Herenga Manawa | B11: 20 Hours ECE | C11: 0 | D11: 0 | E11: 0 | F11: 0 | G11: 0 | H11: 0 | I11: 31486.271 | J11: 46468.989 | K11: 53257.773 | L11: 58452.289 | M11: 66890.124 | N11: 77263.49 | O11: 88665.798 | P11: 96565.025 | Q11: 101377.56 | R11: 103742.18 | S11: 105505.29 | T11: 107696.1 | U11: 111931.49 | V11: 118692.06 | W11: 117910.09 | X11: 121901.45
A12: Tāmaki Herenga Manawa | B12: Under 2's | C12: 5103.6083 | D12: 5700.6184 | E12: 6341.6405 | F12: 6887.7629 | G12: 8773.7163 | H12: 10272.312 | I12: 12867.582 | J12: 14234.25 | K12: 14878.928 | L12: 15284.463 | M12: 19646.628 | N12: 25011.873 | O12: 30555.726 | P12: 34643.607 | Q12: 38271.667 | R12: 38660.906 | S12: 40971.168 | T12: 43372.236 | U12: 43775.586 | V12: 48771.705 | W12: 51278.441 | X12: 58884.104
A13: Tāmaki Herenga Manawa | B13: 2 and over - non 20 Hours ECE | C13: 17398.168 | D13: 19133.055 | E13: 21115.35 | F13: 23960.51 | G13: 29271.598 | H13: 33640.109 | I13: 19958.4 | J13: 20900.862 | K13: 21861.177 | L13: 22130.632 | M13: 24496.97 | N13: 28001.876 | O13: 31884.443 | P13: 36007.045 | Q13: 39032.129 | R13: 42264.165 | S13: 43962.028 | T13: 47428.866 | U13: 49720.345 | V13: 51343.68 | W13: 54267.272 | X13: 59418.136
A14: Tāmaki Herenga Manawa | B14: Equity | C14: 140.0645 | D14: 282.86198 | E14: 282.88392 | F14: 301.82144 | G14: 324.83772 | H14: 339.7726 | I14: 335.36808 | J14: 407.60971 | K14: 406.41895 | L14: 417.20282 | M14: 494.03113 | N14: 830.20427 | O14: 1375.7754 | P14: 1765.1723 | Q14: 2171.5948 | R14: 2420.0716 | S14: 2518.5561 | T14: 2775.7445 | U14: 2907.4627 | V14: 3049.392 | W14: 3111.8593 | X14: 3182.6089
A15: Tāmaki Herenga Manawa | B15: Targeted Funding for Disadvantage | C15: 0 | D15: 0 | E15: 0 | F15: 0 | G15: 0 | H15: 0 | I15: 0 | J15: 0 | K15: 0 | L15: 0 | M15: 0 | N15: 0 | O15: 0 | P15: 0 | Q15: 0 | R15: 0 | S15: 185.94175 | T15: 360.45928 | U15: 342.01368 | V15: 351.50738 | W15: 371.17138 | X15: 410.79645
A16: Tāmaki Herenga Manawa | B16: Total | C16: 22641.84 | D16: 25116.535 | E16: 27739.875 | F16: 31150.095 | G16: 38370.152 | H16: 44252.194 | I16: 64647.621 | J16: 82011.711 | K16: 90404.296 | L16: 96284.587 | M16: 111527.75 | N16: 131107.44 | O16: 152481.74 | P16: 168980.85 | Q16: 180852.95 | R16: 187087.33 | S16: 193142.99 | T16: 201633.4 | U16: 208676.89 | V16: 222208.35 | W16: 226938.83 | X16: 243797.1
... A88: Total | B88: Total | C88: 302864.04 | D88: 344391.96 | E88: 373238.91 | F88: 411706.92 | G88: 496476.84 | H88: 564286.95 | I88: 817900.71 | J88: 1026788.4 | K88: 1169325 | L88: 1255904 | M88: 1305814.3 | N88: 1388788.3 | O88: 1508694.3 | P88: 1607689.9 | Q88: 1698932.7 | R88: 1753786.4 | S88: 1810524.3 | T88: 1869377.8 | U88: 1962027.7 | V88: 2096777.7 | W88: 2172070.9 | X88: 2316512.2

Sheet EXP9
A1: ='Table Index'!J13 -> Entitlement funding, equity funding and targeted funding for disadvantage by New Zealand Index of Deprivation and programme ($000, GST exclusive) | M1: About the data in this table | P1: Table Index
A3: Click on arrow to select (filter) the information you need
A4: NZDep18 Index of Deprivation 18 | B4: Programme 14 | C4: 2001/02 | D4: 2002/03 | E4: 2003/04 | F4: 2004/05 | G4: 2005/06 | H4: 2006/07 | I4: 2007/08 | J4: 2008/09 | K4: 2009/10 | L4: 2010/11 | M4: 2011/12 | N4: 2012/13 | O4: 2013/14 | P4: 2014/15 | Q4: 2015/16 | R4: 2016/17 | S4: 2017/18 | T4: 2018/19 | U4: 2019/20 | V4: 2020/21 | W4: 2021/22 | X4: 2022/23
A5: NZDep decile 1 | B5: 20 Hours ECE | C5: 0 | D5: 0 | E5: 0 | F5: 0 | G5: 0 | H5: 0 | I5: 18761.704 | J5: 26584.876 | K5: 32683.878 | L5: 38166.961 | M5: 38789.622 | N5: 41129.839 | O5: 45645.767 | P5: 48225.97 | Q5: 51468.637 | R5: 55135.602 | S5: 56705.638 | T5: 59772.299 | U5: 64464.106 | V5: 71558.573 | W5: 74354.684 | X5: 78440.423
A6: NZDep decile 1 | B6: Under 2's | C6: 3000.7421 | D6: 3132.322 | E6: 3835.3735 | F6: 4903.5031 | G6: 5574.9892 | H6: 6591.7593 | I6: 8107.2587 | J6: 9477.8933 | K6: 10625.175 | L6: 11417.365 | M6: 11213.522 | N6: 11213.801 | O6: 12656.948 | P6: 13218.72 | Q6: 14673.817 | R6: 17223.893 | S6: 18140.75 | T6: 18794.892 | U6: 20547.51 | V6: 23928.387 | W6: 26059.198 | X6: 30330.748
A7: NZDep decile 1 | B7: 2 and over - non 20 Hours ECE | C7: 8994.6492 | D7: 9984.5777 | E7: 11328.941 | F7: 12961.448 | G7: 16020.98 | H7: 18800.564 | I7: 10706.018 | J7: 11940.272 | K7: 12811.065 | L7: 12860.589 | M7: 11881.188 | N7: 12186.778 | O7: 13778.297 | P7: 15177.577 | Q7: 16457.689 | R7: 18346.444 | S7: 20169.157 | T7: 21729.729 | U7: 23165.874 | V7: 25790.287 | W7: 28401.172 | X7: 31204.331
A8: NZDep decile 1 | B8: Equity | C8: 13.783893 | D8: 29.157849 | E8: 31.52656 | F8: 31.424133 | G8: 32.51872 | H8: 28.93104 | I8: 32.663049 | J8: 47.70256 | K8: 36.828105 | L8: 40.002348 | M8: 60.048843 | N8: 98.53182 | O8: 235.7345 | P8: 258.25642 | Q8: 279.41782 | R8: 276.13491 | S8: 280.5319 | T8: 276.88006 | U8: 318.71569 | V8: 403.41065 | W8: 431.05107 | X8: 427.64095
A9: NZDep decile 1 | B9: Targeted Funding for Disadvantage | C9: 0 | D9: 0 | E9: 0 | F9: 0 | G9: 0 | H9: 0 | I9: 0 | J9: 0 | K9: 0 | L9: 0 | M9: 0 | N9: 0 | O9: 0 | P9: 0 | Q9: 0 | R9: 0 | S9: 43.385478 | T9: 78.071624 | U9: 68.138959 | V9: 72.85514 | W9: 66.552174 | X9: 48.99696
A10: NZDep decile 1 | B10: Total | C10: 12009.175 | D10: 13146.058 | E10: 15195.841 | F10: 17896.375 | G10: 21628.488 | H10: 25421.254 | I10: 37607.644 | J10: 48050.745 | K10: 56156.947 | L10: 62484.917 | M10: 61944.38 | N10: 64628.949 | O10: 72316.747 | P10: 76880.523 | Q10: 82879.561 | R10: 90982.073 | S10: 95339.462 | T10: 100651.87 | U10: 108564.34 | V10: 121753.51 | W10: 129312.66 | X10: 140452.14
A11: NZDep decile 2 | B11: 20 Hours ECE | C11: 0 | D11: 0 | E11: 0 | F11: 0 | G11: 0 | H11: 0 | I11: 17247.937 | J11: 26512.386 | K11: 31984.219 | L11: 34609.287 | M11: 36731.995 | N11: 38233.919 | O11: 41124.402 | P11: 43710.584 | Q11: 44679.593 | R11: 45150.718 | S11: 47369.516 | T11: 49193.636 | U11: 52337.49 | V11: 58219.148 | W11: 60650.082 | X11: 64726.029
A12: NZDep decile 2 | B12: Under 2's | C12: 5044.092 | D12: 4984.5048 | E12: 5512.9793 | F12: 5977.6907 | G12: 7369.515 | H12: 8592.2285 | I12: 9683.4182 | J12: 10532.208 | K12: 11571.965 | L12: 11823.886 | M12: 12213.153 | N12: 12579.002 | O12: 13903.819 | P12: 14031.159 | Q12: 15380.772 | R12: 15842.51 | S12: 17524.358 | T12: 18639.058 | U12: 18633.047 | V12: 20858.225 | W12: 22541.923 | X12: 26781.277
A13: NZDep decile 2 | B13: 2 and over - non 20 Hours ECE | C13: 9928.7318 | D13: 10877.826 | E13: 11653.525 | F13: 12876.694 | G13: 16068.656 | H13: 18830.448 | I13: 11665.851 | J13: 12242.875 | K13: 12281.022 | L13: 11953.72 | M13: 12127.518 | N13: 12866.168 | O13: 13655.937 | P13: 14578.998 | Q13: 15373.219 | R13: 16556.982 | S13: 17765.089 | T13: 18886.995 | U13: 19817.947 | V13: 20919.827 | W13: 23069.446 | X13: 25677.19
A14: NZDep decile 2 | B14: Equity | C14: 31.894107 | D14: 63.515067 | E14: 57.603253 | F14: 52.650933 | G14: 45.902507 | H14: 40.7212 | I14: 46.204311 | J14: 58.656689 | K14: 58.470878 | L14: 60.762285 | M14: 114.40749 | N14: 195.45933 | O14: 288.54452 | P14: 289.32262 | Q14: 354.44823 | R14: 341.198 | S14: 363.25134 | T14: 357.94283 | U14: 360.23755 | V14: 355.74303 | W14: 326.29015 | X14: 324.5426
A15: NZDep decile 2 | B15: Targeted Funding for Disadvantage | C15: 0 | D15: 0 | E15: 0 | F15: 0 | G15: 0 | H15: 0 | I15: 0 | J15: 0 | K15: 0 | L15: 0 | M15: 0 | N15: 0 | O15: 0 | P15: 0 | Q15: 0 | R15: 0 | S15: 66.659846 | T15: 120.32628 | U15: 99.30584 | V15: 114.697 | W15: 123.23739 | X15: 141.01126
A16: NZDep decile 2 | B16: Total | C16: 15004.718 | D16: 15925.845 | E16: 17224.107 | F16: 18907.035 | G16: 23484.074 | H16: 27463.398 | I16: 38643.411 | J16: 49346.125 | K16: 55895.677 | L16: 58447.655 | M16: 61187.073 | N16: 63874.548 | O16: 68972.703 | P16: 72610.064 | Q16: 75788.033 | R16: 77891.408 | S16: 83088.874 | T16: 87197.959 | U16: 91248.027 | V16: 100467.64 | W16: 106710.98 | X16: 117650.05
... A76: Total | B76: Total | C76: 302864.04 | D76: 344391.96 | E76: 373238.91 | F76: 411706.92 | G76: 496476.84 | H76: 564286.95 | I76: 817900.71 | J76: 1026788.4 | K76: 1169325 | L76: 1255904 | M76: 1305814.3 | N76: 1388788.3 | O76: 1508694.3 | P76: 1607689.9 | Q76: 1698932.7 | R76: 1753786.4 | S76: 1810524.3 | T76: 1869377.8 | U76: 1962027.7 | V76: 2096777.7 | W76: 2172070.9 | X76: 2316512.2

Sheet EXP10
A1: ='Table Index'!J14 -> Entitlement funding, equity funding and targeted funding for disadvantage per funded child hour by service type and programme ($, GST exclusive) | M1: About the data in this table | P1: Table Index
A2: Note that for this table, Education & Care services includes both Casual Education & Care and Hospital-based services. Kōhanga reo includes unlicensed Kōhanga reo up to 2008.
A4: Click on arrow to select (filter) the information you need
A5: Service type 13 | B5: Programme 14 | C5: 2001/02 | D5: 2002/03 | E5: 2003/04 | F5: 2004/05 | G5: 2005/06 | H5: 2006/07 | I5: 2007/08 | J5: 2008/09 | K5: 2009/10 | L5: 2010/11 | M5: 2011/12 | N5: 2012/13 | O5: 2013/14 | P5: 2014/15 | Q5: 2015/16 | R5: 2016/17 | S5: 2017/18 | T5: 2018/19 | U5: 2019/20 | V5: 2020/21 | W5: 2021/22 | X5: 2022/23
A6: Education & Care | B6: 20 Hours ECE | I6: 8.6090122 | J6: 9.5223692 | K6: 9.8612123 | L6: 9.7718978 | M6: 9.7022673 | N6: 9.7402819 | O6: 9.8237377 | P6: 9.9164887 | Q6: 9.9212882 | R6: 9.9209794 | S6: 9.921886 | T6: 9.9973205 | U6: 10.174373 | V6: 10.608682 | W6: 11.005206 | X6: 11.749516
A7: Education & Care | B7: Under 2's | C7: 5.153482 | D7: 5.2797169 | E7: 5.4800807 | F7: 5.8439762 | G7: 7.0566641 | H7: 7.859665 | I7: 8.6959502 | J7: 9.3450118 | K7: 10.168443 | L7: 10.176273 | M7: 10.23822 | N7: 10.305789 | O7: 10.401236 | P7: 10.502144 | Q7: 10.506286 | R7: 10.506643 | S7: 10.506363 | T7: 10.589117 | U7: 10.780151 | V7: 11.218507 | W7: 11.598372 | X7: 12.386566
A8: Education & Care | B8: 2 and over - non 20 Hours ECE | C8: 2.5762444 | D8: 2.6439955 | E8: 2.742875 | F8: 2.9488949 | G8: 3.6764487 | H8: 4.1446084 | I8: 4.4728399 | J8: 5.3775463 | K8: 5.6925357 | L8: 5.6539807 | M8: 5.6174017 | N8: 5.6707453 | O8: 5.7284061 | P8: 5.7891654 | Q8: 5.794153 | R8: 5.7947677 | S8: 5.7951527 | T8: 5.8404725 | U8: 5.9492583 | V8: 6.2112421 | W8: 6.4893991 | X8: 6.9284243
A9: Education & Care | B9: Equity | C9: 0.021046981 | D9: 0.041034953 | E9: 0.039934894 | F9: 0.039845042 | G9: 0.040724265 | H9: 0.042486272 | I9: 0.040118756 | J9: 0.042816593 | K9: 0.040858411 | L9: 0.040665509 | M9: 0.072295731 | N9: 0.12055321 | O9: 0.17608373 | P9: 0.1868137 | Q9: 0.1935846 | R9: 0.19839233 | S9: 0.20075867 | T9: 0.19716986 | U9: 0.20077237 | V9: 0.2011694 | W9: 0.2035383 | X9: 0.20369382
A10: Education & Care | B10: Targeted Funding for Disadvantage | C10: 0 | D10: 0 | E10: 0 | F10: 0 | G10: 0 | H10: 0 | I10: 0 | J10: 0 | K10: 0 | L10: 0 | M10: 0 | N10: 0 | O10: 0 | P10: 0 | Q10: 0 | R10: 0 | S10: 0.019187764 | T10: 0.036355603 | U10: 0.036148141 | V10: 0.037198404 | W10: 0.036880006 | X10: 0.036842575
A11: Education & Care | B11: Total | C11: 3.1389303 | D11: 3.222765 | E11: 3.3538629 | F11: 3.6076603 | G11: 4.4507213 | H11: 4.9832651 | I11: 6.6969196 | J11: 7.8942992 | K11: 8.414454 | L11: 8.4356366 | M11: 8.4788975 | N11: 8.589473 | O11: 8.7347631 | P11: 8.8192354 | Q11: 8.8290174 | R11: 8.7891523 | S11: 8.7942223 | T11: 8.8519507 | U11: 9.0076277 | V11: 9.4298174 | W11: 9.7650793 | X11: 10.414911
A12: Home-based | B12: 20 Hours ECE | I12: 7.3933418 | J12: 7.5789178 | K12: 7.6804467 | L12: 7.7042133 | M12: 7.7584315 | N12: 7.7470787 | O12: 7.7700747 | P12: 7.7976068 | Q12: 7.7681616 | R12: 7.7670932 | S12: 7.7650005 | T12: 7.7736265 | U12: 7.8467025 | V12: 8.0934063 | W12: 8.3897679 | X12: 8.6940259
A13: Home-based | B13: Under 2's | C13: 5.0976776 | D13: 5.1325266 | E13: 5.2410049 | F13: 5.4254808 | G13: 5.7082102 | H13: 6.0213098 | I13: 6.3742049 | J13: 6.503098 | K13: 6.537077 | L13: 6.5563335 | M13: 6.6001397 | N13: 6.5735105 | O13: 6.555125 | P13: 6.5586524 | Q13: 6.5394486 | R13: 6.5480301 | S13: 6.5477756 | T13: 6.5306069 | U13: 6.5833179 | V13: 6.7561209 | W13: 6.9958306 | X13: 7.3376752
A14: Home-based | B14: 2 and over - non 20 Hours ECE | C14: 2.552839 | D14: 2.5730945 | E14: 2.6259178 | F14: 2.736297 | G14: 2.9675659 | H14: 3.1748864 | I14: 3.3487688 | J14: 3.4714263 | K14: 3.5231136 | L14: 3.5368873 | M14: 3.5566307 | N14: 3.5506253 | O14: 3.5466632 | P14: 3.5515967 | Q14: 3.5380421 | R14: 3.5377232 | S14: 3.5343637 | T14: 3.5265009 | U14: 3.5532162 | V14: 3.6311215 | W14: 3.7605734 | X14: 3.932066
A15: Home-based | B15: Equity | C15: 0.0096664847 | D15: 0.015177301 | E15: 0.013632498 | F15: 0.010661901 | G15: 0.0097014166 | H15: 0.0088370627 | I15: 0.011409723 | J15: 0.014197354 | K15: 0.012137395 | L15: 0.010861553 | M15: 0.039880409 | N15: 0.086704719 | O15: 0.15899005 | P15: 0.18204505 | Q15: 0.20015918 | R15: 0.24164131 | S15: 0.28592213 | T15: 0.29856529 | U15: 0.32309085 | V15: 0.30782608 | W15: 0.30317713 | X15: 0.30257853
A16: Home-based | B16: Targeted Funding for Disadvantage | C16: 0 | D16: 0 | E16: 0 | F16: 0 | G16: 0 | H16: 0 | I16: 0 | J16: 0 | K16: 0 | L16: 0 | M16: 0 | N16: 0 | O16: 0 | P16: 0 | Q16: 0 | R16: 0 | S16: 0.023034422 | T16: 0.045404092 | U16: 0.049881675 | V16: 0.054215105 | W16: 0.054547061 | X16: 0.050765283
A17: Home-based | B17: Total | C17: 3.5188427 | D17: 3.5572113 | E17: 3.6236653 | F17: 3.7524152 | G17: 3.9979181 | H17: 4.2320852 | I17: 5.3935205 | J17: 5.6712181 | K17: 5.7677384 | L17: 5.7714126 | M17: 5.8211972 | N17: 5.8464855 | O17: 5.9275455 | P17: 5.9182927 | Q17: 5.8668498 | R17: 5.8649975 | S17: 5.8813882 | T17: 5.8522957 | U17: 5.9009633 | V17: 6.0380237 | W17: 6.2775197 | X17: 6.5022157
A18: Kindergarten | B18: 20 Hours ECE | I18: 6.519544 | J18: 8.1055508 | K18: 9.1224205 | L18: 9.4342939 | M18: 9.4172288 | N18: 9.5716568 | O18: 9.925618 | P18: 10.149953 | Q18: 10.249329 | R18: 10.400093 | S18: 10.520802 | T18: 10.602407 | U18: 11.149175 | V18: 12.078578 | W18: 12.822386 | X18: 13.29607
A19: Kindergarten | B19: Under 2's | G19: 8.4266667 | H19: 9.2048775 | I19: 10.265803 | J19: 10.453109 | K19: 12.245916 | L19: 10.910766 | M19: 10.513043 | N19: 10.519852 | O19: 10.660676 | P19: 10.812894 | Q19: 10.963916 | R19: 11.091935 | S19: 11.156643 | T19: 11.24672 | U19: 11.828732 | V19: 12.923377 | W19: 13.591447 | X19: 14.265408
A20: Kindergarten | B20: 2 and over - non 20 Hours ECE | C20: 3.1678915 | D20: 3.3459744 | E20: 3.5327049 | F20: 3.9540032 | G20: 4.3554145 | H20: 4.7715825 | I20: 5.0016851 | J20: 5.9542886 | K20: 6.2799958 | L20: 6.0645938 | M20: 5.8150458 | N20: 5.8290129 | O20: 5.9301514 | P20: 6.0156748 | Q20: 6.0632981 | R20: 6.1494537 | S20: 6.2168695 | T20: 6.2636759 | U20: 6.587252 | V20: 7.2448338 | W20: 7.8045958 | X20: 8.1619804
A21: Kindergarten | B21: Equity | C21: 0.042928421 | D21: 0.083933449 | E21: 0.084081455 | F21: 0.08502926 | G21: 0.086704799 | H21: 0.088929827 | I21: 0.087233684 | J21: 0.097800534 | K21: 0.099231115 | L21: 0.099065532 | M21: 0.1027046 | N21: 0.17800879 | O21: 0.25302372 | P21: 0.25971295 | Q21: 0.2594373 | R21: 0.2633357 | S21: 0.269053 | T21: 0.26641116 | U21: 0.27466174 | V21: 0.27671696 | W21: 0.28033096 | X21: 0.29082555
A22: Kindergarten | B22: Targeted Funding for Disadvantage | C22: 0 | D22: 0 | E22: 0 | F22: 0 | G22: 0 | H22: 0 | I22: 0 | J22: 0 | K22: 0 | L22: 0 | M22: 0 | N22: 0 | O22: 0 | P22: 0 | Q22: 0 | R22: 0 | S22: 0.0295372 | T22: 0.056685125 | U22: 0.053609174 | V22: 0.055051541 | W22: 0.05848054 | X22: 0.060999079
A23: Kindergarten | B23: Total | C23: 3.2108199 | D23: 3.4299078 | E23: 3.6167864 | F23: 4.0390325 | G23: 4.4424136 | H23: 4.8611287 | I23: 6.4376063 | J23: 7.9359264 | K23: 8.8646139 | L23: 9.1040554 | M23: 9.0412025 | N23: 9.1910351 | O23: 9.4974967 | P23: 9.6176963 | Q23: 9.6014934 | R23: 9.653769 | S23: 9.7310164 | T23: 9.7911796 | U23: 10.271589 | V23: 11.089432 | W23: 11.741476 | X23: 12.099879
A24: Kōhanga reo | B24: 20 Hours ECE | I24: 6.746753 | J24: 6.9270057 | K24: 6.9789319 | L24: 6.9907465 | M24: 7.0423197 | N24: 7.0406045 | O24: 7.0852798 | P24: 7.1605541 | Q24: 7.1658981 | R24: 7.1574415 | S24: 7.1750892 | T24: 7.2329897 | U24: 9.3805666 | V24: 10.862327 | W24: 11.016464 | X24: 11.282013
A25: Kōhanga reo | B25: Under 2's | C25: 4.9578022 | D25: 5.0937402 | E25: 5.2275274 | F25: 5.3577758 | G25: 5.549997 | H25: 5.8034709 | I25: 6.6133404 | J25: 7.0202913 | K25: 7.1422097 | L25: 7.2632753 | M25: 7.3635406 | N25: 7.3926741 | O25: 7.4549697 | P25: 7.543337 | Q25: 7.5484906 | R25: 7.5417877 | S25: 7.5726644 | T25: 7.6391252 | U25: 9.8051285 | V25: 11.339283 | W25: 11.444203 | X25: 11.651808
A26: Kōhanga reo | B26: 2 and over - non 20 Hours ECE | C26: 2.4934726 | D26: 2.5553154 | E26: 2.6204434 | F26: 2.6926482 | G26: 2.7816478 | H26: 2.9107514 | I26: 3.3167554 | J26: 3.5094317 | K26: 3.580495 | L26: 3.6397169 | M26: 3.6958932 | N26: 3.7073762 | O26: 3.7431777 | P26: 3.7851115 | Q26: 3.7897301 | R26: 3.7852535 | S26: 3.803322 | T26: 3.8345481 | U26: 5.9219773 | V26: 7.4307948 | W26: 7.4695367 | X26: 7.5795308
A27: Kōhanga reo | B27: Equity | C27: 0.29596504 | D27: 0.38409503 | E27: 0.38323993 | F27: 0.38474259 | G27: 0.39031922 | H27: 0.39495055 | I27: 0.40015346 | J27: 0.46769499 | K27: 0.46525839 | L27: 0.45876915 | M27: 0.46025954 | N27: 0.76878766 | O27: 1.0406127 | P27: 1.0427071 | Q27: 1.0582403 | R27: 1.0642903 | S27: 1.0664605 | T27: 1.0624921 | U27: 1.0854609 | V27: 1.0909272 | W27: 1.1125325 | X27: 1.1288419
A28: Kōhanga reo | B28: Targeted Funding for Disadvantage | C28: 0 | D28: 0 | E28: 0 | F28: 0 | G28: 0 | H28: 0 | I28: 0 | J28: 0 | K28: 0 | L28: 0 | M28: 0 | N28: 0 | O28: 0 | P28: 0 | Q28: 0 | R28: 0 | S28: 0.06530509 | T28: 0.12888915 | U28: 0.12768097 | V28: 0.1382622 | W28: 0.14488122 | X28: 0.13748233
A29: Kōhanga reo | B29: Total | C29: 3.3381219 | D29: 3.4940738 | E29: 3.5605536 | F29: 3.6554465 | G29: 3.778596 | H29: 3.9716947 | I29: 4.7048321 | J29: 5.2693786 | K29: 5.4232482 | L29: 5.6950351 | M29: 5.8344524 | N29: 6.2081472 | O29: 6.5878718 | P29: 6.666368 | Q29: 6.7156513 | R29: 6.7310981 | S29: 6.8321927 | T29: 6.9362922 | U29: 9.0407892 | V29: 10.576301 | W29: 10.493175 | X29: 10.888952
A30: Playcentre | B30: 20 Hours ECE | L30: 4.2712932 | M30: 4.466717 | N30: 4.4538277 | O30: 4.4667412 | P30: 4.5281019 | Q30: 4.5435597 | R30: 4.5593304 | S30: 4.5560255 | T30: 4.5910792 | U30: 4.6704192 | V30: 5.0003744 | W30: 4.9020047 | X30: 5.2373752
A31: Playcentre | B31: Under 2's | C31: 5.0748043 | D31: 5.182159 | E31: 5.2868278 | F31: 5.4084257 | G31: 5.5704873 | H31: 6.0742862 | I31: 6.5657072 | J31: 6.9253052 | K31: 6.9846033 | L31: 7.0749472 | M31: 7.1141779 | N31: 7.0623853 | O31: 7.0573618 | P31: 7.1228719 | Q31: 7.120599 | R31: 7.1194735 | S31: 7.1135004 | T31: 7.1604827 | U31: 7.2932439 | V31: 7.8036625 | W31: 7.6704445 | X31: 8.1031093
A32: Playcentre | B32: 2 and over - non 20 Hours ECE | C32: 2.5414346 | D32: 2.598372 | E32: 2.6431627 | F32: 2.7089422 | G32: 2.7919011 | H32: 3.0419031 | I32: 3.2971647 | J32: 3.4732521 | K32: 3.5160223 | L32: 3.5542366 | M32: 3.5935363 | N32: 3.5845181 | O32: 3.5802418 | P32: 3.609864 | Q32: 3.604888 | R32: 3.6040018 | S32: 3.6076339 | T32: 3.6347573 | U32: 3.6993066 | V32: 3.9498942 | W32: 3.8644638 | X32: 4.0993953
A33: Playcentre | B33: Equity | C33: 0.048287664 | D33: 0.088137801 | E33: 0.084855385 | F33: 0.090642703 | G33: 0.095723889 | H33: 0.098659038 | I33: 0.093807479 | J33: 0.10088894 | K33: 0.10161704 | L33: 0.10134342 | M33: 0.10437268 | N33: 0.13164427 | O33: 0.15416173 | P33: 0.15735278 | Q33: 0.15035265 | R33: 0.14635323 | S33: 0.1443316 | T33: 0.14288167 | U33: 0.14201474 | V33: 0.13512669 | W33: 0.13299043 | X33: 0.13932691
A34: Playcentre | B34: Targeted Funding for Disadvantage | C34: 0 | D34: 0 | E34: 0 | F34: 0 | G34: 0 | H34: 0 | I34: 0 | J34: 0 | K34: 0 | L34: 0 | M34: 0 | N34: 0 | O34: 0 | P34: 0 | Q34: 0 | R34: 0 | S34: 0.0010986025 | T34: 0.0033066418 | U34: 0.0054769228 | V34: 0.0063266958 | W34: 0.006986305 | X34: 0.006309854
A35: Playcentre | B35: Total | C35: 3.2192874 | D35: 3.3358489 | E35: 3.3770172 | F35: 3.4711065 | G35: 3.6251799 | H35: 3.9817551 | I35: 4.3589166 | J35: 4.6512794 | K35: 4.7058682 | L35: 4.8313376 | M35: 4.9542407 | N35: 5.0213555 | O35: 5.0809211 | P35: 5.2076772 | Q35: 5.2501061 | R35: 5.2911322 | S35: 5.2688469 | T35: 5.3376511 | U35: 5.4873715 | V35: 5.9398392 | W35: 5.8916994 | X35: 6.3240717
A36: Total | B36: 20 Hours ECE | I36: 7.6481389 | J36: 8.8758823 | K36: 9.4360739 | L36: 9.4465298 | M36: 9.3979001 | N36: 9.4678945 | O36: 9.6149914 | P36: 9.7334845 | Q36: 9.7547013 | R36: 9.7855422 | S36: 9.8221195 | T36: 9.906903 | U36: 10.209697 | V36: 10.775285 | W36: 11.234698 | X36: 11.907835
A37: Total | B37: Under 2's | C37: 5.118562 | D37: 5.2228817 | E37: 5.3978233 | F37: 5.697 | G37: 6.6065909 | H37: 7.2696339 | I37: 8.0180439 | J37: 8.5380394 | K37: 9.0911267 | L37: 9.0861958 | M37: 9.1631898 | N37: 9.2164472 | O37: 9.282339 | P37: 9.2768902 | Q37: 9.2428356 | R37: 9.3275986 | S37: 9.3642399 | T37: 9.4987181 | U37: 9.8936739 | V37: 10.500033 | W37: 10.889875 | X37: 11.685426
A38: Total | B38: 2 and over - non 20 Hours ECE | C38: 2.7389345 | D38: 2.8184366 | E38: 2.9308143 | F38: 3.1639145 | G38: 3.696513 | H38: 4.1029699 | I38: 4.2010475 | J38: 4.9021145 | K38: 5.1475772 | L38: 5.1353563 | M38: 5.1155665 | N38: 5.1797755 | O38: 5.2604048 | P38: 5.3235968 | Q38: 5.331188 | R38: 5.3630102 | S38: 5.3821937 | T38: 5.4403753 | U38: 5.7104189 | V38: 6.1135174 | W38: 6.4274197 | X38: 6.8424631
A39: Total | B39: Equity | C39: 0.050663477 | D39: 0.0935057 | E39: 0.089973049 | F39: 0.086861312 | G39: 0.085764196 | H39: 0.083997416 | I39: 0.078110933 | J39: 0.085082938 | K39: 0.081088002 | L39: 0.078664884 | M39: 0.10167444 | N39: 0.16898393 | O39: 0.23873868 | P39: 0.24553046 | Q39: 0.24945822 | R39: 0.25571183 | S39: 0.26124895 | T39: 0.25799496 | U39: 0.26395828 | V39: 0.26073391 | W39: 0.26239115 | X39: 0.26482808
A40: Total | B40: Targeted Funding for Disadvantage | C40: 0 | D40: 0 | E40: 0 | F40: 0 | G40: 0 | H40: 0 | I40: 0 | J40: 0 | K40: 0 | L40: 0 | M40: 0 | N40: 0 | O40: 0 | P40: 0 | Q40: 0 | R40: 0 | S40: 0.023000092 | T40: 0.04398088 | U40: 0.043713002 | V40: 0.045247193 | W40: 0.045618511 | X40: 0.045270838
A41: Total | B41: Total | C41: 3.2051286 | D41: 3.3308951 | E41: 3.4569731 | F41: 3.7115714 | G41: 4.3213876 | H41: 4.7784772 | I41: 6.3149153 | J41: 7.4158631 | K41: 7.9256169 | L41: 7.9986924 | M41: 8.0437358 | N41: 8.1849709 | O41: 8.3725531 | P41: 8.4416295 | Q41: 8.4319761 | R41: 8.4284143 | S41: 8.4568308 | T41: 8.5316829 | U41: 8.8424921 | V41: 9.3905146 | W41: 9.7571172 | X41: 10.359926

Sheet EXP11
A1: ='Table Index'!J15 -> Entitlement funding, equity funding and targeted funding for disadvantage per funded child hour by Regional Council and programme ($, GST exclusive) | M1: About the data in this table | P1: Table Index
A3: Click on arrow to select (filter) the information you need
A4: Regional Council 15 | B4: Programme 14 | C4: 2001/02 | D4: 2002/03 | E4: 2003/04 | F4: 2004/05 | G4: 2005/06 | H4: 2006/07 | I4: 2007/08 | J4: 2008/09 | K4: 2009/10 | L4: 2010/11 | M4: 2011/12 | N4: 2012/13 | O4: 2013/14 | P4: 2014/15 | Q4: 2015/16 | R4: 2016/17 | S4: 2017/18 | T4: 2018/19 | U4: 2019/20 | V4: 2020/21 | W4: 2021/22 | X4: 2022/23
A5: Area outside regions | B5: 20 Hours ECE | I5: 6.5985185 | J5: 6.9688889 | K5: 7.004057 | L5: 7.1897542 | M5: 7.1043478 | N5: 7.1043478 | O5: 7.1478261 | P5: 7.2173913 | Q5: 7.2173913 | R5: 7.2173913 | S5: 7.2173913 | T5: 7.2811099 | U5: 9.3869994 | V5: 10.939244 | W5: 11.051736 | X5: 11.348585
A6: Area outside regions | B6: Under 2's | C6: 4.7377778 | D6: 4.8533333 | E6: 4.9511111 | F6: 5.0666667 | G6: 5.2088889 | H6: 5.4044444 | I6: 6.2376465 | J6: 7.4044444 | K6: 7.4663233 | L6: 7.5043478 | M6: 7.5652174 | N6: 7.5652174 | O6: 7.6173913 | P6: 7.6869565 | Q6: 7.6869565 | R6: 7.6869565 | S6: 7.6869565 | T6: 7.7521437 | U6: 9.9033692 | V6: 11.434301 | W6: 11.564251 | X6: 11.770709
A7: Area outside regions | B7: 2 and over - non 20 Hours ECE | C7: 2.3733333 | D7: 2.4355556 | E7: 2.48 | F7: 2.5422222 | G7: 2.6133333 | H7: 2.7111111 | I7: 3.1228608 | J7: 3.7155556 | K7: 3.7507713 | L7: 3.7163718 | M7: 3.8 | N7: 3.8 | O7: 3.826087 | P7: 3.8608696 | Q7: 3.8608696 | R7: 3.8608696 | S7: 3.8608696 | T7: 3.8907714 | U7: 5.9641411 | V7: 7.4578175 | W7: 7.5424997 | X7: 7.6514905
A8: Area outside regions | B8: Equity | C8: 0.13448509 | D8: 0.16482433 | E8: 0.16626096 | F8: 0.17435222 | G8: 0.18218322 | H8: 0.22534412 | I8: 0.24312014 | J8: 0.21017632 | K8: 0.25411888 | L8: 0.264117 | M8: 0.26584664 | N8: 0.34473677 | O8: 0.32793294 | P8: 0.2883174 | Q8: 0.30068605 | R8: 0.3298844 | S8: 0.3884021 | T8: 0.31239309 | U8: 0.333665 | V8: 0.30250444 | W8: 0.29864828 | X8: 0.30723399
A9: Area outside regions | B9: Targeted Funding for Disadvantage | C9: 0 | D9: 0 | E9: 0 | F9: 0 | G9: 0 | H9: 0 | I9: 0 | J9: 0 | K9: 0 | L9: 0 | M9: 0 | N9: 0 | O9: 0 | P9: 0 | Q9: 0 | R9: 0 | S9: 0 | T9: 0.019178026 | U9: 0.040602502 | V9: 0 | W9: 0.023355879 | X9: 0.082177216
A10: Area outside regions | B10: Total | C10: 3.1944444 | D10: 3.2429374 | E10: 3.31512 | F10: 3.3015371 | G10: 3.5211197 | H10: 3.7551185 | I10: 4.5406178 | J10: 6.0547439 | K10: 6.0285561 | L10: 6.1045364 | M10: 6.1066949 | N10: 5.8473024 | O10: 5.7608474 | P10: 5.8619029 | Q10: 6.0152367 | R10: 5.80314 | S10: 5.7042887 | T10: 6.1372761 | U10: 8.4083844 | V10: 9.7786129 | W10: 8.4758562 | X10: 9.559006
A11: Auckland Region | B11: 20 Hours ECE | I11: 7.5724267 | J11: 8.6371176 | K11: 9.1708127 | L11: 9.271223 | M11: 9.309831 | N11: 9.4059436 | O11: 9.6455847 | P11: 9.7858199 | Q11: 9.7957827 | R11: 9.7995795 | S11: 9.8236538 | T11: 9.9052947 | U11: 10.150929 | V11: 10.656065 | W11: 11.10647 | X11: 11.814699
A12: Auckland Region | B12: Under 2's | C12: 5.0530154 | D12: 5.1537502 | E12: 5.3420891 | F12: 5.6565352 | G12: 6.5106793 | H12: 7.2221804 | I12: 8.0746772 | J12: 8.7495174 | K12: 9.4339225 | L12: 9.4837526 | M12: 9.5480408 | N12: 9.5333432 | O12: 9.4911526 | P12: 9.251935 | Q12: 9.1441855 | R12: 9.2762157 | S12: 9.2676968 | T12: 9.3633399 | U12: 9.7139372 | V12: 10.300121 | W12: 10.664299 | X12: 11.513708
A13: Auckland Region | B13: 2 and over - non 20 Hours ECE | C13: 2.6765884 | D13: 2.7533125 | E13: 2.866035 | F13: 3.0884019 | G13: 3.6077473 | H13: 4.0268262 | I13: 4.2324168 | J13: 5.0613841 | K13: 5.3647214 | L13: 5.3417934 | M13: 5.3340136 | N13: 5.3873219 | O13: 5.4419624 | P13: 5.440421 | Q13: 5.3768251 | R13: 5.3962385 | S13: 5.3864593 | T13: 5.4357821 | U13: 5.6233903 | V13: 5.948133 | W13: 6.2509074 | X13: 6.6714602
A14: Auckland Region | B14: Equity | C14: 0.036349286 | D14: 0.069579101 | E14: 0.066964082 | F14: 0.066545748 | G14: 0.06581213 | H14: 0.065496917 | I14: 0.062468214 | J14: 0.069036806 | K14: 0.065663506 | L14: 0.065385717 | M14: 0.095213101 | N14: 0.16079854 | O14: 0.23479712 | P14: 0.24252743 | Q14: 0.25114077 | R14: 0.26588419 | S14: 0.28104612 | T14: 0.28024063 | U14: 0.28706382 | V14: 0.28284017 | W14: 0.29046001 | X14: 0.29117077
A15: Auckland Region | B15: Targeted Funding for Disadvantage | C15: 0 | D15: 0 | E15: 0 | F15: 0 | G15: 0 | H15: 0 | I15: 0 | J15: 0 | K15: 0 | L15: 0 | M15: 0 | N15: 0 | O15: 0 | P15: 0 | Q15: 0 | R15: 0 | S15: 0.018433109 | T15: 0.034692461 | U15: 0.034418657 | V15: 0.035294013 | W15: 0.036425664 | X15: 0.03784853
A16: Auckland Region | B16: Total | C16: 3.1329685 | D16: 3.239577 | E16: 3.3729243 | F16: 3.6159042 | G16: 4.210046 | H16: 4.6890216 | I16: 6.2216457 | J16: 7.3726792 | K16: 7.9205439 | L16: 8.0282509 | M16: 8.1236761 | N16: 8.2711518 | O16: 8.487834 | P16: 8.5015011 | Q16: 8.4265042 | R16: 8.3988414 | S16: 8.4178181 | T16: 8.470919 | U16: 8.7189979 | V16: 9.2119706 | W16: 9.5652091 | X16: 10.170734
A17: Bay of Plenty Region | B17: 20 Hours ECE | I17: 7.7986353 | J17: 8.8793402 | K17: 9.3974614 | L17: 9.3138388 | M17: 9.2231268 | N17: 9.2753981 | O17: 9.3662545 | P17: 9.4940696 | Q17: 9.5254435 | R17: 9.5646088 | S17: 9.6015233 | T17: 9.7002152 | U17: 10.090435 | V17: 10.699343 | W17: 11.148167 | X17: 11.788858
A18: Bay of Plenty Region | B18: Under 2's | C18: 5.0919438 | D18: 5.2234941 | E18: 5.3775304 | F18: 5.6179423 | G18: 6.3425236 | H18: 6.8584094 | I18: 7.5061472 | J18: 7.9662339 | K18: 8.4922293 | L18: 8.4954828 | M18: 8.5154938 | N18: 8.4987729 | O18: 8.6273615 | P18: 8.8414141 | Q18: 8.9848415 | R18: 9.0804479 | S18: 9.1264377 | T18: 9.2940774 | U18: 9.8743693 | V18: 10.632997 | W18: 11.024891 | X18: 11.690168
A19: Bay of Plenty Region | B19: 2 and over - non 20 Hours ECE | C19: 2.680183 | D19: 2.751591 | E19: 2.855981 | F19: 3.0447412 | G19: 3.4851533 | H19: 3.8403422 | I19: 3.9377496 | J19: 4.5461883 | K19: 4.7718633 | L19: 4.8344342 | M19: 4.8257889 | N19: 4.8563053 | O19: 4.9450011 | P19: 5.0444889 | Q19: 5.1441046 | R19: 5.1798368 | S19: 5.206435 | T19: 5.2594315 | U19: 5.7100488 | V19: 6.2113278 | W19: 6.531424 | X19: 6.8874204
A20: Bay of Plenty Region | B20: Equity | C20: 0.085743537 | D20: 0.14955394 | E20: 0.14479202 | F20: 0.13621165 | G20: 0.13289541 | H20: 0.12801428 | I20: 0.11872887 | J20: 0.13695614 | K20: 0.13342151 | L20: 0.12607444 | M20: 0.15614369 | N20: 0.26689462 | O20: 0.37300165 | P20: 0.37211307 | Q20: 0.37190263 | R20: 0.37957298 | S20: 0.3840907 | T20: 0.37164097 | U20: 0.37815345 | V20: 0.37349764 | W20: 0.36940772 | X20: 0.37540579
A21: Bay of Plenty Region | B21: Targeted Funding for Disadvantage | C21: 0 | D21: 0 | E21: 0 | F21: 0 | G21: 0 | H21: 0 | I21: 0 | J21: 0 | K21: 0 | L21: 0 | M21: 0 | N21: 0 | O21: 0 | P21: 0 | Q21: 0 | R21: 0 | S21: 0.034545666 | T21: 0.067308276 | U21: 0.066417656 | V21: 0.066253665 | W21: 0.064609915 | X21: 0.059935419
A22: Bay of Plenty Region | B22: Total | C22: 3.2429879 | D22: 3.3832398 | E22: 3.4916011 | F22: 3.7105177 | G22: 4.2074348 | H22: 4.5864289 | I22: 6.0451346 | J22: 7.0913987 | K22: 7.5586581 | L22: 7.6168112 | M22: 7.654905 | N22: 7.8011813 | O22: 8.0094471 | P22: 8.1257258 | Q22: 8.2052699 | R22: 8.22286 | S22: 8.2817417 | T22: 8.382181 | U22: 8.8327632 | V22: 9.460332 | W22: 9.8208644 | X22: 10.413329
A23: Canterbury Region | B23: 20 Hours ECE | I23: 7.8735672 | J23: 8.9529128 | K23: 9.477491 | L23: 9.6134495 | M23: 9.5801455 | N23: 9.6651924 | O23: 9.7697135 | P23: 9.8777296 | Q23: 9.8962314 | R23: 9.9253138 | S23: 9.9478288 | T23: 10.036485 | U23: 10.272294 | V23: 10.797912 | W23: 11.239335 | X23: 11.953948
A24: Canterbury Region | B24: Under 2's | C24: 5.3167621 | D24: 5.4190176 | E24: 5.5980317 | F24: 5.9482067 | G24: 7.2102881 | H24: 7.9165448 | I24: 8.6833468 | J24: 9.2003627 | K24: 9.7907128 | L24: 9.6496442 | M24: 9.6403893 | N24: 9.7305011 | O24: 9.8609243 | P24: 9.966877 | Q24: 9.9263811 | R24: 9.9019792 | S24: 9.9179019 | T24: 10.069238 | U24: 10.304153 | V24: 10.794184 | W24: 11.204924 | X24: 12.019251
A25: Canterbury Region | B25: 2 and over - non 20 Hours ECE | C25: 2.8034112 | D25: 2.8908374 | E25: 3.0108063 | F25: 3.2745813 | G25: 3.9667357 | H25: 4.4144824 | I25: 4.5679635 | J25: 5.3936112 | K25: 5.5804387 | L25: 5.4973407 | M25: 5.3985702 | N25: 5.4606381 | O25: 5.5150158 | P25: 5.6061409 | Q25: 5.6015201 | R25: 5.6180302 | S25: 5.6341719 | T25: 5.6967438 | U25: 5.8313249 | V25: 6.1903422 | W25: 6.5030493 | X25: 6.9814954
A26: Canterbury Region | B26: Equity | C26: 0.015813342 | D26: 0.029182359 | E26: 0.027170311 | F26: 0.025954358 | G26: 0.026826294 | H26: 0.028344402 | I26: 0.026950361 | J26: 0.027984242 | K26: 0.025206815 | L26: 0.024190054 | M26: 0.033520843 | N26: 0.05857019 | O26: 0.085806104 | P26: 0.088961495 | Q26: 0.089130187 | R26: 0.089016125 | S26: 0.087908096 | T26: 0.084572689 | U26: 0.086666894 | V26: 0.088331015 | W26: 0.087398449 | X26: 0.0878183
A27: Canterbury Region | B27: Targeted Funding for Disadvantage | C27: 0 | D27: 0 | E27: 0 | F27: 0 | G27: 0 | H27: 0 | I27: 0 | J27: 0 | K27: 0 | L27: 0 | M27: 0 | N27: 0 | O27: 0 | P27: 0 | Q27: 0 | R27: 0 | S27: 0.012743051 | T27: 0.025010263 | U27: 0.026681401 | V27: 0.029358817 | W27: 0.029300494 | X27: 0.029419611
A28: Canterbury Region | B28: Total | C28: 3.2505033 | D28: 3.3500776 | E28: 3.4877517 | F28: 3.7792271 | G28: 4.5929784 | H28: 5.0808932 | I28: 6.6799626 | J28: 7.7986087 | K28: 8.3147459 | L28: 8.4110735 | M28: 8.411126 | N28: 8.4874018 | O28: 8.6033742 | P28: 8.708385 | Q28: 8.7019077 | R28: 8.6801566 | S28: 8.6725033 | T28: 8.7525563 | U28: 8.9613902 | V28: 9.4650101 | W28: 9.8322235 | X28: 10.490949
A29: Gisborne Region | B29: 20 Hours ECE | I29: 7.7795394 | J29: 8.7233613 | K29: 8.9362755 | L29: 8.7942485 | M29: 8.9815566 | N29: 9.0918956 | O29: 9.2377356 | P29: 9.4281136 | Q29: 9.4727526 | R29: 9.5045317 | S29: 9.574893 | T29: 9.6320352 | U29: 10.177092 | V29: 10.829923 | W29: 11.272529 | X29: 11.809731
A30: Gisborne Region | B30: Under 2's | C30: 5.1295873 | D30: 5.2741302 | E30: 5.4990985 | F30: 5.6894448 | G30: 6.2827356 | H30: 6.8467789 | I30: 7.5768775 | J30: 8.2193349 | K30: 8.8033711 | L30: 8.8188607 | M30: 8.8464684 | N30: 8.8673113 | O30: 8.9732132 | P30: 9.028757 | Q30: 9.0930132 | R30: 9.1211024 | S30: 9.2404969 | T30: 9.356412 | U30: 10.173084 | V30: 11.039443 | W30: 11.433396 | X30: 12.050487
A31: Gisborne Region | B31: 2 and over - non 20 Hours ECE | C31: 2.6985678 | D31: 2.7561722 | E31: 2.8712809 | F31: 3.035729 | G31: 3.4390073 | H31: 3.8148999 | I31: 3.9163464 | J31: 4.4877231 | K31: 4.753657 | L31: 4.7313212 | M31: 4.7987804 | N31: 4.8549049 | O31: 5.0083052 | P31: 5.0603831 | Q31: 5.1136782 | R31: 5.1363863 | S31: 5.2182705 | T31: 5.2689602 | U31: 5.9393458 | V31: 6.5666318 | W31: 6.8189952 | X31: 7.1845504
A32: Gisborne Region | B32: Equity | C32: 0.16127607 | D32: 0.25631889 | E32: 0.25426673 | F32: 0.24248972 | G32: 0.24683762 | H32: 0.23183694 | I32: 0.24484339 | J32: 0.29688522 | K32: 0.28302377 | L32: 0.27387081 | M32: 0.2808823 | N32: 0.45270794 | O32: 0.61297735 | P32: 0.62376292 | Q32: 0.63413043 | R32: 0.64990368 | S32: 0.62671292 | T32: 0.6016804 | U32: 0.62278296 | V32: 0.62705788 | W32: 0.66129059 | X32: 0.68452672
A33: Gisborne Region | B33: Targeted Funding for Disadvantage | C33: 0 | D33: 0 | E33: 0 | F33: 0 | G33: 0 | H33: 0 | I33: 0 | J33: 0 | K33: 0 | L33: 0 | M33: 0 | N33: 0 | O33: 0 | P33: 0 | Q33: 0 | R33: 0 | S33: 0.048275996 | T33: 0.092256805 | U33: 0.09517919 | V33: 0.10581387 | W33: 0.10861997 | X33: 0.098706455
A34: Gisborne Region | B34: Total | C34: 3.330972 | D34: 3.5218299 | E34: 3.6381887 | F34: 3.7737635 | G34: 4.199296 | H34: 4.6247449 | I34: 6.2219917 | J34: 7.1770844 | K34: 7.5624195 | L34: 7.6204667 | M34: 7.7944702 | N34: 8.0226448 | O34: 8.283328 | P34: 8.4218623 | Q34: 8.4684002 | R34: 8.4499368 | S34: 8.5333774 | T34: 8.6037646 | U34: 9.2593248 | V34: 9.94585 | W34: 10.354616 | X34: 10.843429
A35: Hawkes Bay Region | B35: 20 Hours ECE | I35: 7.5719638 | J35: 8.8098405 | K35: 9.4268329 | L35: 9.383312 | M35: 9.2502091 | N35: 9.2910361 | O35: 9.4322005 | P35: 9.5321486 | Q35: 9.5202656 | R35: 9.5610088 | S35: 9.6056485 | T35: 9.7060311 | U35: 10.138043 | V35: 10.791278 | W35: 11.271678 | X35: 11.865094
A36: Hawkes Bay Region | B36: Under 2's | C36: 5.0541168 | D36: 5.1804861 | E36: 5.3522349 | F36: 5.6282297 | G36: 6.3259167 | H36: 6.9624349 | I36: 7.6234982 | J36: 7.8763951 | K36: 8.191548 | L36: 8.2453541 | M36: 8.3828171 | N36: 8.5164607 | O36: 8.7083009 | P36: 8.863799 | Q36: 8.9236577 | R36: 8.9752089 | S36: 9.0154763 | T36: 9.2177805 | U36: 9.8023293 | V36: 10.500269 | W36: 10.852245 | X36: 11.507507
A37: Hawkes Bay Region | B37: 2 and over - non 20 Hours ECE | C37: 2.7312682 | D37: 2.8105537 | E37: 2.9249784 | F37: 3.1475511 | G37: 3.6005808 | H37: 3.9489825 | I37: 3.9799062 | J37: 4.4522355 | K37: 4.6723572 | L37: 4.6686391 | M37: 4.6335156 | N37: 4.7292587 | O37: 4.9063439 | P37: 4.9989888 | Q37: 5.0415726 | R37: 5.092721 | S37: 5.1484536 | T37: 5.2324638 | U37: 5.7371384 | V37: 6.299522 | W37: 6.5939849 | X37: 6.9710413
A38: Hawkes Bay Region | B38: Equity | C38: 0.1095816 | D38: 0.19233142 | E38: 0.18622801 | F38: 0.18092984 | G38: 0.18356936 | H38: 0.18218256 | I38: 0.18131646 | J38: 0.20713957 | K38: 0.19940023 | L38: 0.1908502 | M38: 0.22134475 | N38: 0.36199677 | O38: 0.50180062 | P38: 0.5170707 | Q38: 0.53134449 | R38: 0.52937431 | S38: 0.5232683 | T38: 0.51574772 | U38: 0.52784393 | V38: 0.52343078 | W38: 0.52815464 | X38: 0.53436256
A39: Hawkes Bay Region | B39: Targeted Funding for Disadvantage | C39: 0 | D39: 0 | E39: 0 | F39: 0 | G39: 0 | H39: 0 | I39: 0 | J39: 0 | K39: 0 | L39: 0 | M39: 0 | N39: 0 | O39: 0 | P39: 0 | Q39: 0 | R39: 0 | S39: 0.038984661 | T39: 0.077957295 | U39: 0.078604347 | V39: 0.076940358 | W39: 0.079498317 | X39: 0.076900379
A40: Hawkes Bay Region | B40: Total | C40: 3.2891897 | D40: 3.4767352 | E40: 3.6003447 | F40: 3.8289524 | G40: 4.3686566 | H40: 4.7800654 | I40: 6.1358914 | J40: 7.0694711 | K40: 7.5077852 | L40: 7.5704857 | M40: 7.551748 | N40: 7.8164511 | O40: 8.1570572 | P40: 8.2488407 | Q40: 8.299563 | R40: 8.3242731 | S40: 8.3772902 | T40: 8.4761601 | U40: 8.96771 | V40: 9.6305484 | W40: 9.9995487 | X40: 10.537316
A41: Manawatū-Whanganui Region | B41: 20 Hours ECE | I41: 7.6186319 | J41: 8.9308919 | K41: 9.434793 | L41: 9.367877 | M41: 9.3381288 | N41: 9.3853106 | O41: 9.4926091 | P41: 9.6343313 | Q41: 9.6672608 | R41: 9.7072687 | S41: 9.7661933 | T41: 9.8453761 | U41: 10.230076 | V41: 10.905054 | W41: 11.400652 | X41: 11.997755
A42: Manawatū-Whanganui Region | B42: Under 2's | C42: 5.107883 | D42: 5.2348613 | E42: 5.3768512 | F42: 5.6582904 | G42: 6.4899269 | H42: 7.1176872 | I42: 7.864083 | J42: 8.2982246 | K42: 8.6020529 | L42: 8.6366612 | M42: 8.7604989 | N42: 8.815059 | O42: 8.9513104 | P42: 9.0679166 | Q42: 9.1051406 | R42: 9.1596377 | S42: 9.2119832 | T42: 9.3471913 | U42: 9.9653307 | V42: 10.746265 | W42: 11.132086 | X42: 11.829822
A43: Manawatū-Whanganui Region | B43: 2 and over - non 20 Hours ECE | C43: 2.7655785 | D43: 2.8425724 | E43: 2.9501249 | F43: 3.1932797 | G43: 3.7107793 | H43: 4.1116666 | I43: 4.0781005 | J43: 4.7094629 | K43: 4.8594304 | L43: 4.8418201 | M43: 4.8426073 | N43: 4.9389666 | O43: 4.9808881 | P43: 5.0681284 | Q43: 5.1358477 | R43: 5.1762826 | S43: 5.2500283 | T43: 5.3146378 | U43: 5.752356 | V43: 6.3224565 | W43: 6.6609954 | X43: 7.0310591
A44: Manawatū-Whanganui Region | B44: Equity | C44: 0.072069063 | D44: 0.13065618 | E44: 0.1261566 | F44: 0.12410689 | G44: 0.12213844 | H44: 0.11871104 | I44: 0.10943577 | J44: 0.11770558 | K44: 0.1106664 | L44: 0.10310136 | M44: 0.13108549 | N44: 0.22566423 | O44: 0.31525149 | P44: 0.32068795 | Q44: 0.32604879 | R44: 0.32681065 | S44: 0.32380795 | T44: 0.32365671 | U44: 0.3299526 | V44: 0.32598584 | W44: 0.3265487 | X44: 0.33851612
A45: Manawatū-Whanganui Region | B45: Targeted Funding for Disadvantage | C45: 0 | D45: 0 | E45: 0 | F45: 0 | G45: 0 | H45: 0 | I45: 0 | J45: 0 | K45: 0 | L45: 0 | M45: 0 | N45: 0 | O45: 0 | P45: 0 | Q45: 0 | R45: 0 | S45: 0.03696738 | T45: 0.06943598 | U45: 0.065006961 | V45: 0.069021123 | W45: 0.07007511 | X45: 0.070423602
A46: Manawatū-Whanganui Region | B46: Total | C46: 3.2345669 | D46: 3.3899551 | E46: 3.500531 | F46: 3.7437865 | G46: 4.3336024 | H46: 4.8022079 | I46: 6.3456565 | J46: 7.3382725 | K46: 7.7187875 | L46: 7.7659486 | M46: 7.8280599 | N46: 8.005846 | O46: 8.19262 | P46: 8.2964241 | Q46: 8.309152 | R46: 8.3325705 | S46: 8.4134001 | T46: 8.5085156 | U46: 8.9373069 | V46: 9.6080121 | W46: 10.003838 | X46: 10.61958
A47: Marlborough Region | B47: 20 Hours ECE | I47: 7.3076581 | J47: 9.0813297 | K47: 10.056316 | L47: 9.6352445 | M47: 9.4865214 | N47: 9.4521907 | O47: 9.5886586 | P47: 9.7504606 | Q47: 9.7741055 | R47: 9.8192006 | S47: 9.8912243 | T47: 10.006866 | U47: 10.272683 | V47: 10.894832 | W47: 11.412577 | X47: 12.038589
A48: Marlborough Region | B48: Under 2's | C48: 5.1547702 | D48: 5.2769571 | E48: 5.4979882 | F48: 5.8241617 | G48: 6.8385241 | H48: 7.6649707 | I48: 8.8317747 | J48: 8.8309907 | K48: 8.9072095 | L48: 8.5954754 | M48: 8.5022474 | N48: 8.4895233 | O48: 8.6656059 | P48: 8.7934784 | Q48: 8.9752274 | R48: 8.9869255 | S48: 9.3392215 | T48: 9.5965127 | U48: 9.9555955 | V48: 10.61548 | W48: 10.880071 | X48: 11.506476
A49: Marlborough Region | B49: 2 and over - non 20 Hours ECE | C49: 2.7872844 | D49: 2.8953954 | E49: 3.0303624 | F49: 3.3054386 | G49: 3.8521814 | H49: 4.2554084 | I49: 4.40291 | J49: 5.0772774 | K49: 5.1266544 | L49: 4.8905821 | M49: 4.7787326 | N49: 4.8529552 | O49: 4.9870549 | P49: 5.0893863 | Q49: 5.2148682 | R49: 5.3166748 | S49: 5.3728573 | T49: 5.5381428 | U49: 5.7447627 | V49: 6.1143796 | W49: 6.4980573 | X49: 6.8300991
A50: Marlborough Region | B50: Equity | C50: 0.019016233 | D50: 0.024122318 | E50: 0.024014223 | F50: 0.024377735 | G50: 0.03111546 | H50: 0.034070033 | I50: 0.026304571 | J50: 0.026664973 | K50: 0.022951886 | L50: 0.021492175 | M50: 0.021039318 | N50: 0.029147607 | O50: 0.034753849 | P50: 0.034185216 | Q50: 0.03377269 | R50: 0.035052076 | S50: 0.047704335 | T50: 0.053757857 | U50: 0.055991107 | V50: 0.05724864 | W50: 0.054769754 | X50: 0.057774682
A51: Marlborough Region | B51: Targeted Funding for Disadvantage | C51: 0 | D51: 0 | E51: 0 | F51: 0 | G51: 0 | H51: 0 | I51: 0 | J51: 0 | K51: 0 | L51: 0 | M51: 0 | N51: 0 | O51: 0 | P51: 0 | Q51: 0 | R51: 0 | S51: 0.016529633 | T51: 0.030379542 | U51: 0.030922293 | V51: 0.039448308 | W51: 0.035576549 | X51: 0.025172015
A52: Marlborough Region | B52: Total | C52: 3.1140598 | D52: 3.2725743 | E52: 3.3980122 | F52: 3.7271918 | G52: 4.3844136 | H52: 4.7957996 | I52: 6.5248466 | J52: 7.7572287 | K52: 8.3423485 | L52: 8.0128942 | M52: 7.9660516 | N52: 8.0177004 | O52: 8.159962 | P52: 8.3245738 | Q52: 8.366881 | R52: 8.3811604 | S52: 8.5131043 | T52: 8.6377154 | U52: 8.9111306 | V52: 9.5367539 | W52: 9.9499496 | X52: 10.349435
A53: Nelson Region | B53: 20 Hours ECE | I53: 7.6963486 | J53: 10.292777 | K53: 10.346709 | L53: 9.9599599 | M53: 9.7106896 | N53: 9.7391408 | O53: 9.8532633 | P53: 9.9175093 | Q53: 9.9236846 | R53: 9.9598516 | S53: 10.02651 | T53: 10.094242 | U53: 10.441842 | V53: 11.10365 | W53: 11.674671 | X53: 12.212003
A54: Nelson Region | B54: Under 2's | C54: 5.2018921 | D54: 5.1976168 | E54: 5.439567 | F54: 5.6510452 | G54: 6.9839319 | H54: 7.7851765 | I54: 8.39101 | J54: 9.0362842 | K54: 9.7400147 | L54: 9.6578026 | M54: 9.6484138 | N54: 9.5789075 | O54: 9.4492362 | P54: 9.1380074 | Q54: 9.1050429 | R54: 9.4296959 | S54: 9.5941695 | T54: 9.722105 | U54: 10.062948 | V54: 10.531902 | W54: 10.871052 | X54: 11.493077
A55: Nelson Region | B55: 2 and over - non 20 Hours ECE | C55: 2.8168875 | D55: 2.8981919 | E55: 3.0353971 | F55: 3.3105413 | G55: 3.947295 | H55: 4.4218698 | I55: 4.4405826 | J55: 5.1707599 | K55: 5.3820065 | L55: 5.3518384 | M55: 5.3740752 | N55: 5.4291386 | O55: 5.4694085 | P55: 5.4754838 | Q55: 5.4782453 | R55: 5.5426994 | S55: 5.6049537 | T55: 5.6833836 | U55: 5.9183296 | V55: 6.3832974 | W55: 6.7836791 | X55: 7.1097196
A56: Nelson Region | B56: Equity | C56: 0.0370663 | D56: 0.070201108 | E56: 0.070964287 | F56: 0.058867371 | G56: 0.056381505 | H56: 0.055244765 | I56: 0.052682591 | J56: 0.064044831 | K56: 0.065026372 | L56: 0.062210082 | M56: 0.067473243 | N56: 0.097320118 | O56: 0.12516711 | P56: 0.12827401 | Q56: 0.13452761 | R56: 0.13521926 | S56: 0.15085248 | T56: 0.14881998 | U56: 0.15265113 | V56: 0.15870658 | W56: 0.15417839 | X56: 0.15065699
A57: Nelson Region | B57: Targeted Funding for Disadvantage | C57: 0 | D57: 0 | E57: 0 | F57: 0 | G57: 0 | H57: 0 | I57: 0 | J57: 0 | K57: 0 | L57: 0 | M57: 0 | N57: 0 | O57: 0 | P57: 0 | Q57: 0 | R57: 0 | S57: 0.028622708 | T57: 0.052278907 | U57: 0.048117489 | V57: 0.050489916 | W57: 0.050731204 | X57: 0.047415659
A58: Nelson Region | B58: Total | C58: 3.1852751 | D58: 3.2974161 | E58: 3.4216833 | F58: 3.7113042 | G58: 4.4278945 | H58: 4.9205027 | I58: 6.8652276 | J58: 8.6503687 | K58: 8.7873042 | L58: 8.6365448 | M58: 8.6116402 | N58: 8.6580306 | O58: 8.7124819 | P58: 8.6864479 | Q58: 8.570812 | R58: 8.6501984 | S58: 8.6954028 | T58: 8.7938834 | U58: 9.1196731 | V58: 9.6389587 | W58: 10.104169 | X58: 10.561682
A59: Northland Region | B59: 20 Hours ECE | I59: 7.5540713 | J59: 9.6411775 | K59: 9.9108016 | L59: 9.6158273 | M59: 9.4845573 | N59: 9.4742781 | O59: 9.5167802 | P59: 9.6031474 | Q59: 9.6441214 | R59: 9.6979291 | S59: 9.69325 | T59: 9.7614401 | U59: 10.148622 | V59: 10.751369 | W59: 11.215361 | X59: 11.865382
A60: Northland Region | B60: Under 2's | C60: 5.0840031 | D60: 5.1829374 | E60: 5.324283 | F60: 5.5772611 | G60: 6.3164949 | H60: 7.1113249 | I60: 8.0680622 | J60: 8.4540123 | K60: 8.9530157 | L60: 8.9367145 | M60: 9.0738033 | N60: 9.1194145 | O60: 9.2686578 | P60: 9.4327824 | Q60: 9.4176604 | R60: 9.3964621 | S60: 9.4621362 | T60: 9.5315129 | U60: 10.045516 | V60: 10.677502 | W60: 11.050266 | X60: 11.748244
A61: Northland Region | B61: 2 and over - non 20 Hours ECE | C61: 2.7197388 | D61: 2.787131 | E61: 2.8986384 | F61: 3.1021308 | G61: 3.4984573 | H61: 3.9413375 | I61: 4.0657266 | J61: 4.6373505 | K61: 4.8388919 | L61: 4.8113934 | M61: 4.8535342 | N61: 4.9759435 | O61: 5.0815241 | P61: 5.2228821 | Q61: 5.2759281 | R61: 5.283293 | S61: 5.294724 | T61: 5.3509869 | U61: 5.7658863 | V61: 6.2508142 | W61: 6.5408531 | X61: 6.9149635
A62: Northland Region | B62: Equity | C62: 0.12920307 | D62: 0.22465047 | E62: 0.21617783 | F62: 0.20471393 | G62: 0.20077924 | H62: 0.19186288 | I62: 0.17368978 | J62: 0.18420685 | K62: 0.17525271 | L62: 0.17799852 | M62: 0.22200662 | N62: 0.34624686 | O62: 0.46940704 | P62: 0.47235956 | Q62: 0.47126935 | R62: 0.49395247 | S62: 0.50954086 | T62: 0.51118975 | U62: 0.52372142 | V62: 0.51613639 | W62: 0.51062675 | X62: 0.51083015
A63: Northland Region | B63: Targeted Funding for Disadvantage | C63: 0 | D63: 0 | E63: 0 | F63: 0 | G63: 0 | H63: 0 | I63: 0 | J63: 0 | K63: 0 | L63: 0 | M63: 0 | N63: 0 | O63: 0 | P63: 0 | Q63: 0 | R63: 0 | S63: 0.042803033 | T63: 0.083697724 | U63: 0.081480079 | V63: 0.083340408 | W63: 0.085725969 | X63: 0.087666796
A64: Northland Region | B64: Total | C64: 3.291475 | D64: 3.4636187 | E64: 3.5650191 | F64: 3.7799405 | G64: 4.2485887 | H64: 4.7719015 | I64: 6.2876518 | J64: 7.6737758 | K64: 8.0022409 | L64: 7.9357667 | M64: 8.0698599 | N64: 8.2342468 | O64: 8.494148 | P64: 8.580991 | Q64: 8.581021 | R64: 8.601859 | S64: 8.6590902 | T64: 8.726518 | U64: 9.1522293 | V64: 9.7643992 | W64: 10.090106 | X64: 10.655315
A65: Not Applicable | B65: 20 Hours ECE | I65: 8.7088663 | J65: 9.624071 | K65: 9.8680312 | L65: 9.6819332 | M65: 9.5494576 | N65: 9.5219858 | O65: 9.5504511 | P65: 9.7136756 | Q65: 9.682415 | R65: 9.7763796 | S65: 9.8097499 | T65: 9.862454 | U65: 10.046905 | V65: 10.407559 | W65: 10.616402 | X65: 11.604832
A66: Not Applicable | B66: Under 2's | C66: 4.0210764 | D66: 4.0738714 | E66: 4.8372368 | F66: 5.8256928 | G66: 7.1908274 | H66: 7.7574639 | I66: 8.4531815 | J66: 9.4704747 | K66: 10.082201 | L66: 9.5143044 | M66: 9.2399429 | N66: 9.0605689 | O66: 8.8140736 | P66: 8.3960454 | Q66: 7.5035106 | R66: 7.6313527 | S66: 7.8568511 | T66: 8.1839266 | U66: 8.4447381 | V66: 8.9609045 | W66: 9.5227475 | X66: 10.877092
A67: Not Applicable | B67: 2 and over - non 20 Hours ECE | C67: 2.4014219 | D67: 2.3850774 | E67: 2.5562693 | F67: 2.7945172 | G67: 3.5939501 | H67: 4.1615528 | I67: 4.5320027 | J67: 5.4521811 | K67: 5.7522555 | L67: 5.5111608 | M67: 5.3397074 | N67: 5.2081938 | O67: 5.1872113 | P67: 5.162297 | Q67: 4.7652415 | R67: 4.7241736 | S67: 4.7043521 | T67: 4.6460688 | U67: 4.779077 | V67: 4.9499525 | W67: 5.3200746 | X67: 5.9299901
A68: Not Applicable | B68: Equity | C68: 0.0052034844 | D68: 0.0088335337 | E68: 0.0081874733 | F68: 0.0040854467 | G68: 0.0081012597 | H68: 0.0099053325 | I68: 0.012514557 | J68: 0.012479172 | K68: 0.0088986843 | L68: 0.0017958908 | M68: 0.012716698 | N68: 0.021719303 | O68: 0.02857305 | P68: 0.041934513 | Q68: 0.036605296 | R68: 0.036948813 | S68: 0.035741782 | T68: 0.029707949 | U68: 0.044424832 | V68: 0.060707284 | W68: 0.071704778 | X68: 0.058706874
A69: Not Applicable | B69: Targeted Funding for Disadvantage | C69: 0 | D69: 0 | E69: 0 | F69: 0 | G69: 0 | H69: 0 | I69: 0 | J69: 0 | K69: 0 | L69: 0 | M69: 0 | N69: 0 | O69: 0 | P69: 0 | Q69: 0 | R69: 0 | S69: 0.010218512 | T69: 0.016985927 | U69: 0.017081399 | V69: 0.020747031 | W69: 0.0214756 | X69: 0.020724685
A70: Not Applicable | B70: Total | C70: 2.6577137 | D70: 2.7042937 | E70: 2.9312409 | F70: 3.4406876 | G70: 4.4195262 | H70: 4.9148311 | I70: 6.702823 | J70: 8.1642682 | K70: 8.4484442 | L70: 8.1546479 | M70: 8.0470823 | N70: 7.9502166 | O70: 7.8528301 | P70: 7.7805106 | Q70: 7.2059742 | R70: 7.1588066 | S70: 7.1405841 | T70: 7.0492959 | U70: 7.3349986 | V70: 7.7668832 | W70: 8.2608284 | X70: 9.1366265
A71: Otago Region | B71: 20 Hours ECE | H71: 0 | I71: 8.0516356 | J71: 9.3665275 | K71: 9.9678074 | L71: 9.8332624 | M71: 9.5824842 | N71: 9.5914569 | O71: 9.6742715 | P71: 9.755849 | Q71: 9.7789166 | R71: 9.8291684 | S71: 9.869173 | T71: 9.9811447 | U71: 10.238894 | V71: 10.866606 | W71: 11.393678 | X71: 12.064789
A72: Otago Region | B72: Under 2's | C72: 5.2112126 | D72: 5.2962847 | E72: 5.4696157 | F72: 5.8293942 | G72: 7.1080209 | H72: 7.6591517 | I72: 8.4366807 | J72: 8.8602572 | K72: 9.2915134 | L72: 9.3610643 | M72: 9.2676081 | N72: 9.1861385 | O72: 9.2584663 | P72: 9.3636071 | Q72: 9.4554031 | R72: 9.5576823 | S72: 9.5894756 | T72: 9.9299731 | U72: 10.173959 | V72: 10.728913 | W72: 11.141236 | X72: 11.905815
A73: Otago Region | B73: 2 and over - non 20 Hours ECE | C73: 2.7945607 | D73: 2.8933441 | E73: 3.0072732 | F73: 3.2875231 | G73: 3.9585882 | H73: 4.3781962 | I73: 4.4678464 | J73: 5.1698455 | K73: 5.4649717 | L73: 5.4600858 | M73: 5.2303888 | N73: 5.2102825 | O73: 5.3107684 | P73: 5.387399 | Q73: 5.4296127 | R73: 5.486279 | S73: 5.5156042 | T73: 5.6428063 | U73: 5.8382673 | V73: 6.2677771 | W73: 6.6297672 | X73: 7.0579777
A74: Otago Region | B74: Equity | C74: 0.023911858 | D74: 0.043918811 | E74: 0.040744281 | F74: 0.039140074 | G74: 0.03963304 | H74: 0.040126558 | I74: 0.031516696 | J74: 0.028707328 | K74: 0.028022272 | L74: 0.028359867 | M74: 0.049805114 | N74: 0.063151034 | O74: 0.082881134 | P74: 0.086970661 | Q74: 0.087536798 | R74: 0.097095687 | S74: 0.10665317 | T74: 0.10589415 | U74: 0.10941757 | V74: 0.10610142 | W74: 0.10397207 | X74: 0.10543871
A75: Otago Region | B75: Targeted Funding for Disadvantage | C75: 0 | D75: 0 | E75: 0 | F75: 0 | G75: 0 | H75: 0 | I75: 0 | J75: 0 | K75: 0 | L75: 0 | M75: 0 | N75: 0 | O75: 0 | P75: 0 | Q75: 0 | R75: 0 | S75: 0.012252711 | T75: 0.023725353 | U75: 0.02493654 | V75: 0.027388908 | W75: 0.024418122 | X75: 0.022941644
A76: Otago Region | B76: Total | C76: 3.2557006 | D76: 3.3602266 | E76: 3.4852697 | F76: 3.7888421 | G76: 4.5561873 | H76: 5.0140468 | I76: 6.8002985 | J76: 7.8584734 | K76: 8.3214277 | L76: 8.3589374 | M76: 8.193561 | N76: 8.2109856 | O76: 8.3468884 | P76: 8.4190983 | Q76: 8.4406637 | R76: 8.4941917 | S76: 8.4943882 | T76: 8.6639705 | U76: 8.9032866 | V76: 9.4714376 | W76: 9.9025928 | X76: 10.48597
A77: Southland Region | B77: 20 Hours ECE | I77: 7.1195347 | J77: 8.4693728 | K77: 9.0307719 | L77: 9.0837845 | M77: 9.0715531 | N77: 9.5887032 | O77: 9.7381598 | P77: 9.8227864 | Q77: 9.8243269 | R77: 9.836853 | S77: 9.8667242 | T77: 9.9349911 | U77: 10.270028 | V77: 10.924421 | W77: 11.451796 | X77: 12.063972
A78: Southland Region | B78: Under 2's | C78: 5.1849442 | D78: 5.3219656 | E78: 5.4953243 | F78: 5.8230504 | G78: 6.9638945 | H78: 7.5910091 | I78: 8.1176653 | J78: 8.4185918 | K78: 8.9731499 | L78: 9.1977466 | M78: 9.2928511 | N78: 9.5748126 | O78: 9.7330315 | P78: 9.659137 | Q78: 9.5595086 | R78: 9.513222 | S78: 9.6695952 | T78: 9.7781867 | U78: 10.134515 | V78: 10.733169 | W78: 11.025844 | X78: 11.780337
A79: Southland Region | B79: 2 and over - non 20 Hours ECE | C79: 2.8773272 | D79: 2.9731751 | E79: 3.1034657 | F79: 3.377111 | G79: 3.9050448 | H79: 4.247121 | I79: 4.0680791 | J79: 4.7391821 | K79: 4.904278 | L79: 5.0425317 | M79: 5.062699 | N79: 5.2026932 | O79: 5.3513245 | P79: 5.4248716 | Q79: 5.4073382 | R79: 5.414501 | S79: 5.4290768 | T79: 5.5337666 | U79: 5.8052602 | V79: 6.2200096 | W79: 6.5773851 | X79: 7.0058687
A80: Southland Region | B80: Equity | C80: 0.067429883 | D80: 0.12938423 | E80: 0.12167012 | F80: 0.11490517 | G80: 0.10257996 | H80: 0.091286118 | I80: 0.082664094 | J80: 0.088532281 | K80: 0.085059164 | L80: 0.081495827 | M80: 0.10263423 | N80: 0.16098669 | O80: 0.23043031 | P80: 0.23084142 | Q80: 0.23408535 | R80: 0.23787658 | S80: 0.2255633 | T80: 0.22291135 | U80: 0.22893278 | V80: 0.22237299 | W80: 0.2189157 | X80: 0.2300419
A81: Southland Region | B81: Targeted Funding for Disadvantage | C81: 0 | D81: 0 | E81: 0 | F81: 0 | G81: 0 | H81: 0 | I81: 0 | J81: 0 | K81: 0 | L81: 0 | M81: 0 | N81: 0 | O81: 0 | P81: 0 | Q81: 0 | R81: 0 | S81: 0.023426505 | T81: 0.04625899 | U81: 0.045264177 | V81: 0.044315852 | W81: 0.043041971 | X81: 0.042775378
A82: Southland Region | B82: Total | C82: 3.2802737 | D82: 3.4594283 | E82: 3.6175162 | F82: 3.9386613 | G82: 4.5793364 | H82: 4.9311424 | I82: 6.2868588 | J82: 7.4044492 | K82: 7.8237494 | L82: 8.0254132 | M82: 8.0909612 | N82: 8.4990506 | O82: 8.7197591 | P82: 8.7519023 | Q82: 8.7557701 | R82: 8.73939 | S82: 8.7392354 | T82: 8.8530304 | U82: 9.1075156 | V82: 9.7055375 | W82: 10.036139 | X82: 10.609507
A83: Taranaki Region | B83: 20 Hours ECE | I83: 7.4000413 | J83: 8.7300294 | K83: 9.3431304 | L83: 9.5460005 | M83: 9.4942416 | N83: 9.5251523 | O83: 9.6166749 | P83: 9.7053774 | Q83: 9.7087173 | R83: 9.7555205 | S83: 9.8405894 | T83: 9.9107007 | U83: 10.293328 | V83: 11.024492 | W83: 11.521481 | X83: 12.14654
A84: Taranaki Region | B84: Under 2's | C84: 5.1322573 | D84: 5.259154 | E84: 5.4530993 | F84: 5.6619602 | G84: 6.5269424 | H84: 7.4251124 | I84: 7.8608469 | J84: 8.1645979 | K84: 8.7853633 | L84: 8.7617947 | M84: 8.7202816 | N84: 8.7928885 | O84: 8.968766 | P84: 8.9666089 | Q84: 9.0786568 | R84: 9.1710123 | S84: 9.2326553 | T84: 9.3983575 | U84: 9.8528635 | V84: 10.765624 | W84: 11.036998 | X84: 11.730753
A85: Taranaki Region | B85: 2 and over - non 20 Hours ECE | C85: 2.8138894 | D85: 2.9079454 | E85: 3.0304523 | F85: 3.2916347 | G85: 3.7826302 | H85: 4.1624368 | I85: 4.155183 | J85: 4.621683 | K85: 4.8469387 | L85: 4.8995794 | M85: 4.8742782 | N85: 4.8998758 | O85: 5.0111283 | P85: 5.1199272 | Q85: 5.1624154 | R85: 5.2165642 | S85: 5.294219 | T85: 5.3560951 | U85: 5.7703589 | V85: 6.4097973 | W85: 6.6832598 | X85: 7.1065451
A86: Taranaki Region | B86: Equity | C86: 0.066995318 | D86: 0.11947671 | E86: 0.12360877 | F86: 0.12128825 | G86: 0.11957546 | H86: 0.11433791 | I86: 0.093958619 | J86: 0.08782283 | K86: 0.082089849 | L86: 0.078526314 | M86: 0.090976453 | N86: 0.15229819 | O86: 0.20191411 | P86: 0.19594508 | Q86: 0.19241495 | R86: 0.19200168 | S86: 0.19496028 | T86: 0.19938288 | U86: 0.20568339 | V86: 0.2042143 | W86: 0.20044104 | X86: 0.21131366
A87: Taranaki Region | B87: Targeted Funding for Disadvantage | C87: 0 | D87: 0 | E87: 0 | F87: 0 | G87: 0 | H87: 0 | I87: 0 | J87: 0 | K87: 0 | L87: 0 | M87: 0 | N87: 0 | O87: 0 | P87: 0 | Q87: 0 | R87: 0 | S87: 0.021534293 | T87: 0.041460644 | U87: 0.044565974 | V87: 0.050155902 | W87: 0.051211856 | X87: 0.05235221
A88: Taranaki Region | B88: Total | C88: 3.2914402 | D88: 3.4193201 | E88: 3.5663756 | F88: 3.8181131 | G88: 4.3757966 | H88: 4.8406238 | I88: 6.3716998 | J88: 7.337923 | K88: 7.8549422 | L88: 8.0958204 | M88: 8.1294827 | N88: 8.2225216 | O88: 8.3726749 | P88: 8.4275798 | Q88: 8.4884387 | R88: 8.4621021 | S88: 8.5160564 | T88: 8.61793 | U88: 9.0302993 | V88: 9.7247388 | W88: 10.108007 | X88: 10.700137
A89: Tasman Region | B89: 20 Hours ECE | I89: 8.1273204 | J89: 9.9021458 | K89: 10.063761 | L89: 9.8433193 | M89: 9.6797198 | N89: 9.7524186 | O89: 9.8435875 | P89: 9.9327442 | Q89: 9.9500424 | R89: 10.025715 | S89: 10.078072 | T89: 10.160162 | U89: 10.491622 | V89: 11.129681 | W89: 11.678488 | X89: 12.26326
A90: Tasman Region | B90: Under 2's | C90: 5.018657 | D90: 5.0489002 | E90: 5.2962503 | F90: 5.706148 | G90: 6.6499063 | H90: 7.535345 | I90: 8.3678069 | J90: 8.9128257 | K90: 9.6066962 | L90: 9.4356989 | M90: 9.3603699 | N90: 9.5144698 | O90: 9.7581605 | P90: 9.9105557 | Q90: 9.6678536 | R90: 9.6938822 | S90: 9.7015957 | T90: 9.8528938 | U90: 10.215647 | V90: 10.752411 | W90: 11.137989 | X90: 11.738894
A91: Tasman Region | B91: 2 and over - non 20 Hours ECE | C91: 2.7738438 | D91: 2.8339679 | E91: 2.9508769 | F91: 3.2524109 | G91: 3.8540321 | H91: 4.397709 | I91: 4.4131015 | J91: 5.0197052 | K91: 5.343685 | L91: 5.2655445 | M91: 5.168292 | N91: 5.2760378 | O91: 5.3981459 | P91: 5.4940694 | Q91: 5.5716877 | R91: 5.6305237 | S91: 5.6695332 | T91: 5.7259404 | U91: 5.949467 | V91: 6.3494462 | W91: 6.7470152 | X91: 7.1373185
A92: Tasman Region | B92: Equity | C92: 0.043778471 | D92: 0.077729142 | E92: 0.071634589 | F92: 0.072318135 | G92: 0.072804899 | H92: 0.072066202 | I92: 0.063395143 | J92: 0.06149103 | K92: 0.056878939 | L92: 0.056174247 | M92: 0.089399841 | N92: 0.10908761 | O92: 0.12656342 | P92: 0.12986703 | Q92: 0.13087254 | R92: 0.13339471 | S92: 0.13250831 | T92: 0.13835265 | U92: 0.14393322 | V92: 0.15255468 | W92: 0.15807922 | X92: 0.14781996
A93: Tasman Region | B93: Targeted Funding for Disadvantage | C93: 0 | D93: 0 | E93: 0 | F93: 0 | G93: 0 | H93: 0 | I93: 0 | J93: 0 | K93: 0 | L93: 0 | M93: 0 | N93: 0 | O93: 0 | P93: 0 | Q93: 0 | R93: 0 | S93: 0.015785593 | T93: 0.031190052 | U93: 0.033148413 | V93: 0.033176968 | W93: 0.032659109 | X93: 0.02959106
A94: Tasman Region | B94: Total | C94: 3.0911579 | D94: 3.1463617 | E94: 3.2749516 | F94: 3.5820368 | G94: 4.2439975 | H94: 4.8713086 | I94: 7.2463044 | J94: 8.569538 | K94: 8.8521305 | L94: 8.7117871 | M94: 8.6244448 | N94: 8.7370487 | O94: 8.7546716 | P94: 8.821672 | Q94: 8.7925165 | R94: 8.8647474 | S94: 8.8080752 | T94: 8.8405544 | U94: 9.2014989 | V94: 9.7237873 | W94: 10.21214 | X94: 10.735804
A95: Waikato Region | B95: 20 Hours ECE | I95: 7.5880994 | J95: 8.9014649 | K95: 9.6091368 | L95: 9.4346348 | M95: 9.3971734 | N95: 9.4534303 | O95: 9.5720067 | P95: 9.6881498 | Q95: 9.75029 | R95: 9.7952851 | S95: 9.8372584 | T95: 9.9063917 | U95: 10.239982 | V95: 10.768983 | W95: 11.167267 | X95: 11.823726
A96: Waikato Region | B96: Under 2's | C96: 5.1294564 | D96: 5.2234092 | E96: 5.3530652 | F96: 5.6181469 | G96: 6.4664037 | H96: 7.0884145 | I96: 7.7085242 | J96: 8.1266525 | K96: 8.6840803 | L96: 8.7044428 | M96: 8.9484675 | N96: 9.0968206 | O96: 9.181672 | P96: 9.3314651 | Q96: 9.5151983 | R96: 9.5229366 | S96: 9.5812286 | T96: 9.6705698 | U96: 10.045427 | V96: 10.614542 | W96: 11.117179 | X96: 11.871287
A97: Waikato Region | B97: 2 and over - non 20 Hours ECE | C97: 2.7712727 | D97: 2.849437 | E97: 2.9495171 | F97: 3.1718526 | G97: 3.6464335 | H97: 4.0185123 | I97: 4.0364428 | J97: 4.5989642 | K97: 4.8182959 | L97: 4.884772 | M97: 4.9803476 | N97: 5.0687362 | O97: 5.153521 | P97: 5.2606748 | Q97: 5.3422165 | R97: 5.3880332 | S97: 5.4285001 | T97: 5.4900406 | U97: 5.7798559 | V97: 6.1683769 | W97: 6.4666362 | X97: 6.8883405
A98: Waikato Region | B98: Equity | C98: 0.063610065 | D98: 0.11414024 | E98: 0.10849176 | F98: 0.10329026 | G98: 0.099895145 | H98: 0.09855473 | I98: 0.084760132 | J98: 0.085853547 | K98: 0.083906349 | L98: 0.079077791 | M98: 0.096538691 | N98: 0.16578339 | O98: 0.23942706 | P98: 0.25226016 | Q98: 0.25368654 | R98: 0.24793268 | S98: 0.24675751 | T98: 0.24539221 | U98: 0.25094997 | V98: 0.24714936 | W98: 0.24252145 | X98: 0.24888308
A99: Waikato Region | B99: Targeted Funding for Disadvantage | C99: 0 | D99: 0 | E99: 0 | F99: 0 | G99: 0 | H99: 0 | I99: 0 | J99: 0 | K99: 0 | L99: 0 | M99: 0 | N99: 0 | O99: 0 | P99: 0 | Q99: 0 | R99: 0 | S99: 0.028271636 | T99: 0.053889149 | U99: 0.053691821 | V99: 0.055733844 | W99: 0.056934985 | X99: 0.055736207
A100: Waikato Region | B100: Total | C100: 3.2086515 | D100: 3.3568238 | E100: 3.4669958 | F100: 3.7129632 | G100: 4.2655375 | H100: 4.6786147 | I100: 6.0967094 | J100: 7.1238014 | K100: 7.671418 | L100: 7.7135562 | M100: 7.8456295 | N100: 8.0153609 | O100: 8.197236 | P100: 8.31391 | Q100: 8.4286952 | R100: 8.4305068 | S100: 8.4635945 | T100: 8.5465691 | U100: 8.894326 | V100: 9.4200976 | W100: 9.7741436 | X100: 10.366759
A101: Wellington Region | B101: 20 Hours ECE | I101: 7.5638624 | J101: 8.8620359 | K101: 9.6442724 | L101: 9.7508361 | M101: 9.5857199 | N101: 9.6053143 | O101: 9.6814714 | P101: 9.759389 | Q101: 9.7846611 | R101: 9.8571604 | S101: 9.9246796 | T101: 10.018169 | U101: 10.359742 | V101: 11.009195 | W101: 11.529403 | X101: 12.16925
...

Sheet EXP12
A1: ='Table Index'!J16 -> Entitlement funding, equity funding and targeted funding for disadvantage per funded child hour by Territorial Authority, Auckland Local Board and programme ($, GST exclusive) | M1: About the data in this table | P1: Table Index
A3: Click on arrow to select (filter) the information you need
A4: Territorial Authority with Auckland Local Boards 16 | B4: Programme 14 | C4: 2001/02 | D4: 2002/03 | E4: 2003/04 | F4: 2004/05 | G4: 2005/06 | H4: 2006/07 | I4: 2007/08 | J4: 2008/09 | K4: 2009/10 | L4: 2010/11 | M4: 2011/12 | N4: 2012/13 | O4: 2013/14 | P4: 2014/15 | Q4: 2015/16 | R4: 2016/17 | S4: 2017/18 | T4: 2018/19 | U4: 2019/20 | V4: 2020/21 | W4: 2021/22 | X4: 2022/23
A5: Ashburton District | B5: 20 Hours ECE | I5: 7.2327247 | J5: 8.7637992 | K5: 9.4972966 | L5: 9.3667616 | M5: 9.6288767 | N5: 9.6143055 | O5: 9.7496922 | P5: 9.8799535 | Q5: 9.9304827 | R5: 9.9712527 | S5: 9.9866623 | T5: 10.073397 | U5: 10.304681 | V5: 10.777441 | W5: 11.201226 | X5: 11.84688
A6: Ashburton District | B6: Under 2's | C6: 5.2775334 | D6: 5.32939 | E6: 5.505861 | F6: 5.8437065 | G6: 6.9936307 | H6: 8.1273376 | I6: 8.5687878 | J6: 9.1619045 | K6: 9.867906 | L6: 9.7544916 | M6: 10.058603 | N6: 10.040645 | O6: 10.154453 | P6: 10.208754 | Q6: 10.25225 | R6: 10.324828 | S6: 10.373745 | T6: 10.425887 | U6: 10.625786 | V6: 11.102366 | W6: 11.385722 | X6: 12.095277
A7: Ashburton District | B7: 2 and over - non 20 Hours ECE | C7: 2.8765976 | D7: 2.9872179 | E7: 3.1122385 | F7: 3.3941473 | G7: 3.9729872 | H7: 4.4735791 | I7: 4.5913149 | J7: 5.3845689 | K7: 5.5200377 | L7: 5.3618656 | M7: 5.478772 | N7: 5.5534233 | O7: 5.647759 | P7: 5.7333873 | Q7: 5.7541805 | R7: 5.7778812 | S7: 5.8020737 | T7: 5.8443812 | U7: 5.9934805 | V7: 6.3032101 | W7: 6.555861 | X7: 6.9544457
A8: Ashburton District | B8: Equity | C8: 0 | D8: 0 | E8: 0 | F8: 0 | G8: 0 | H8: 0 | I8: 0.0041195981 | J8: 0.0088386291 | K8: 0.0073801638 | L8: 0.007124481 | M8: 0.0084329238 | N8: 0.025112782 | O8: 0.046499519 | P8: 0.052021937 | Q8: 0.055570689 | R8: 0.053009458 | S8: 0.04533535 | T8: 0.04314797 | U8: 0.044185151 | V8: 0.044712275 | W8: 0.054782729 | X8: 0.052272278
A9: Ashburton District | B9: Targeted Funding for Disadvantage | C9: 0 | D9: 0 | E9: 0 | F9: 0 | G9: 0 | H9: 0 | I9: 0 | J9: 0 | K9: 0 | L9: 0 | M9: 0 | N9: 0 | O9: 0 | P9: 0 | Q9: 0 | R9: 0 | S9: 0.011811414 | T9: 0.020048648 | U9: 0.016019226 | V9: 0.019643125 | W9: 0.016484598 | X9: 0.014893041
A10: Ashburton District | B10: Total | C10: 3.1947165 | D10: 3.3080758 | E10: 3.4050779 | F10: 3.6910414 | G10: 4.3707817 | H10: 5.0185785 | I10: 6.7193322 | J10: 7.8826698 | K10: 8.3672443 | L10: 8.3390992 | M10: 8.6404947 | N10: 8.5680303 | O10: 8.74362 | P10: 8.8759362 | Q10: 8.9554721 | R10: 8.9815669 | S10: 8.9425694 | T10: 8.9300743 | U10: 9.2021519 | V10: 9.6448595 | W10: 10.002274 | X10: 10.479431
A11: Auckland: Albert-Eden | B11: 20 Hours ECE | I11: 7.7204075 | J11: 8.7152034 | K11: 9.0718496 | L11: 9.0168051 | M11: 9.0953628 | N11: 9.2804834 | O11: 9.6081983 | P11: 9.8367657 | Q11: 9.9203275 | R11: 9.9584245 | S11: 9.9857415 | T11: 10.041494 | U11: 10.278706 | V11: 10.706668 | W11: 11.130487 | X11: 11.958116
A12: Auckland: Albert-Eden | B12: Under 2's | C12: 5.118397 | D12: 5.1916079 | E12: 5.4425922 | F12: 5.7603035 | G12: 6.7191839 | H12: 7.3541454 | I12: 8.3901188 | J12: 9.2975341 | K12: 10.099837 | L12: 10.220485 | M12: 10.24657 | N12: 10.261323 | O12: 10.310594 | P12: 8.8246373 | Q12: 8.3016319 | R12: 8.5409539 | S12: 8.9388485 | T12: 9.0677114 | U12: 9.253155 | V12: 9.2844082 | W12: 9.5164075 | X12: 10.40013
A13: Auckland: Albert-Eden | B13: 2 and over - non 20 Hours ECE | C13: 2.681137 | D13: 2.7631508 | E13: 2.8934258 | F13: 3.1298619 | G13: 3.732477 | H13: 4.1760112 | I13: 4.4363911 | J13: 5.3901993 | K13: 5.6530611 | L13: 5.6451807 | M13: 5.5657194 | N13: 5.6173839 | O13: 5.6790417 | P13: 5.5281576 | Q13: 5.3116903 | R13: 5.2852377 | S13: 5.3597096 | T13: 5.3045798 | U13: 5.3777608 | V13: 5.4891548 | W13: 5.6871598 | X13: 6.0015191
A14: Auckland: Albert-Eden | B14: Equity | C14: 0.0075580323 | D14: 0.014168952 | E14: 0.014034453 | F14: 0.014965356 | G14: 0.015498842 | H14: 0.015408138 | I14: 0.012168586 | J14: 0.0098602252 | K14: 0.0095354672 | L14: 0.0089831128 | M14: 0.01150628 | N14: 0.014018693 | O14: 0.020721612 | P14: 0.021765986 | Q14: 0.025187484 | R14: 0.027514323 | S14: 0.029251142 | T14: 0.028390689 | U14: 0.029171742 | V14: 0.029986464 | W14: 0.02955825 | X14: 0.034126133
A15: Auckland: Albert-Eden | B15: Targeted Funding for Disadvantage | C15: 0 | D15: 0 | E15: 0 | F15: 0 | G15: 0 | H15: 0 | I15: 0 | J15: 0 | K15: 0 | L15: 0 | M15: 0 | N15: 0 | O15: 0 | P15: 0 | Q15: 0 | R15: 0 | S15: 0.0027252205 | T15: 0.0048681042 | U15: 0.0042852334 | V15: 0.0050043534 | W15: 0.0073225906 | X15: 0.010787425
A16: Auckland: Albert-Eden | B16: Total | C16: 3.1119658 | D16: 3.1845479 | E16: 3.3611961 | F16: 3.6227501 | G16: 4.3210826 | H16: 4.7676295 | I16: 6.2052216 | J16: 7.4693235 | K16: 7.9732469 | L16: 8.014044 | M16: 8.0521816 | N16: 8.2253426 | O16: 8.4618603 | P16: 8.2407403 | Q16: 8.0319463 | R16: 8.0428363 | S16: 8.1579617 | T16: 8.0857627 | U16: 8.2057303 | V16: 8.4444208 | W16: 8.7047511 | X16: 9.3038619
A17: Auckland: Aotea/Great Barrier | B17: 20 Hours ECE | M17: 4.88 | N17: 4.88 | O17: 4.91 | P17: 4.96 | Q17: 4.96 | R17: 4.96 | S17: 4.96 | T17: 4.549212 | U17: 4.4306114 | V17: 4.7635658 | W17: 4.8249922 | X17: 7.6901779
A18: Auckland: Aotea/Great Barrier | B18: Under 2's | C18: 5.33 | D18: 5.46 | E18: 5.57 | F18: 5.7 | G18: 5.86 | H18: 6.38 | I18: 6.89 | J18: 7.29 | K18: 7.3735857 | L18: 7.56 | M18: 7.62 | N18: 7.62 | O18: 7.67 | P18: 7.74 | Q18: 7.74 | R18: 7.74 | S18: 7.74 | T18: 7.1908817 | U18: 6.9096288 | V18: 7.4409156 | W18: 7.518796 | X18: 8.7154145
A19: Auckland: Aotea/Great Barrier | B19: 2 and over - non 20 Hours ECE | C19: 2.67 | D19: 2.74 | E19: 2.79 | F19: 2.86 | G19: 2.94 | H19: 3.2 | I19: 3.47 | J19: 3.66 | K19: 3.7079134 | L19: 3.8 | M19: 3.83 | N19: 3.83 | O19: 3.86 | P19: 3.9 | Q19: 3.9 | R19: 3.9 | S19: 3.9 | T19: 3.5916293 | U19: 3.4802711 | V19: 3.7311551 | W19: 3.7900076 | X19: 4.5068782
A20: Auckland: Aotea/Great Barrier | B20: Equity | C20: 0.41425696 | D20: 0.68047771 | E20: 0.9811853 | F20: 1.1120212 | G20: 0.79661972 | H20: 0.8575 | I20: 1.0742591 | J20: 0.9983965 | K20: 0.90699892 | L20: 0.94059474 | M20: 1.0662712 | N20: 0.68623745 | O20: 1.0902238 | P20: 1.204385 | Q20: 1.1813046 | R20: 1.190161 | S20: 1.0353263 | T20: 0.88155146 | U20: 0.72991241 | V20: 0.7100955 | W20: 0.76842034 | X20: 0.82249977
A21: Auckland: Aotea/Great Barrier | B21: Targeted Funding for Disadvantage | C21: 0 | D21: 0 | E21: 0 | F21: 0 | G21: 0 | H21: 0 | I21: 0 | J21: 0 | K21: 0 | L21: 0 | M21: 0 | N21: 0 | O21: 0 | P21: 0 | Q21: 0 | R21: 0 | S21: 0.031483777 | T21: 0.035037718 | U21: 0 | V21: 0 | W21: 0 | X21: 0
A22: Auckland: Aotea/Great Barrier | B22: Total | C22: 3.5929485 | D22: 3.9887267 | E22: 4.1716054 | F22: 4.3605472 | G22: 4.3025239 | H22: 5.00355 | I22: 5.4637445 | J22: 5.7140598 | K22: 5.2104358 | L22: 5.3117024 | M22: 5.8643094 | N22: 6.0902599 | O22: 6.4753106 | P22: 6.0473575 | Q22: 6.4636135 | R22: 6.5304965 | S22: 6.4389683 | T22: 5.7003665 | U22: 5.1968817 | V22: 5.6033236 | W22: 5.8658898 | X22: 7.9825793
A23: Auckland: Devonport-Takapuna | B23: 20 Hours ECE | I23: 7.2970616 | J23: 8.3377407 | K23: 8.9057121 | L23: 9.0487348 | M23: 8.9788071 | N23: 9.024132 | O23: 9.3603223 | P23: 9.6597148 | Q23: 9.8182113 | R23: 9.9182952 | S23: 9.9505929 | T23: 10.038578 | U23: 10.269935 | V23: 10.783035 | W23: 11.211359 | X23: 11.974748
A24: Auckland: Devonport-Takapuna | B24: Under 2's | C24: 4.9882708 | D24: 5.0779502 | E24: 5.2682419 | F24: 5.6899263 | G24: 6.5860621 | H24: 7.6371015 | I24: 8.7759874 | J24: 9.1437301 | K24: 10.174144 | L24: 10.2348 | M24: 10.159598 | N24: 10.268679 | O24: 10.298266 | P24: 10.392055 | Q24: 10.303 | R24: 10.047616 | S24: 9.7574014 | T24: 9.7319758 | U24: 10.035489 | V24: 10.283966 | W24: 10.399271 | X24: 10.986634
A25: Auckland: Devonport-Takapuna | B25: 2 and over - non 20 Hours ECE | C25: 2.6774371 | D25: 2.7393775 | E25: 2.833242 | F25: 3.0885528 | G25: 3.6526767 | H25: 4.2178159 | I25: 4.51324 | J25: 5.2680373 | K25: 5.674952 | L25: 5.6642113 | M25: 5.5799909 | N25: 5.6155917 | O25: 5.663554 | P25: 5.7256803 | Q25: 5.7286532 | R25: 5.6801259 | S25: 5.5755906 | T25: 5.6074556 | U25: 5.7540211 | V25: 5.9164161 | W25: 6.1133932 | X25: 6.5542571
A26: Auckland: Devonport-Takapuna | B26: Equity | C26: 0.00061924393 | D26: 0.0011860655 | E26: 0.0011224384 | F26: 0.0011241663 | G26: 0.0011259264 | H26: 0.0011175955 | I26: 0.001054115 | J26: 0.0011938897 | K26: 0.0010919722 | L26: 0.0010245292 | M26: 0.0010000241 | N26: 0.0016142503 | O26: 0.0020920745 | P26: 0.0020338751 | Q26: 0.0027485459 | R26: 0.0045130105 | S26: 0.0058076624 | T26: 0.0055184469 | U26: 0.005624372 | V26: 0.005473134 | W26: 0.0057355877 | X26: 0.007792284
A27: Auckland: Devonport-Takapuna | B27: Targeted Funding for Disadvantage | C27: 0 | D27: 0 | E27: 0 | F27: 0 | G27: 0 | H27: 0 | I27: 0 | J27: 0 | K27: 0 | L27: 0 | M27: 0 | N27: 0 | O27: 0 | P27: 0 | Q27: 0 | R27: 0 | S27: 0 | T27: 0.00039626681 | U27: 0.00080388878 | V27: 0.00026566427 | W27: 0.0011772167 | X27: 0.001746713
A28: Auckland: Devonport-Takapuna | B28: Total | C28: 3.0761808 | D28: 3.1381683 | E28: 3.2497057 | F28: 3.533707 | G28: 4.1588962 | H28: 4.8215887 | I28: 6.1753608 | J28: 7.2123107 | K28: 7.9894181 | L28: 8.1081031 | M28: 8.0239322 | N28: 8.0832778 | O28: 8.3412951 | P28: 8.5143008 | Q28: 8.6025888 | R28: 8.5210894 | S28: 8.433222 | T28: 8.4395892 | U28: 8.6870194 | V28: 9.0545541 | W28: 9.265619 | X28: 9.7822941
A29: Auckland: Franklin | B29: 20 Hours ECE | I29: 7.4437627 | J29: 8.6093671 | K29: 9.2777268 | L29: 9.3323963 | M29: 9.4355453 | N29: 9.4638799 | O29: 9.5948762 | P29: 9.7896893 | Q29: 9.854385 | R29: 9.8927629 | S29: 9.9532181 | T29: 10.034164 | U29: 10.257388 | V29: 10.734654 | W29: 11.167461 | X29: 11.842477
A30: Auckland: Franklin | B30: Under 2's | C30: 4.9604489 | D30: 5.0722319 | E30: 5.1572912 | F30: 5.6407133 | G30: 6.4652416 | H30: 7.2447252 | I30: 7.8047534 | J30: 8.5051366 | K30: 8.8244313 | L30: 8.9273318 | M30: 9.1905014 | N30: 9.2614923 | O30: 9.6762059 | P30: 9.8385845 | Q30: 10.000691 | R30: 10.08466 | S30: 10.108572 | T30: 10.115456 | U30: 10.417781 | V30: 10.988574 | W30: 11.390499 | X30: 12.112431
A31: Auckland: Franklin | B31: 2 and over - non 20 Hours ECE | C31: 2.7702577 | D31: 2.8687342 | E31: 2.9534311 | F31: 3.206367 | G31: 3.6577966 | H31: 4.0992179 | I31: 4.1966248 | J31: 4.8430867 | K31: 5.0341922 | L31: 5.1334726 | M31: 5.2239409 | N31: 5.2686285 | O31: 5.3936012 | P31: 5.5385867 | Q31: 5.5997886 | R31: 5.6337824 | S31: 5.6510936 | T31: 5.6649617 | U31: 5.7709065 | V31: 6.05756 | W31: 6.3740705 | X31: 6.8030733
A32: Auckland: Franklin | B32: Equity | C32: 0.012282871 | D32: 0.020087687 | E32: 0.023714096 | F32: 0.02155817 | G32: 0.027571959 | H32: 0.030722713 | I32: 0.030327014 | J32: 0.03132994 | K32: 0.028948406 | L32: 0.026136991 | M32: 0.034335414 | N32: 0.053869384 | O32: 0.07473962 | P32: 0.082214416 | Q32: 0.080273575 | R32: 0.077371438 | S32: 0.081147442 | T32: 0.10826036 | U32: 0.12099153 | V32: 0.1190953 | W32: 0.11507772 | X32: 0.10791377
A33: Auckland: Franklin | B33: Targeted Funding for Disadvantage | C33: 0 | D33: 0 | E33: 0 | F33: 0 | G33: 0 | H33: 0 | I33: 0 | J33: 0 | K33: 0 | L33: 0 | M33: 0 | N33: 0 | O33: 0 | P33: 0 | Q33: 0 | R33: 0 | S33: 0.012332598 | T33: 0.023968574 | U33: 0.024851176 | V33: 0.026946001 | W33: 0.032071568 | X33: 0.031760181
A34: Auckland: Franklin | B34: Total | C34: 3.0770858 | D34: 3.1570064 | E34: 3.2671321 | F34: 3.5522257 | G34: 4.090262 | H34: 4.6400018 | I34: 6.2426252 | J34: 7.3444017 | K34: 7.7518302 | L34: 7.9291137 | M34: 8.1438016 | N34: 8.2000138 | O34: 8.3902605 | P34: 8.5297454 | Q34: 8.608813 | R34: 8.6031209 | S34: 8.6371636 | T34: 8.6480369 | U34: 8.8343997 | V34: 9.3157533 | W34: 9.7401884 | X34: 10.241873
A35: Auckland: Henderson-Massey | B35: 20 Hours ECE | I35: 7.3928919 | J35: 8.5444838 | K35: 9.0591404 | L35: 9.2010787 | M35: 9.2558307 | N35: 9.307536 | O35: 9.6792801 | P35: 9.8481078 | Q35: 9.8623907 | R35: 9.8707487 | S35: 9.8926388 | T35: 9.9995489 | U35: 10.242405 | V35: 10.742588 | W35: 11.19422 | X35: 11.919732
A36: Auckland: Henderson-Massey | B36: Under 2's | C36: 5.064656 | D36: 5.1015612 | E36: 5.3128106 | F36: 5.6323007 | G36: 6.5534896 | H36: 7.2360199 | I36: 8.2095479 | J36: 8.9101034 | K36: 9.6917211 | L36: 9.7436786 | M36: 9.8057642 | N36: 9.8177465 | O36: 9.9715742 | P36: 10.089105 | Q36: 10.171578 | R36: 10.077595 | S36: 9.847473 | T36: 9.9398126 | U36: 10.153528 | V36: 10.578267 | W36: 10.838628 | X36: 11.615423
A37: Auckland: Henderson-Massey | B37: 2 and over - non 20 Hours ECE | C37: 2.6687333 | D37: 2.7367839 | E37: 2.8692158 | F37: 3.0990026 | G37: 3.6450305 | H37: 4.0334302 | I37: 4.2249374 | J37: 5.0331727 | K37: 5.396495 | L37: 5.3305532 | M37: 5.325878 | N37: 5.3807963 | O37: 5.5082274 | P37: 5.5854312 | Q37: 5.5918248 | R37: 5.6147834 | S37: 5.5835819 | T37: 5.6224345 | U37: 5.7740938 | V37: 6.0815754 | W37: 6.3372494 | X37: 6.7360994
A38: Auckland: Henderson-Massey | B38: Equity | C38: 0.02100392 | D38: 0.039466462 | E38: 0.039688634 | F38: 0.040795717 | G38: 0.039253109 | H38: 0.041068874 | I38: 0.046182949 | J38: 0.05392866 | K38: 0.050737798 | L38: 0.050409299 | M38: 0.077481217 | N38: 0.1372751 | O38: 0.17916286 | P38: 0.17029394 | Q38: 0.15906213 | R38: 0.15855669 | S38: 0.17780277 | T38: 0.1846741 | U38: 0.18459359 | V38: 0.18722185 | W38: 0.19271695 | X38: 0.19008863
A39: Auckland: Henderson-Massey | B39: Targeted Funding for Disadvantage | C39: 0 | D39: 0 | E39: 0 | F39: 0 | G39: 0 | H39: 0 | I39: 0 | J39: 0 | K39: 0 | L39: 0 | M39: 0 | N39: 0 | O39: 0 | P39: 0 | Q39: 0 | R39: 0 | S39: 0.021147399 | T39: 0.041234201 | U39: 0.043275629 | V39: 0.048070278 | W39: 0.051635154 | X39: 0.052869218
A40: Auckland: Henderson-Massey | B40: Total | C40: 3.0851649 | D40: 3.1708623 | E40: 3.3112634 | F40: 3.548118 | G40: 4.1703095 | H40: 4.6199063 | I40: 6.0993147 | J40: 7.2849422 | K40: 7.8708184 | L40: 7.9751001 | M40: 8.0688407 | N40: 8.2330654 | O40: 8.5719595 | P40: 8.6759549 | Q40: 8.6844498 | R40: 8.628861 | S40: 8.6301584 | T40: 8.6584454 | U40: 8.8515902 | V40: 9.2853775 | W40: 9.5924511 | X40: 10.171216
A41: Auckland: Hibiscus and Bays | B41: 20 Hours ECE | I41: 7.3523225 | J41: 8.4057452 | K41: 9.4304662 | L41: 9.7672355 | M41: 9.5898736 | N41: 9.5645264 | O41: 9.6225282 | P41: 9.7720609 | Q41: 9.8368552 | R41: 9.9079525 | S41: 9.9307684 | T41: 10.020717 | U41: 10.259087 | V41: 10.843656 | W41: 11.245481 | X41: 11.985442
A42: Auckland: Hibiscus and Bays | B42: Under 2's | C42: 5.1760968 | D42: 5.0667371 | E42: 5.3543031 | F42: 5.7341697 | G42: 6.6587315 | H42: 7.3915381 | I42: 8.0832524 | J42: 8.6153687 | K42: 9.2126034 | L42: 9.1701262 | M42: 9.214805 | N42: 9.0626589 | O42: 9.2676512 | P42: 9.5161145 | Q42: 9.6821775 | R42: 9.8353503 | S42: 9.7178143 | T42: 9.2248936 | U42: 9.4479061 | V42: 10.169498 | W42: 10.4335 | X42: 11.29317
A43: Auckland: Hibiscus and Bays | B43: 2 and over - non 20 Hours ECE | C43: 2.7430967 | D43: 2.8323318 | E43: 2.9462888 | F43: 3.2188721 | G43: 3.832693 | H43: 4.2677482 | I43: 4.3336164 | J43: 5.117445 | K43: 5.31248 | L43: 5.2879154 | M43: 5.3319825 | N43: 5.3147419 | O43: 5.3573136 | P43: 5.4039104 | Q43: 5.5026821 | R43: 5.587616 | S43: 5.613734 | T43: 5.5672926 | U43: 5.6110679 | V43: 5.8752819 | W43: 6.0610121 | X43: 6.5064635
A44: Auckland: Hibiscus and Bays | B44: Equity | C44: 0 | D44: 0 | E44: 0 | F44: 0 | G44: 0 | H44: 0 | I44: 0 | J44: 0 | K44: 0 | L44: 0 | M44: 0 | N44: 0.010846822 | O44: 0.042936281 | P44: 0.038128568 | Q44: 0.023786658 | R44: 0.011844693 | S44: 0.010457649 | T44: 0.011475734 | U44: 0.0099483611 | V44: 0.010107586 | W44: 0.010753052 | X44: 0.0050032249
A45: Auckland: Hibiscus and Bays | B45: Targeted Funding for Disadvantage | C45: 0 | D45: 0 | E45: 0 | F45: 0 | G45: 0 | H45: 0 | I45: 0 | J45: 0 | K45: 0 | L45: 0 | M45: 0 | N45: 0 | O45: 0 | P45: 0 | Q45: 0 | R45: 0 | S45: 0.0044217919 | T45: 0.0075582606 | U45: 0.0074256644 | V45: 0.0067775256 | W45: 0.0081951305 | X45: 0.011340481
A46: Auckland: Hibiscus and Bays | B46: Total | C46: 2.9996732 | D46: 3.0665765 | E46: 3.2392965 | F46: 3.5546371 | G46: 4.2292097 | H46: 4.6846584 | I46: 6.2526901 | J46: 7.3401782 | K46: 8.1603435 | L46: 8.3904274 | M46: 8.3787433 | N46: 8.2791749 | O46: 8.3822209 | P46: 8.4930928 | Q46: 8.5390435 | R46: 8.5462651 | S46: 8.5170789 | T46: 8.4714842 | U46: 8.5963656 | V46: 9.0775602 | W46: 9.3243751 | X46: 9.9387141
A47: Auckland: Howick | B47: 20 Hours ECE | I47: 7.6517269 | J47: 8.5542055 | K47: 9.0421902 | L47: 9.2305722 | M47: 9.1872011 | N47: 9.3525417 | O47: 9.6680422 | P47: 9.773859 | Q47: 9.8296035 | R47: 9.8567421 | S47: 9.8729375 | T47: 9.9057798 | U47: 10.136999 | V47: 10.602119 | W47: 11.006536 | X47: 11.723673
A48: Auckland: Howick | B48: Under 2's | C48: 5.0951445 | D48: 5.2131991 | E48: 5.4486416 | F48: 5.6658831 | G48: 6.3124913 | H48: 6.8821912 | I48: 7.5822202 | J48: 8.0809701 | K48: 8.492437 | L48: 8.464394 | M48: 8.6806315 | N48: 8.8685545 | O48: 9.1218775 | P48: 9.2431002 | Q48: 9.4813532 | R48: 9.4435731 | S48: 8.8915422 | T48: 8.6961494 | U48: 9.2659071 | V48: 9.8158022 | W48: 9.9822765 | X48: 10.908402
A49: Auckland: Howick | B49: 2 and over - non 20 Hours ECE | C49: 2.6921933 | D49: 2.7807088 | E49: 2.9053949 | F49: 3.1016492 | G49: 3.5647386 | H49: 3.9977766 | I49: 4.2286844 | J49: 4.9115502 | K49: 5.1624987 | L49: 5.0625126 | M49: 5.0787338 | N49: 5.2188042 | O49: 5.3362455 | P49: 5.4170191 | Q49: 5.4959362 | R49: 5.5503896 | S49: 5.4823314 | T49: 5.4028638 | U49: 5.5803418 | V49: 5.8223492 | W49: 6.1018946 | X49: 6.5521791
A50: Auckland: Howick | B50: Equity | C50: 0.0057086227 | D50: 0.01088557 | E50: 0.0088320744 | F50: 0.0069561838 | G50: 0.0078065214 | H50: 0.0078402113 | I50: 0.0071885659 | J50: 0.0080261249 | K50: 0.0071501834 | L50: 0.0071550894 | M50: 0.015296181 | N50: 0.028630826 | O50: 0.039415597 | P50: 0.035718979 | Q50: 0.026688851 | R50: 0.024255855 | S50: 0.036744924 | T50: 0.050494379 | U50: 0.058012 | V50: 0.063869235 | W50: 0.071741879 | X50: 0.069986612
A51: Auckland: Howick | B51: Targeted Funding for Disadvantage | C51: 0 | D51: 0 | E51: 0 | F51: 0 | G51: 0 | H51: 0 | I51: 0 | J51: 0 | K51: 0 | L51: 0 | M51: 0 | N51: 0 | O51: 0 | P51: 0 | Q51: 0 | R51: 0 | S51: 0.0044656158 | T51: 0.0071381359 | U51: 0.006209438 | V51: 0.0079987838 | W51: 0.0085787202 | X51: 0.011407313
A52: Auckland: Howick | B52: Total | C52: 3.1424323 | D52: 3.2464068 | E52: 3.4001322 | F52: 3.6042975 | G52: 4.1229957 | H52: 4.5878289 | I52: 6.1650939 | J52: 7.1729951 | K52: 7.592229 | L52: 7.6846142 | M52: 7.7714801 | N52: 7.9797253 | O52: 8.2528867 | P52: 8.2927496 | Q52: 8.3850275 | R52: 8.3800128 | S52: 8.2727439 | T52: 8.1930872 | U52: 8.4654514 | V52: 8.9521464 | W52: 9.1876372 | X52: 9.7956305
A53: Auckland: Kaipātiki | B53: 20 Hours ECE | I53: 7.2644884 | J53: 8.3603665 | K53: 8.8200507 | L53: 8.9739202 | M53: 9.030795 | N53: 9.1509858 | O53: 9.6178934 | P53: 9.8447726 | Q53: 9.8529994 | R53: 9.9058416 | S53: 9.9034172 | T53: 9.9665158 | U53: 10.264866 | V53: 10.793715 | W53: 11.240155 | X53: 11.950424
A54: Auckland: Kaipātiki | B54: Under 2's | C54: 4.9861184 | D54: 5.0907705 | E54: 5.2171591 | F54: 5.5261464 | G54: 6.3415876 | H54: 7.107861 | I54: 7.5960063 | J54: 8.4648061 | K54: 9.4636413 | L54: 9.6900218 | M54: 9.6299474 | N54: 9.818819 | O54: 9.994525 | P54: 9.8562008 | Q54: 9.6285489 | R54: 9.6572407 | S54: 9.5163467 | T54: 9.4050313 | U54: 10.096114 | V54: 10.757988 | W54: 11.228395 | X54: 12.074936
A55: Auckland: Kaipātiki | B55: 2 and over - non 20 Hours ECE | C55: 2.6431351 | D55: 2.7180899 | E55: 2.8278207 | F55: 3.048363 | G55: 3.5551211 | H55: 3.9380818 | I55: 4.0600289 | J55: 4.9863239 | K55: 5.3456191 | L55: 5.3855593 | M55: 5.3671304 | N55: 5.4403529 | O55: 5.5737088 | P55: 5.6298194 | Q55: 5.5881331 | R55: 5.5898293 | S55: 5.5637557 | T55: 5.5908746 | U55: 5.7757169 | V55: 6.1592354 | W55: 6.4332178 | X55: 6.910882
A56: Auckland: Kaipātiki | B56: Equity | C56: 0.0043359788 | D56: 0.010037483 | E56: 0.010202325 | F56: 0.0097726192 | G56: 0.0090423313 | H56: 0.0082152182 | I56: 0.0065869355 | J56: 0.0053658437 | K56: 0.004996087 | L56: 0.003263597 | M56: 0.005375568 | N56: 0.015495688 | O56: 0.023976752 | P56: 0.023133076 | Q56: 0.030965566 | R56: 0.022963729 | S56: 0.025763315 | T56: 0.033635321 | U56: 0.033313285 | V56: 0.01604063 | W56: 0.015657247 | X56: 0.015340662
A57: Auckland: Kaipātiki | B57: Targeted Funding for Disadvantage | C57: 0 | D57: 0 | E57: 0 | F57: 0 | G57: 0 | H57: 0 | I57: 0 | J57: 0 | K57: 0 | L57: 0 | M57: 0 | N57: 0 | O57: 0 | P57: 0 | Q57: 0 | R57: 0 | S57: 0.0049091547 | T57: 0.0078383048 | U57: 0.0058358783 | V57: 0.007517282 | W57: 0.0071791599 | X57: 0.0078579097
A58: Auckland: Kaipātiki | B58: Total | C58: 3.0742677 | D58: 3.1678156 | E58: 3.2906073 | F58: 3.5466788 | G58: 4.0705581 | H58: 4.5296238 | I58: 5.899627 | J58: 7.1095223 | K58: 7.7012543 | L58: 7.8610676 | M58: 7.9215689 | N58: 8.0529532 | O58: 8.3325644 | P58: 8.498815 | Q58: 8.4724685 | R58: 8.432372 | S58: 8.4098964 | T58: 8.3585468 | U58: 8.6973479 | V58: 9.2579871 | W58: 9.5711568 | X58: 10.248613
A59: Auckland: Māngere-Ōtāhuhu | B59: 20 Hours ECE | I59: 7.4288662 | J59: 8.4869993 | K59: 9.0434572 | L59: 9.2369229 | M59: 9.3807224 | N59: 9.5368048 | O59: 9.7313597 | P59: 9.8072815 | Q59: 9.754039 | R59: 9.6282538 | S59: 9.5999175 | T59: 9.6236082 | U59: 9.8340398 | V59: 11.683224 | W59: 12.505074 | X59: 13.531324
A60: Auckland: Māngere-Ōtāhuhu | B60: Under 2's | C60: 5.153365 | D60: 5.2616486 | E60: 5.4557782 | F60: 5.7936447 | G60: 6.7521148 | H60: 7.3307483 | I60: 8.0127339 | J60: 8.8360314 | K60: 9.619524 | L60: 9.7419722 | M60: 9.8254965 | N60: 9.9696997 | O60: 10.139948 | P60: 9.9953258 | Q60: 9.5368563 | R60: 8.9728799 | S60: 8.8260587 | T60: 8.9399585 | U60: 9.0876906 | V60: 8.5676187 | W60: 8.8966991 | X60: 9.4805239
A61: Auckland: Māngere-Ōtāhuhu | B61: 2 and over - non 20 Hours ECE | C61: 2.7174919 | D61: 2.7882169 | E61: 2.8925608 | F61: 3.0922208 | G61: 3.5681834 | H61: 3.8613203 | I61: 4.0517271 | J61: 4.9222172 | K61: 5.2189177 | L61: 5.2578054 | M61: 5.3440104 | N61: 5.4742157 | O61: 5.5859666 | P61: 5.5902911 | Q61: 5.4404668 | R61: 5.2729858 | S61: 5.2377155 | T61: 5.2647508 | U61: 5.4302506 | V61: 5.9587675 | W61: 6.220387 | X61: 6.8112924
A62: Auckland: Māngere-Ōtāhuhu | B62: Equity | C62: 0.16555237 | D62: 0.31909822 | E62: 0.30188996 | F62: 0.30165317 | G62: 0.31111974 | H62: 0.330861 | I62: 0.31542725 | J62: 0.30598392 | K62: 0.2686611 | L62: 0.25883876 | M62: 0.34973689 | N62: 0.57330669 | O62: 0.83241346 | P62: 0.83329779 | Q62: 0.80785117 | R62: 0.78359063 | S62: 0.83536142 | T62: 0.86856944 | U62: 0.90129648 | V62: 0.78950854 | W62: 0.82757221 | X62: 0.82842648
A63: Auckland: Māngere-Ōtāhuhu | B63: Targeted Funding for Disadvantage | C63: 0 | D63: 0 | E63: 0 | F63: 0 | G63: 0 | H63: 0 | I63: 0 | J63: 0 | K63: 0 | L63: 0 | M63: 0 | N63: 0 | O63: 0 | P63: 0 | Q63: 0 | R63: 0 | S63: 0.040839409 | T63: 0.075734117 | U63: 0.083962306 | V63: 0.097898711 | W63: 0.097643922 | X63: 0.10066121
A64: Auckland: Māngere-Ōtāhuhu | B64: Total | C64: 3.2955474 | D64: 3.5038914 | E64: 3.5863525 | F64: 3.825239 | G64: 4.4268956 | H64: 4.7723899 | I64: 6.4549046 | J64: 7.4796844 | K64: 8.0159178 | L64: 8.1258195 | M64: 8.3312081 | N64: 8.6742374 | O64: 9.1482261 | P64: 9.154055 | Q64: 8.9047613 | R64: 8.6005485 | S64: 8.5984594 | T64: 8.716101 | U64: 8.8945917 | V64: 9.7221428 | W64: 10.239084 | X64: 10.960361
A65: Auckland: Manurewa | B65: 20 Hours ECE | I65: 7.5594794 | J65: 8.6540899 | K65: 9.3120134 | L65: 9.4187261 | M65: 9.5076661 | N65: 9.608968 | O65: 9.7261469 | P65: 9.8530987 | Q65: 9.8266021 | R65: 9.7989102 | S65: 9.823631 | T65: 9.9008207 | U65: 10.181136 | V65: 9.3721353 | W65: 9.135481 | X65: 9.2567079
A66: Auckland: Manurewa | B66: Under 2's | C66: 4.9199317 | D66: 5.0144883 | E66: 5.1646557 | F66: 5.559366 | G66: 6.4509522 | H66: 7.1916949 | I66: 8.017954 | J66: 8.6942993 | K66: 9.5843574 | L66: 9.8164342 | M66: 9.8823916 | N66: 9.9029458 | O66: 9.8782505 | P66: 10.133689 | Q66: 10.000877 | R66: 9.7898015 | S66: 9.8366285 | T66: 9.8477335 | U66: 10.351468 | V66: 14.329103 | W66: 14.540048 | X66: 16.27233
A67: Auckland: Manurewa | B67: 2 and over - non 20 Hours ECE | C67: 2.6505681 | D67: 2.7016852 | E67: 2.7936709 | F67: 3.0192429 | G67: 3.4940901 | H67: 3.913991 | I67: 3.9546383 | J67: 4.8140473 | K67: 5.256787 | L67: 5.4082341 | M67: 5.4379837 | N67: 5.4866206 | O67: 5.5285042 | P67: 5.6385894 | Q67: 5.6066676 | R67: 5.547462 | S67: 5.552476 | T67: 5.5717351 | U67: 5.8751937 | V67: 5.6824387 | W67: 5.7477763 | X67: 6.1387346
A68: Auckland: Manurewa | B68: Equity | C68: 0.072254963 | D68: 0.13417933 | E68: 0.12983649 | F68: 0.12786361 | G68: 0.12991144 | H68: 0.12685423 | I68: 0.13139367 | J68: 0.16539142 | K68: 0.16775736 | L68: 0.16312901 | M68: 0.28031727 | N68: 0.47362738 | O68: 0.72793136 | P68: 0.74531468 | Q68: 0.74695789 | R68: 0.74680293 | S68: 0.76412526 | T68: 0.77803373 | U68: 0.78790591 | V68: 0.40232481 | W68: 0.36477033 | X68: 0.36463567
A69: Auckland: Manurewa | B69: Targeted Funding for Disadvantage | C69: 0 | D69: 0 | E69: 0 | F69: 0 | G69: 0 | H69: 0 | I69: 0 | J69: 0 | K69: 0 | L69: 0 | M69: 0 | N69: 0 | O69: 0 | P69: 0 | Q69: 0 | R69: 0 | S69: 0.051240248 | T69: 0.10271977 | U69: 0.10041762 | V69: 0.047767047 | W69: 0.04185591 | X69: 0.043552205
A70: Auckland: Manurewa | B70: Total | C70: 3.1448292 | D70: 3.2652751 | E70: 3.3332104 | F70: 3.5916672 | G70: 4.1832333 | H70: 4.6497547 | I70: 5.9792164 | J70: 7.3120147 | K70: 8.114837 | L70: 8.3764974 | M70: 8.6047684 | N70: 8.8252162 | O70: 9.0920893 | P70: 9.2150203 | Q70: 9.0959747 | R70: 8.8931695 | S70: 8.9516112 | T70: 9.0768381 | U70: 9.4288786 | V70: 9.1761199 | W70: 9.0826867 | X70: 9.5405959
A71: Auckland: Maungakiekie-Tāmaki | B71: 20 Hours ECE | I71: 7.376919 | J71: 8.2332695 | K71: 8.7336124 | L71: 8.7755233 | M71: 9.0143671 | N71: 9.1803438 | O71: 9.407817 | P71: 9.5357904 | Q71: 9.4733984 | R71: 9.5097382 | S71: 9.5794116 | T71: 9.6844501 | U71: 9.9703434 | V71: 10.58183 | W71: 11.571466 | X71: 12.497479
A72: Auckland: Maungakiekie-Tāmaki | B72: Under 2's | C72: 4.9612318 | D72: 5.0479858 | E72: 5.2035602 | F72: 5.5121158 | G72: 6.2058194 | H72: 6.8949265 | I72: 7.8110676 | J72: 8.3177222 | K72: 9.0514702 | L72: 8.8881908 | M72: 9.1081629 | N72: 9.3397177 | O72: 9.4996021 | P72: 9.196622 | Q72: 8.7681007 | R72: 8.8988364 | S72: 9.0786181 | T72: 9.2555981 | U72: 9.5951353 | V72: 9.0868343 | W72: 9.9935392 | X72: 10.232234
A73: Auckland: Maungakiekie-Tāmaki | B73: 2 and over - non 20 Hours ECE | C73: 2.6119791 | D73: 2.6681716 | E73: 2.763788 | F73: 2.9517945 | G73: 3.4084282 | H73: 3.7567942 | I73: 4.0111086 | J73: 4.6505553 | K73: 4.927755 | L73: 4.9018247 | M73: 5.0683481 | N73: 5.1311121 | O73: 5.2250488 | P73: 5.1614459 | Q73: 5.0129227 | R73: 5.1072352 | S73: 5.1319888 | T73: 5.253453 | U73: 5.4978444 | V73: 6.3054951 | W73: 7.0887231 | X73: 7.2286593
A74: Auckland: Maungakiekie-Tāmaki | B74: Equity | C74: 0.074545226 | D74: 0.13882541 | E74: 0.13848143 | F74: 0.13785044 | G74: 0.12540307 | H74: 0.11207349 | I74: 0.1039256 | J74: 0.12379112 | K74: 0.11424988 | L74: 0.11179952 | M74: 0.12518006 | N74: 0.1991578 | O74: 0.26867769 | P74: 0.30859585 | Q74: 0.38536336 | R74: 0.41617982 | S74: 0.38589234 | T74: 0.38694743 | U74: 0.39168325 | V74: 0.90251818 | W74: 0.95547552 | X74: 0.96211322
A75: Auckland: Maungakiekie-Tāmaki | B75: Targeted Funding for Disadvantage | C75: 0 | D75: 0 | E75: 0 | F75: 0 | G75: 0 | H75: 0 | I75: 0 | J75: 0 | K75: 0 | L75: 0 | M75: 0 | N75: 0 | O75: 0 | P75: 0 | Q75: 0 | R75: 0 | S75: 0.025191789 | T75: 0.045431081 | U75: 0.0435091 | V75: 0.091226438 | W75: 0.10029212 | X75: 0.096736386
A76: Auckland: Maungakiekie-Tāmaki | B76: Total | C76: 3.2623838 | D76: 3.3580502 | E76: 3.4888612 | F76: 3.70381 | G76: 4.2090073 | H76: 4.6437975 | I76: 6.003891 | J76: 6.9593849 | K76: 7.42293 | L76: 7.4099472 | M76: 7.7181667 | N76: 8.0062882 | O76: 8.3262303 | P76: 8.2561303 | Q76: 8.0748555 | R76: 8.1156667 | S76: 8.1784598 | T76: 8.3125436 | U76: 8.5879415 | V76: 9.6661099 | W76: 10.617332 | X76: 11.01592
A77: Auckland: Ōrākei | B77: 20 Hours ECE | I77: 7.4097141 | J77: 8.6087282 | K77: 9.1692365 | L77: 9.2533473 | M77: 9.2142309 | N77: 9.3449401 | O77: 9.6861965 | P77: 9.8668787 | Q77: 9.8792238 | R77: 9.9052068 | S77: 9.9567107 | T77: 10.043862 | U77: 10.289685 | V77: 13.368962 | W77: 16.028142 | X77: 17.68887
A78: Auckland: Ōrākei | B78: Under 2's | C78: 5.0234156 | D78: 5.1483996 | E78: 5.4391445 | F78: 5.6842801 | G78: 6.5519391 | H78: 7.1493273 | I78: 7.8655735 | J78: 8.3873934 | K78: 8.9135079 | L78: 9.1372522 | M78: 9.537845 | N78: 9.6877102 | O78: 9.7451882 | P78: 9.8795018 | Q78: 9.8504386 | R78: 9.9016995 | S78: 10.066063 | T78: 10.259762 | U78: 10.500748 | V78: 12.634508 | W78: 13.69337 | X78: 13.914747
A79: Auckland: Ōrākei | B79: 2 and over - non 20 Hours ECE | C79: 2.7149797 | D79: 2.8006908 | E79: 2.9392034 | F79: 3.1521473 | G79: 3.6637115 | H79: 4.0931934 | I79: 4.34559 | J79: 5.0874228 | K79: 5.305946 | L79: 5.3439143 | M79: 5.4122144 | N79: 5.4719478 | O79: 5.5263877 | P79: 5.6258678 | Q79: 5.6327418 | R79: 5.6469073 | S79: 5.6934409 | T79: 5.7758139 | U79: 5.9404512 | V79: 9.7526884 | W79: 10.244702 | X79: 10.214746
A80: Auckland: Ōrākei | B80: Equity | C80: 0.0030170407 | D80: 0.0063646056 | E80: 0.00625134 | F80: 0.011645344 | G80: 0.015031349 | H80: 0.016435821 | I80: 0.017953813 | J80: 0.021889708 | K80: 0.021404552 | L80: 0.020023986 | M80: 0.022910146 | N80: 0.037861272 | O80: 0.051617956 | P80: 0.046916048 | Q80: 0.046816268 | R80: 0.047009354 | S80: 0.047022643 | T80: 0.046298502 | U80: 0.051287784 | V80: 0.74860311 | W80: 0.80684763 | X80: 0.80364762
A81: Auckland: Ōrākei | B81: Targeted Funding for Disadvantage | C81: 0 | D81: 0 | E81: 0 | F81: 0 | G81: 0 | H81: 0 | I81: 0 | J81: 0 | K81: 0 | L81: 0 | M81: 0 | N81: 0 | O81: 0 | P81: 0 | Q81: 0 | R81: 0 | S81: 0.0027227895 | T81: 0.0052836401 | U81: 0.0050129775 | V81: 0.082211242 | W81: 0.082673618 | X81: 0.082354797
A82: Auckland: Ōrākei | B82: Total | C82: 3.0589975 | D82: 3.1458934 | E82: 3.3141312 | F82: 3.5668361 | G82: 4.1370333 | H82: 4.6182455 | I82: 5.9741526 | J82: 7.2520559 | K82: 7.881193 | L82: 8.0094983 | M82: 8.1448794 | N82: 8.2591737 | O82: 8.4660546 | P82: 8.594787 | Q82: 8.5480244 | R82: 8.5341118 | S82: 8.6425095 | T82: 8.7010836 | U82: 8.9277877 | V82: 12.91623 | W82: 14.481668 | X82: 15.101049
A83: Auckland: Ōtara-Papatoetoe | B83: 20 Hours ECE | I83: 7.6876144 | J83: 8.6440159 | K83: 9.0772306 | L83: 9.1575296 | M83: 9.3554521 | N83: 9.4998957 | O83: 9.6544935 | P83: 9.6850334 | Q83: 9.570434 | R83: 9.4664774 | S83: 9.4453453 | T83: 9.5752184 | U83: 9.8599261 | V83: 3.3574183 | W83: 3.620648 | X83: 4.0075202
A84: Auckland: Ōtara-Papatoetoe | B84: Under 2's | C84: 5.120317 | D84: 5.2180087 | E84: 5.3790922 | F84: 5.6572275 | G84: 6.3711313 | H84: 7.1512475 | I84: 7.8661909 | J84: 8.4716176 | K84: 9.2267428 | L84: 9.2879605 | M84: 9.341074 | N84: 9.3556475 | O84: 9.0367675 | P84: 8.7475647 | Q84: 8.4772534 | R84: 8.2705872 | S84: 8.2587794 | T84: 8.5225256 | U84: 8.9695956 | V84: 2.4019191 | W84: 2.5317314 | X84: 3.1251177
A85: Auckland: Ōtara-Papatoetoe | B85: 2 and over - non 20 Hours ECE | C85: 2.687503 | D85: 2.749027 | E85: 2.850847 | F85: 3.0564771 | G85: 3.4979512 | H85: 3.9501553 | I85: 4.0674387 | J85: 4.9116504 | K85: 5.28474 | L85: 5.1821085 | M85: 5.1846207 | N85: 5.267654 | O85: 5.2395877 | P85: 5.2054704 | Q85: 5.0744793 | R85: 4.9614032 | S85: 4.9419117 | T85: 5.1053723 | U85: 5.3526961 | V85: 1.3230257 | W85: 1.507075 | X85: 1.7122959
A86: Auckland: Ōtara-Papatoetoe | B86: Equity | C86: 0.13618842 | D86: 0.24797901 | E86: 0.2473335 | F86: 0.24530685 | G86: 0.23501154 | H86: 0.22537149 | I86: 0.21573146 | J86: 0.23861449 | K86: 0.21370028 | L86: 0.21271913 | M86: 0.29500576 | N86: 0.50026518 | O86: 0.69893956 | P86: 0.70906409 | Q86: 0.70978097 | R86: 0.73317597 | S86: 0.7805458 | T86: 0.76710671 | U86: 0.77701598 | V86: 0.046755608 | W86: 0.053571328 | X86: 0.058045834
A87: Auckland: Ōtara-Papatoetoe | B87: Targeted Funding for Disadvantage | C87: 0 | D87: 0 | E87: 0 | F87: 0 | G87: 0 | H87: 0 | I87: 0 | J87: 0 | K87: 0 | L87: 0 | M87: 0 | N87: 0 | O87: 0 | P87: 0 | Q87: 0 | R87: 0 | S87: 0.038053507 | T87: 0.074826013 | U87: 0.070328535 | V87: 0.0067964705 | W87: 0.0087138817 | X87: 0.0085881427
A88: Auckland: Ōtara-Papatoetoe | B88: Total | C88: 3.2574747 | D88: 3.448826 | E88: 3.5849228 | F88: 3.7771224 | G88: 4.2666238 | H88: 4.8174576 | I88: 6.4216632 | J88: 7.4794272 | K88: 7.9815191 | L88: 8.0470821 | M88: 8.2921223 | N88: 8.5826348 | O88: 8.770253 | P88: 8.674851 | Q88: 8.4451939 | R88: 8.2298361 | S88: 8.2579813 | T88: 8.3945786 | U88: 8.6926634 | V88: 2.4067946 | W88: 2.6111617 | X88: 2.9579551
A89: Auckland: Papakura | B89: 20 Hours ECE | I89: 7.7578928 | J89: 9.056322 | K89: 9.5690114 | L89: 9.4732574 | M89: 9.5652116 | N89: 9.6530547 | O89: 9.7716925 | P89: 9.8898809 | Q89: 9.9165373 | R89: 9.9244663 | S89: 9.9396373 | T89: 9.9947212 | U89: 10.234915 | V89: 8.294416 | W89: 8.5301243 | X89: 9.1308508
A90: Auckland: Papakura | B90: Under 2's | C90: 4.962847 | D90: 5.0839935 | E90: 5.1663169 | F90: 5.4582063 | G90: 6.4235914 | H90: 6.9583165 | I90: 7.7684167 | J90: 8.414434 | K90: 9.1256443 | L90: 9.2207711 | M90: 9.4499801 | N90: 9.598774 | O90: 9.6997524 | P90: 9.7988189 | Q90: 9.9413478 | R90: 9.9212746 | S90: 10.004606 | T90: 10.154604 | U90: 10.542299 | V90: 8.5352118 | W90: 8.3009641 | X90: 9.8563093
A91: Auckland: Papakura | B91: 2 and over - non 20 Hours ECE | C91: 2.6746651 | D91: 2.764199 | E91: 2.8725705 | F91: 3.0786336 | G91: 3.5184329 | H91: 3.8412 | I91: 3.9309083 | J91: 4.6993645 | K91: 5.0363992 | L91: 5.0889435 | M91: 5.1473145 | N91: 5.283504 | O91: 5.4351016 | P91: 5.5231606 | Q91: 5.5575745 | R91: 5.6125005 | S91: 5.6267251 | T91: 5.6728204 | U91: 5.9210327 | V91: 3.6421179 | W91: 4.0736598 | X91: 4.2622476
A92: Auckland: Papakura | B92: Equity | C92: 0.057588843 | D92: 0.10908258 | E92: 0.10438953 | F92: 0.096930463 | G92: 0.091044877 | H92: 0.085481712 | I92: 0.083082796 | J92: 0.097384593 | K92: 0.092677974 | L92: 0.095851055 | M92: 0.18809199 | N92: 0.33351933 | O92: 0.49246571 | P92: 0.54279882 | Q92: 0.55775419 | R92: 0.54106635 | S92: 0.56114192 | T92: 0.55743007 | U92: 0.55855778 | V92: 0.011407374 | W92: 0.010074105 | X92: 0.010528057
A93: Auckland: Papakura | B93: Targeted Funding for Disadvantage | C93: 0 | D93: 0 | E93: 0 | F93: 0 | G93: 0 | H93: 0 | I93: 0 | J93: 0 | K93: 0 | L93: 0 | M93: 0 | N93: 0 | O93: 0 | P93: 0 | Q93: 0 | R93: 0 | S93: 0.041230998 | T93: 0.07648221 | U93: 0.068800939 | V93: 0.0079486797 | W93: 0.0078474896 | X93: 0.0084800834
A94: Auckland: Papakura | B94: Total | C94: 3.1052458 | D94: 3.2011858 | E94: 3.3565835 | F94: 3.5728568 | G94: 4.0979858 | H94: 4.4882746 | I94: 6.2730792 | J94: 7.4011164 | K94: 7.949781 | L94: 8.0380822 | M94: 8.359904 | N94: 8.762609 | O94: 8.9346351 | P94: 9.0252484 | Q94: 8.9535074 | R94: 8.8579778 | S94: 8.9459627 | T94: 8.9959835 | U94: 9.281067 | V94: 6.5998508 | W94: 6.8366708 | X94: 7.4375024
A95: Auckland: Puketāpapa | B95: 20 Hours ECE | I95: 6.9868648 | J95: 8.0341713 | K95: 8.5895049 | L95: 8.7238981 | M95: 8.8656064 | N95: 9.0428217 | O95: 9.5864684 | P95: 9.9075147 | Q95: 9.9144746 | R95: 9.9177967 | S95: 9.9284125 | T95: 10.029123 | U95: 10.308608 | V95: 28.209523 | W95: 26.679238 | X95: 26.457325
A96: Auckland: Puketāpapa | B96: Under 2's | C96: 5.036855 | D96: 5.144214 | E96: 5.3902763 | F96: 5.5929889 | G96: 6.2466895 | H96: 6.917743 | I96: 7.7020167 | J96: 9.0070727 | K96: 9.752438 | L96: 9.5588896 | M96: 9.6479925 | N96: 9.69313 | O96: 9.674147 | P96: 9.7900923 | Q96: 8.722936 | R96: 8.4818186 | S96: 8.489697 | T96: 8.8272613 | U96: 9.4557683 | V96: 34.671379 | W96: 36.469361 | X96: 33.073011
A97: Auckland: Puketāpapa | B97: 2 and over - non 20 Hours ECE | C97: 2.7125195 | D97: 2.8155154 | E97: 2.9644188 | F97: 3.22732 | G97: 3.6335587 | H97: 4.012505 | I97: 4.0678754 | J97: 5.0245865 | K97: 5.4844201 | L97: 5.4894064 | M97: 5.3346082 | N97: 5.4082072 | O97: 5.5287269 | P97: 5.6100088 | Q97: 5.3736703 | R97: 5.1465486 | S97: 5.0863193 | T97: 5.3359568 | U97: 5.698089 | V97: 19.360377 | W97: 19.06821 | X97: 17.927088
A98: Auckland: Puketāpapa | B98: Equity | C98: 0.031912132 | D98: 0.058534055 | E98: 0.049659679 | F98: 0.049146144 | G98: 0.052875884 | H98: 0.055372202 | I98: 0.048373933 | J98: 0.050700808 | K98: 0.048837108 | L98: 0.045518102 | M98: 0.069457705 | N98: 0.12589693 | O98: 0.1854294 | P98: 0.19769529 | Q98: 0.1753036 | R98: 0.17830019 | S98: 0.16619782 | T98: 0.1591933 | U98: 0.16851254 | V98: 0.0048119913 | W98: 0.0049167922 | X98: 0.0047220451
A99: Auckland: Puketāpapa | B99: Targeted Funding for Disadvantage | C99: 0 | D99: 0 | E99: 0 | F99: 0 | G99: 0 | H99: 0 | I99: 0 | J99: 0 | K99: 0 | L99: 0 | M99: 0 | N99: 0 | O99: 0 | P99: 0 | Q99: 0 | R99: 0 | S99: 0.013141204 | T99: 0.025843598 | U99: 0.027567025 | V99: 0.004569037 | W99: 0.0074804733 | X99: 0.014209214
A100: Auckland: Puketāpapa | B100: Total | C100: 3.0947101 | D100: 3.2674404 | E100: 3.4416803 | F100: 3.7059008 | G100: 4.188758 | H100: 4.6472097 | I100: 5.9011957 | J100: 7.0821812 | K100: 7.7319712 | L100: 7.8582553 | M100: 7.8662242 | N100: 8.1128215 | O100: 8.5686458 | P100: 8.8423511 | Q100: 8.5620036 | R100: 8.2171093 | S100: 8.1049876 | T100: 8.2973792 | U100: 8.7797566 | V100: 26.40661 | W100: 25.796285 | X100: 24.678631
A101: Auckland: Rodney | B101: 20 Hours ECE | I101: 7.7418137 | J101: 8.9771654 | K101: 9.7982242 | L101: 9.9738913 | M101: 9.8360467 | N101: 9.7650706 | O101: 9.8211483 | P101: 9.9318607 | Q101: 9.9498395 | R101: 9.9445147 | S101: 9.9525075 | T101: 10.023556 | U101: 10.216085 | V101: 1.0728031 | W101: 0.98728268 | X101: 1.0574556
...

Sheet EXP13
A1: ='Table Index'!J17 -> Entitlement funding, equity funding and targeted funding for disadvantage per funded child hour by Education Area and programme ($, GST exclusive) | M1: About the data in this table | P1: Table Index
A3: Click on arrow to select (filter) the information you need
A4: Education Area 17 | B4: Programme 14 | C4: 2001/02 | D4: 2002/03 | E4: 2003/04 | F4: 2004/05 | G4: 2005/06 | H4: 2006/07 | I4: 2007/08 | J4: 2008/09 | K4: 2009/10 | L4: 2010/11 | M4: 2011/12 | N4: 2012/13 | O4: 2013/14 | P4: 2014/15 | Q4: 2015/16 | R4: 2016/17 | S4: 2017/18 | T4: 2018/19 | U4: 2019/20 | V4: 2020/21 | W4: 2021/22 | X4: 2022/23
A5: Tai Tokerau | B5: 20 Hours ECE | I5: 7.5546104 | J5: 9.6213963 | K5: 9.8841558 | L5: 9.5888704 | M5: 9.4509598 | N5: 9.4479226 | O5: 9.4922471 | P5: 9.5771993 | Q5: 9.6221855 | R5: 9.6792853 | S5: 9.6806955 | T5: 9.7482178 | U5: 10.141882 | V5: 10.746083 | W5: 11.214271 | X5: 11.865382
A6: Tai Tokerau | B6: Under 2's | C6: 5.0840031 | D6: 5.1829374 | E6: 5.324283 | F6: 5.5779079 | G6: 6.3147831 | H6: 7.1038651 | I6: 8.0272282 | J6: 8.4056373 | K6: 8.868365 | L6: 8.8667015 | M6: 8.9630266 | N6: 8.9940916 | O6: 9.1664791 | P6: 9.331711 | Q6: 9.3533677 | R6: 9.3514875 | S6: 9.3982833 | T6: 9.4895584 | U6: 10.026842 | V6: 10.674246 | W6: 11.046661 | X6: 11.748244
A7: Tai Tokerau | B7: 2 and over - non 20 Hours ECE | C7: 2.7197388 | D7: 2.787131 | E7: 2.8986384 | F7: 3.1020404 | G7: 3.4971196 | H7: 3.9367891 | I7: 4.0550782 | J7: 4.6160844 | K7: 4.7929211 | L7: 4.7640554 | M7: 4.810651 | N7: 4.9368613 | O7: 5.0257122 | P7: 5.174393 | Q7: 5.2422905 | R7: 5.2543749 | S7: 5.2608789 | T7: 5.3223822 | U7: 5.7472491 | V7: 6.2397175 | W7: 6.5374265 | X7: 6.9149635
A8: Tai Tokerau | B8: Equity | C8: 0.12920307 | D8: 0.22465047 | E8: 0.21617783 | F8: 0.20450546 | G8: 0.19978227 | H8: 0.19007682 | I8: 0.17069199 | J8: 0.18165011 | K8: 0.17116872 | L8: 0.17382859 | M8: 0.21845242 | N8: 0.34485353 | O8: 0.47278553 | P8: 0.47574592 | Q8: 0.47253397 | R8: 0.49664778 | S8: 0.51493517 | T8: 0.51558246 | U8: 0.5258659 | V8: 0.51718464 | W8: 0.51093825 | X8: 0.51083015
A9: Tai Tokerau | B9: Targeted Funding for Disadvantage | C9: 0 | D9: 0 | E9: 0 | F9: 0 | G9: 0 | H9: 0 | I9: 0 | J9: 0 | K9: 0 | L9: 0 | M9: 0 | N9: 0 | O9: 0 | P9: 0 | Q9: 0 | R9: 0 | S9: 0.042988191 | T9: 0.084482531 | U9: 0.082969394 | V9: 0.084422172 | W9: 0.086125799 | X9: 0.087666796
A10: Tai Tokerau | B10: Total | C10: 3.291475 | D10: 3.4636187 | E10: 3.5650191 | F10: 3.7803786 | G10: 4.248369 | H10: 4.7670504 | I10: 6.2751274 | J10: 7.6393537 | K10: 7.934207 | L10: 7.8701504 | M10: 8.0085301 | N10: 8.1805184 | O10: 8.4334988 | P10: 8.5294581 | Q10: 8.5449958 | R10: 8.5723871 | S10: 8.6269825 | T10: 8.7009136 | U10: 9.138071 | V10: 9.7570197 | W10: 10.087713 | X10: 10.655315
A11: Tāmaki Herenga Manawa | B11: 20 Hours ECE | I11: 7.4209683 | J11: 8.4938365 | K11: 8.9854901 | L11: 9.0492175 | M11: 9.1222791 | N11: 9.3020951 | O11: 9.6625729 | P11: 9.8369766 | Q11: 9.8522652 | R11: 9.8795004 | S11: 9.9142226 | T11: 9.9880266 | U11: 10.228087 | V11: 10.697312 | W11: 11.140506 | X11: 11.859059
A12: Tāmaki Herenga Manawa | B12: Under 2's | C12: 5.0427523 | D12: 5.1739562 | E12: 5.4004592 | F12: 5.7132264 | G12: 6.6483111 | H12: 7.4093105 | I12: 8.3978401 | J12: 9.1710862 | K12: 9.8485723 | L12: 9.8046526 | M12: 9.9058844 | N12: 9.9419557 | O12: 10.015703 | P12: 9.8163333 | Q12: 9.5748394 | R12: 9.6064996 | S12: 9.6310607 | T12: 9.7726442 | U12: 9.9590012 | V12: 10.273535 | W12: 10.501157 | X12: 11.226076
A13: Tāmaki Herenga Manawa | B13: 2 and over - non 20 Hours ECE | C13: 2.72655 | D13: 2.8171372 | E13: 2.9526115 | F13: 3.1871154 | G13: 3.7176845 | H13: 4.1351117 | I13: 4.3499534 | J13: 5.2495972 | K13: 5.5039151 | L13: 5.4738239 | M13: 5.4832517 | N13: 5.531002 | O13: 5.5768737 | P13: 5.5880262 | Q13: 5.5470999 | R13: 5.533692 | S13: 5.5264142 | T13: 5.5577272 | U13: 5.6854459 | V13: 5.912719 | W13: 6.1855705 | X13: 6.5415552
A14: Tāmaki Herenga Manawa | B14: Equity | C14: 0.018945334 | D14: 0.035834994 | E14: 0.033977222 | F14: 0.034598616 | G14: 0.035334177 | H14: 0.035684244 | I14: 0.032361081 | J14: 0.037040585 | K14: 0.035620202 | L14: 0.034590298 | M14: 0.03584211 | N14: 0.052264944 | O14: 0.076669416 | P14: 0.089198221 | Q14: 0.10184106 | R14: 0.10919515 | S14: 0.11021756 | T14: 0.11685128 | U14: 0.12072016 | V14: 0.12433092 | W14: 0.12837579 | X14: 0.12933406
A15: Tāmaki Herenga Manawa | B15: Targeted Funding for Disadvantage | C15: 0 | D15: 0 | E15: 0 | F15: 0 | G15: 0 | H15: 0 | I15: 0 | J15: 0 | K15: 0 | L15: 0 | M15: 0 | N15: 0 | O15: 0 | P15: 0 | Q15: 0 | R15: 0 | S15: 0.0081372203 | T15: 0.015174353 | U15: 0.014200679 | V15: 0.014331787 | W15: 0.015312202 | X15: 0.016693843
A16: Tāmaki Herenga Manawa | B16: Total | C16: 3.0625692 | D16: 3.1819436 | E16: 3.3318397 | F16: 3.5708204 | G16: 4.1737078 | H16: 4.6475381 | I16: 6.2381217 | J16: 7.4526236 | K16: 7.9233984 | L16: 7.9829579 | M16: 8.0913728 | N16: 8.2537796 | O16: 8.4975252 | P16: 8.5389913 | Q16: 8.4814421 | R16: 8.4414977 | S16: 8.4523623 | T16: 8.4882167 | U16: 8.6644303 | V16: 9.0599596 | W16: 9.3620723 | X16: 9.907365
A17: Tāmaki Herenga Tāngata | B17: 20 Hours ECE | I17: 7.4370041 | J17: 8.56426 | K17: 9.1800421 | L17: 9.368388 | M17: 9.3692289 | N17: 9.4188332 | O17: 9.6941985 | P17: 9.8580558 | Q17: 9.8917138 | R17: 9.9202216 | S17: 9.9389445 | T17: 10.022767 | U17: 10.262172 | V17: 10.778366 | W17: 11.220654 | X17: 11.951464
A18: Tāmaki Herenga Tāngata | B18: Under 2's | C18: 5.0477812 | D18: 5.1725386 | E18: 5.3767846 | F18: 5.6847911 | G18: 6.5995766 | H18: 7.3687421 | I18: 8.2228719 | J18: 9.0006533 | K18: 9.7639821 | L18: 9.7888464 | M18: 9.8657693 | N18: 9.9538273 | O18: 10.047159 | P18: 10.076859 | Q18: 10.096698 | R18: 10.094315 | S18: 9.9699312 | T18: 9.9556959 | U18: 10.140454 | V18: 10.68085 | W18: 10.977502 | X18: 11.769255
A19: Tāmaki Herenga Tāngata | B19: 2 and over - non 20 Hours ECE | C19: 2.7006011 | D19: 2.7859917 | E19: 2.9034698 | F19: 3.1564611 | G19: 3.7316256 | H19: 4.17234 | I19: 4.3790607 | J19: 5.2868729 | K19: 5.5929421 | L19: 5.5130376 | M19: 5.4554968 | N19: 5.5033811 | O19: 5.5799596 | P19: 5.6348 | Q19: 5.6496154 | R19: 5.6743477 | S19: 5.6596511 | T19: 5.6823639 | U19: 5.8057707 | V19: 6.0996208 | W19: 6.3714371 | X19: 6.7972733
A20: Tāmaki Herenga Tāngata | B20: Equity | C20: 0.0091090934 | D20: 0.016322016 | E20: 0.015835303 | F20: 0.015744898 | G20: 0.015907029 | H20: 0.016151021 | I20: 0.016453048 | J20: 0.019021965 | K20: 0.018640883 | L20: 0.018982005 | M20: 0.028253087 | N20: 0.046145294 | O20: 0.060532728 | P20: 0.062452692 | Q20: 0.061329264 | R20: 0.062076401 | S20: 0.068834808 | T20: 0.067904457 | U20: 0.067234517 | V20: 0.067343013 | W20: 0.07088529 | X20: 0.070439613
A21: Tāmaki Herenga Tāngata | B21: Targeted Funding for Disadvantage | C21: 0 | D21: 0 | E21: 0 | F21: 0 | G21: 0 | H21: 0 | I21: 0 | J21: 0 | K21: 0 | L21: 0 | M21: 0 | N21: 0 | O21: 0 | P21: 0 | Q21: 0 | R21: 0 | S21: 0.0089141441 | T21: 0.016813162 | U21: 0.016745373 | V21: 0.017743932 | W21: 0.01995455 | X21: 0.022536864
A22: Tāmaki Herenga Tāngata | B22: Total | C22: 2.9870302 | D22: 3.0824467 | E22: 3.2031671 | F22: 3.4766642 | G22: 4.1007927 | H22: 4.5858268 | I22: 6.1425865 | J22: 7.4197594 | K22: 8.0183271 | L22: 8.1672374 | M22: 8.203839 | N22: 8.2921761 | O22: 8.4972292 | P22: 8.6140992 | Q22: 8.6387239 | R22: 8.588717 | S22: 8.584394 | T22: 8.5934556 | U22: 8.7773512 | V22: 9.2473044 | W22: 9.5418079 | X22: 10.160779
A23: Tāmaki Herenga Waka | B23: 20 Hours ECE | I23: 7.4532621 | J23: 8.5071885 | K23: 9.1141122 | L23: 9.2443945 | M23: 9.4476488 | N23: 9.5767441 | O23: 9.7132036 | P23: 9.8280812 | Q23: 9.8073078 | R23: 9.7544672 | S23: 9.7679071 | T23: 9.8505762 | U23: 10.091819 | V23: 10.554764 | W23: 11.007145 | X23: 11.648578
A24: Tāmaki Herenga Waka | B24: Under 2's | C24: 5.032469 | D24: 5.1390817 | E24: 5.3151399 | F24: 5.6160893 | G24: 6.5108559 | H24: 7.1993 | I24: 8.0631194 | J24: 8.7293426 | K24: 9.3439664 | L24: 9.4112343 | M24: 9.6124742 | N24: 9.7620622 | O24: 9.7444387 | P24: 9.7813061 | Q24: 9.5953449 | R24: 9.3176471 | S24: 9.3293743 | T24: 9.4284104 | U24: 9.7502005 | V24: 10.259359 | W24: 10.777037 | X24: 11.584407
A25: Tāmaki Herenga Waka | B25: 2 and over - non 20 Hours ECE | C25: 2.7108962 | D25: 2.7832706 | E25: 2.888933 | F25: 3.108957 | G25: 3.5864322 | H25: 3.9860061 | I25: 4.0594677 | J25: 4.8671993 | K25: 5.1710227 | L25: 5.1897603 | M25: 5.2662391 | N25: 5.4056118 | O25: 5.4716798 | P25: 5.5369864 | Q25: 5.4837967 | R25: 5.3978081 | S25: 5.393701 | T25: 5.459412 | U25: 5.6641342 | V25: 5.9705092 | W25: 6.2979296 | X25: 6.686316
A26: Tāmaki Herenga Waka | B26: Equity | C26: 0.1048896 | D26: 0.19697602 | E26: 0.19385443 | F26: 0.19269722 | G26: 0.19773311 | H26: 0.2018601 | I26: 0.19775633 | J26: 0.21798602 | K26: 0.20655499 | L26: 0.20496234 | M26: 0.25442009 | N26: 0.41422694 | O26: 0.59995985 | P26: 0.62149043 | Q26: 0.62028784 | R26: 0.6239697 | S26: 0.65130341 | T26: 0.65541389 | U26: 0.66198307 | V26: 0.65876246 | W26: 0.66992706 | X26: 0.66475549
A27: Tāmaki Herenga Waka | B27: Targeted Funding for Disadvantage | C27: 0 | D27: 0 | E27: 0 | F27: 0 | G27: 0 | H27: 0 | I27: 0 | J27: 0 | K27: 0 | L27: 0 | M27: 0 | N27: 0 | O27: 0 | P27: 0 | Q27: 0 | R27: 0 | S27: 0.037521216 | T27: 0.070432385 | U27: 0.069019937 | V27: 0.070656876 | W27: 0.071698601 | X27: 0.071842016
A28: Tāmaki Herenga Waka | B28: Total | C28: 3.1458528 | D28: 3.3086467 | E28: 3.4323656 | F28: 3.6709086 | G28: 4.2277267 | H28: 4.7017547 | I28: 6.281703 | J28: 7.383991 | K28: 7.9199819 | L28: 8.0790336 | M28: 8.3465517 | N28: 8.6354072 | O28: 8.9158999 | P28: 8.9888248 | Q28: 8.8775063 | R28: 8.6794187 | S28: 8.7096128 | T28: 8.8013758 | U28: 9.051276 | V28: 9.4981107 | W28: 9.9128996 | X28: 10.454253
A29: Waikato | B29: 20 Hours ECE | I29: 7.6402159 | J29: 8.9279713 | K29: 9.6285687 | L29: 9.4712383 | M29: 9.4260676 | N29: 9.4798728 | O29: 9.5968023 | P29: 9.7029749 | Q29: 9.745868 | R29: 9.7862311 | S29: 9.828302 | T29: 9.9085677 | U29: 10.258987 | V29: 10.797362 | W29: 11.168521 | X29: 11.825719
A30: Waikato | B30: Under 2's | C30: 5.1397189 | D30: 5.242733 | E30: 5.3528794 | F30: 5.6346114 | G30: 6.5009363 | H30: 7.13043 | I30: 7.7421611 | J30: 8.1726752 | K30: 8.7690014 | L30: 8.8626936 | M30: 9.0872339 | N30: 9.2422199 | O30: 9.3406275 | P30: 9.4491112 | Q30: 9.4977114 | R30: 9.523294 | S30: 9.6141373 | T30: 9.7084112 | U30: 10.132874 | V30: 10.733769 | W30: 11.129704 | X30: 11.863102
A31: Waikato | B31: 2 and over - non 20 Hours ECE | C31: 2.7707425 | D31: 2.8523232 | E31: 2.9516159 | F31: 3.1754803 | G31: 3.6665764 | H31: 4.0392443 | I31: 4.0813682 | J31: 4.6611066 | K31: 4.8806966 | L31: 4.9877545 | M31: 5.0932443 | N31: 5.1736052 | O31: 5.2570224 | P31: 5.3321747 | Q31: 5.3695088 | R31: 5.3962054 | S31: 5.4473615 | T31: 5.5224932 | U31: 5.8203318 | V31: 6.214152 | W31: 6.4659884 | X31: 6.8755531
A32: Waikato | B32: Equity | C32: 0.061895402 | D32: 0.11409638 | E32: 0.10931014 | F32: 0.1037283 | G32: 0.10145178 | H32: 0.099913949 | I32: 0.085203192 | J32: 0.084434585 | K32: 0.082818266 | L32: 0.078673427 | M32: 0.093713012 | N32: 0.15797422 | O32: 0.23129935 | P32: 0.23944439 | Q32: 0.2422333 | R32: 0.24039928 | S32: 0.24128224 | T32: 0.23748463 | U32: 0.24224407 | V32: 0.23961182 | W32: 0.23554495 | X32: 0.24053112
A33: Waikato | B33: Targeted Funding for Disadvantage | C33: 0 | D33: 0 | E33: 0 | F33: 0 | G33: 0 | H33: 0 | I33: 0 | J33: 0 | K33: 0 | L33: 0 | M33: 0 | N33: 0 | O33: 0 | P33: 0 | Q33: 0 | R33: 0 | S33: 0.028492769 | T33: 0.054594138 | U33: 0.054536924 | V33: 0.056303778 | W33: 0.057212992 | X33: 0.056024245
A34: Waikato | B34: Total | C34: 3.2147744 | D34: 3.3753791 | E34: 3.4859289 | F34: 3.7288519 | G34: 4.3094337 | H34: 4.7224708 | I34: 6.1751403 | J34: 7.2063054 | K34: 7.7678102 | L34: 7.8454913 | M34: 7.9729978 | N34: 8.1228972 | O34: 8.2963263 | P34: 8.3784173 | Q34: 8.4221232 | R34: 8.4178878 | S34: 8.4679773 | T34: 8.5605564 | U34: 8.9224822 | V34: 9.46247 | W34: 9.769145 | X34: 10.347907
A35: Bay of Plenty, Waiariki | B35: 20 Hours ECE | I35: 7.7404943 | J35: 8.8553987 | K35: 9.3736822 | L35: 9.2804652 | M35: 9.2137572 | N35: 9.277524 | O35: 9.3768647 | P35: 9.5152307 | Q35: 9.5617921 | R35: 9.6158495 | S35: 9.6625184 | T35: 9.7583741 | U35: 10.142052 | V35: 10.750556 | W35: 11.196094 | X35: 11.841271
A36: Bay of Plenty, Waiariki | B36: Under 2's | C36: 5.1066276 | D36: 5.2316601 | E36: 5.4015844 | F36: 5.6459374 | G36: 6.3831435 | H36: 6.9159231 | I36: 7.6297929 | J36: 8.1078369 | K36: 8.6593697 | L36: 8.6998063 | M36: 8.7653109 | N36: 8.757629 | O36: 8.864621 | P36: 9.0264965 | Q36: 9.136286 | R36: 9.2541264 | S36: 9.3165913 | T36: 9.4500848 | U36: 10.032423 | V36: 10.75364 | W36: 11.145985 | X36: 11.835588
A37: Bay of Plenty, Waiariki | B37: 2 and over - non 20 Hours ECE | C37: 2.6937673 | D37: 2.7652697 | E37: 2.8789602 | F37: 3.076405 | G37: 3.5131218 | H37: 3.8754106 | I37: 3.9628729 | J37: 4.5885752 | K37: 4.8246438 | L37: 4.892433 | M37: 4.9062309 | N37: 4.9469195 | O37: 5.027493 | P37: 5.1274274 | Q37: 5.1928808 | R37: 5.2491013 | S37: 5.2964537 | T37: 5.3401879 | U37: 5.8021283 | V37: 6.3175344 | W37: 6.5902781 | X37: 6.9627026
A38: Bay of Plenty, Waiariki | B38: Equity | C38: 0.092553163 | D38: 0.16078676 | E38: 0.15845172 | F38: 0.15080255 | G38: 0.14560436 | H38: 0.13954867 | I38: 0.12986242 | J38: 0.14824994 | K38: 0.14478196 | L38: 0.13829531 | M38: 0.16539917 | N38: 0.27638776 | O38: 0.37963744 | P38: 0.37997098 | Q38: 0.37777512 | R38: 0.37939824 | S38: 0.37639863 | T38: 0.36351729 | U38: 0.37091933 | V38: 0.365933 | W38: 0.36865394 | X38: 0.37926629
A39: Bay of Plenty, Waiariki | B39: Targeted Funding for Disadvantage | C39: 0 | D39: 0 | E39: 0 | F39: 0 | G39: 0 | H39: 0 | I39: 0 | J39: 0 | K39: 0 | L39: 0 | M39: 0 | N39: 0 | O39: 0 | P39: 0 | Q39: 0 | R39: 0 | S39: 0.034275413 | T39: 0.06587137 | U39: 0.063836933 | V39: 0.06418643 | W39: 0.063877414 | X39: 0.061295947
A40: Bay of Plenty, Waiariki | B40: Total | C40: 3.2357474 | D40: 3.378447 | E40: 3.5000613 | F40: 3.7234261 | G40: 4.2149603 | H40: 4.6036276 | I40: 6.083979 | J40: 7.15331 | K40: 7.6162104 | L40: 7.6913862 | M40: 7.7537569 | N40: 7.9178192 | O40: 8.1224077 | P40: 8.2379608 | Q40: 8.2937231 | R40: 8.3232974 | S40: 8.3896929 | T40: 8.4814588 | U40: 8.9287704 | V40: 9.5549173 | W40: 9.8844535 | X40: 10.496989
A41: Taranaki, Whanganui, Manawatū | B41: 20 Hours ECE | I41: 7.5844195 | J41: 8.9209926 | K41: 9.4762119 | L41: 9.5139276 | M41: 9.4418904 | N41: 9.4739426 | O41: 9.5658879 | P41: 9.6842268 | Q41: 9.7069549 | R41: 9.7499595 | S41: 9.8129327 | T41: 9.8827192 | U41: 10.243115 | V41: 10.917795 | W41: 11.424048 | X41: 12.022738
A42: Taranaki, Whanganui, Manawatū | B42: Under 2's | C42: 5.1455227 | D42: 5.2552223 | E42: 5.4220708 | F42: 5.6761413 | G42: 6.5156548 | H42: 7.2548786 | I42: 7.9231596 | J42: 8.3360904 | K42: 8.7250749 | L42: 8.707204 | M42: 8.7627746 | N42: 8.8158519 | O42: 8.9239178 | P42: 9.0001459 | Q42: 9.111479 | R42: 9.1963698 | S42: 9.2224415 | T42: 9.3390385 | U42: 9.8468642 | V42: 10.608379 | W42: 10.998946 | X42: 11.689088
A43: Taranaki, Whanganui, Manawatū | B43: 2 and over - non 20 Hours ECE | C43: 2.7917314 | D43: 2.8750448 | E43: 2.9856349 | F43: 3.2320243 | G43: 3.7490201 | H43: 4.1507326 | I43: 4.1508848 | J43: 4.7530519 | K43: 4.9506675 | L43: 4.9198297 | M43: 4.8619067 | N43: 4.9367869 | O43: 4.9898409 | P43: 5.0660986 | Q43: 5.1516344 | R43: 5.2066253 | S43: 5.2711416 | T43: 5.3203885 | U43: 5.7133127 | V43: 6.2623502 | W43: 6.5954547 | X43: 6.9775924
A44: Taranaki, Whanganui, Manawatū | B44: Equity | C44: 0.064059984 | D44: 0.11451447 | E44: 0.11173216 | F44: 0.10849782 | G44: 0.10680038 | H44: 0.10315104 | I44: 0.092380146 | J44: 0.097838803 | K44: 0.091890261 | L44: 0.084934343 | M44: 0.10776231 | N44: 0.18651181 | O44: 0.25706615 | P44: 0.25874514 | Q44: 0.25832162 | R44: 0.25788545 | S44: 0.25411288 | T44: 0.25564287 | U44: 0.25898666 | V44: 0.25239912 | W44: 0.24813107 | X44: 0.25651156
A45: Taranaki, Whanganui, Manawatū | B45: Targeted Funding for Disadvantage | C45: 0 | D45: 0 | E45: 0 | F45: 0 | G45: 0 | H45: 0 | I45: 0 | J45: 0 | K45: 0 | L45: 0 | M45: 0 | N45: 0 | O45: 0 | P45: 0 | Q45: 0 | R45: 0 | S45: 0.029788406 | T45: 0.055560163 | U45: 0.053525551 | V45: 0.057685729 | W45: 0.057858708 | X45: 0.059143241
A46: Taranaki, Whanganui, Manawatū | B46: Total | C46: 3.2649952 | D46: 3.4063526 | E46: 3.5283555 | F46: 3.7738027 | G46: 4.3632035 | H46: 4.8372281 | I46: 6.4143863 | J46: 7.4115332 | K46: 7.8645141 | L46: 7.9368529 | M46: 7.9477322 | N46: 8.0845904 | O46: 8.2314477 | P46: 8.3024287 | Q46: 8.3633244 | R46: 8.3759405 | S46: 8.4322595 | T46: 8.5221319 | U46: 8.9015994 | V46: 9.5446168 | W46: 9.9640216 | X46: 10.547316
A47: Hawke's Bay, Tairāwhiti | B47: 20 Hours ECE | I47: 7.6124901 | J47: 8.7919162 | K47: 9.3336234 | L47: 9.2688725 | M47: 9.2114969 | N47: 9.2547386 | O47: 9.386094 | P47: 9.5030109 | Q47: 9.4931608 | R47: 9.5285384 | S47: 9.5825587 | T47: 9.6638699 | U47: 10.142292 | V47: 10.815151 | W47: 11.301201 | X47: 11.890913
A48: Hawke's Bay, Tairāwhiti | B48: Under 2's | C48: 5.0787719 | D48: 5.2183545 | E48: 5.4078665 | F48: 5.6667131 | G48: 6.3768111 | H48: 6.967937 | I48: 7.6500736 | J48: 7.9934727 | K48: 8.3827574 | L48: 8.4436564 | M48: 8.5640354 | N48: 8.6640647 | O48: 8.789208 | P48: 8.9097269 | Q48: 8.95189 | R48: 8.9658623 | S48: 9.0075432 | T48: 9.1578945 | U48: 9.8600515 | V48: 10.675272 | W48: 11.095266 | X48: 11.745206
A49: Hawke's Bay, Tairāwhiti | B49: 2 and over - non 20 Hours ECE | C49: 2.7231954 | D49: 2.7995032 | E49: 2.914571 | F49: 3.1243512 | G49: 3.5624711 | H49: 3.908712 | I49: 3.9547704 | J49: 4.4485301 | K49: 4.6778165 | L49: 4.6786898 | M49: 4.6797476 | N49: 4.762288 | O49: 4.9286608 | P49: 5.0149843 | Q49: 5.0419353 | R49: 5.0738563 | S49: 5.1168424 | T49: 5.1907442 | U49: 5.7655353 | V49: 6.3803251 | W49: 6.7267699 | X49: 7.0991869
A50: Hawke's Bay, Tairāwhiti | B50: Equity | C50: 0.12491625 | D50: 0.21389379 | E50: 0.21048483 | F50: 0.20444142 | G50: 0.20876277 | H50: 0.20233145 | I50: 0.20247723 | J50: 0.23545644 | K50: 0.22702243 | L50: 0.21802097 | M50: 0.2467788 | N50: 0.40006243 | O50: 0.54560688 | P50: 0.56077143 | Q50: 0.57486587 | R50: 0.57981646 | S50: 0.57558455 | T50: 0.56313394 | U50: 0.57755723 | V50: 0.57622363 | W50: 0.58318067 | X50: 0.59532327
A51: Hawke's Bay, Tairāwhiti | B51: Targeted Funding for Disadvantage | C51: 0 | D51: 0 | E51: 0 | F51: 0 | G51: 0 | H51: 0 | I51: 0 | J51: 0 | K51: 0 | L51: 0 | M51: 0 | N51: 0 | O51: 0 | P51: 0 | Q51: 0 | R51: 0 | S51: 0.04309138 | T51: 0.085036809 | U51: 0.086767922 | V51: 0.088195142 | W51: 0.09024058 | X51: 0.084470417
A52: Hawke's Bay, Tairāwhiti | B52: Total | C52: 3.2952859 | D52: 3.487432 | E52: 3.6051627 | F52: 3.8168489 | G52: 4.324172 | H52: 4.7394667 | I52: 6.1318737 | J52: 7.0818797 | K52: 7.5212703 | L52: 7.595444 | M52: 7.6350239 | N52: 7.889889 | O52: 8.205288 | P52: 8.308664 | Q52: 8.3383944 | R52: 8.3399365 | S52: 8.3884376 | T52: 8.4744612 | U52: 9.0387267 | V52: 9.7522604 | W52: 10.173087 | X52: 10.707732
A53: Wellington | B53: 20 Hours ECE | I53: 7.5392645 | J53: 8.8422368 | K53: 9.6032846 | L53: 9.6952686 | M53: 9.5503675 | N53: 9.5802055 | O53: 9.6604846 | P53: 9.7446268 | Q53: 9.7718564 | R53: 9.8408119 | S53: 9.9049252 | T53: 9.9976207 | U53: 10.342844 | V53: 10.999237 | W53: 11.517769 | X53: 12.155694
A54: Wellington | B54: Under 2's | C54: 5.1209605 | D54: 5.2315657 | E54: 5.3970696 | F54: 5.68768 | G54: 6.6252744 | H54: 7.2461435 | I54: 7.9204041 | J54: 8.4075344 | K54: 8.8550033 | L54: 8.8512086 | M54: 8.9764955 | N54: 9.1433618 | O54: 9.2613102 | P54: 9.3255825 | Q54: 9.3394156 | R54: 9.5087161 | S54: 9.5888209 | T54: 9.718941 | U54: 10.082248 | V54: 10.67161 | W54: 11.038669 | X54: 11.832737
A55: Wellington | B55: 2 and over - non 20 Hours ECE | C55: 2.789359 | D55: 2.8788396 | E55: 2.9880305 | F55: 3.2406783 | G55: 3.7966451 | H55: 4.1978206 | I55: 4.219132 | J55: 4.8710497 | K55: 5.1049123 | L55: 5.0768971 | M55: 5.0470345 | N55: 5.120022 | O55: 5.2120285 | P55: 5.3046328 | Q55: 5.3459184 | R55: 5.4244106 | S55: 5.4689722 | T55: 5.5414618 | U55: 5.836608 | V55: 6.2953273 | W55: 6.62851 | X55: 7.0576936
A56: Wellington | B56: Equity | C56: 0.028834999 | D56: 0.05414131 | E56: 0.054600753 | F56: 0.056332905 | G56: 0.056861783 | H56: 0.056727161 | I56: 0.052547875 | J56: 0.056247331 | K56: 0.05442193 | L56: 0.054554593 | M56: 0.067431842 | N56: 0.1183643 | O56: 0.16714641 | P56: 0.17650704 | Q56: 0.17901779 | R56: 0.17513813 | S56: 0.17768947 | T56: 0.17505514 | U56: 0.18371092 | V56: 0.18317955 | W56: 0.18291933 | X56: 0.18544776
A57: Wellington | B57: Targeted Funding for Disadvantage | C57: 0 | D57: 0 | E57: 0 | F57: 0 | G57: 0 | H57: 0 | I57: 0 | J57: 0 | K57: 0 | L57: 0 | M57: 0 | N57: 0 | O57: 0 | P57: 0 | Q57: 0 | R57: 0 | S57: 0.019994699 | T57: 0.038549946 | U57: 0.038139326 | V57: 0.03972339 | W57: 0.03988525 | X57: 0.038808995
A58: Wellington | B58: Total | C58: 3.207589 | D58: 3.3111503 | E58: 3.4447205 | F58: 3.7296567 | G58: 4.3359012 | H58: 4.7965069 | I58: 6.3195425 | J58: 7.3361634 | K58: 7.9313667 | L58: 8.0501109 | M58: 8.0279499 | N58: 8.1481508 | O58: 8.2899789 | P58: 8.3886741 | Q58: 8.4188831 | R58: 8.4749353 | S58: 8.5306302 | T58: 8.6087841 | U58: 8.9359845 | V58: 9.5315612 | W58: 9.8953023 | X58: 10.512268
A59: Nelson, Marlborough, West Coast | B59: 20 Hours ECE | I59: 7.685163 | J59: 9.593743 | K59: 9.9755278 | L59: 9.7158508 | M59: 9.5955991 | N59: 9.6157886 | O59: 9.7338969 | P59: 9.8367395 | Q59: 9.857447 | R59: 9.9067873 | S59: 9.955204 | T59: 10.046156 | U59: 10.358996 | V59: 10.95644 | W59: 11.497427 | X59: 12.110217
A60: Nelson, Marlborough, West Coast | B60: Under 2's | C60: 5.1518562 | D60: 5.2331449 | E60: 5.4253666 | F60: 5.71073 | G60: 6.7104957 | H60: 7.4674031 | I60: 8.1856784 | J60: 8.7372743 | K60: 9.319757 | L60: 9.0892456 | M60: 9.063288 | N60: 9.1660236 | O60: 9.2662157 | P60: 9.2219751 | Q60: 9.297857 | R60: 9.4326587 | S60: 9.5395943 | T60: 9.6662022 | U60: 9.99791 | V60: 10.464425 | W60: 10.853203 | X60: 11.522881
A61: Nelson, Marlborough, West Coast | B61: 2 and over - non 20 Hours ECE | C61: 2.793601 | D61: 2.8784478 | E61: 2.9996019 | F61: 3.262615 | G61: 3.8157326 | H61: 4.2608375 | I61: 4.2700215 | J61: 4.961129 | K61: 5.2069344 | L61: 5.0698876 | M61: 5.0417497 | N61: 5.1371977 | O61: 5.2434194 | P61: 5.3166557 | Q61: 5.4026388 | R61: 5.484274 | S61: 5.5349717 | T61: 5.6118134 | U61: 5.8243416 | V61: 6.1992279 | W61: 6.5880022 | X61: 6.9808016
A62: Nelson, Marlborough, West Coast | B62: Equity | C62: 0.042851587 | D62: 0.075856709 | E62: 0.072557569 | F62: 0.066097325 | G62: 0.06530731 | H62: 0.068082796 | I62: 0.057765378 | J62: 0.057291934 | K62: 0.055606768 | L62: 0.053091914 | M62: 0.068375192 | N62: 0.092730581 | O62: 0.11378672 | P62: 0.11351693 | Q62: 0.11574248 | R62: 0.11513854 | S62: 0.12252617 | T62: 0.12770259 | U62: 0.13777105 | V62: 0.13797461 | W62: 0.13841033 | X62: 0.13683023
A63: Nelson, Marlborough, West Coast | B63: Targeted Funding for Disadvantage | C63: 0 | D63: 0 | E63: 0 | F63: 0 | G63: 0 | H63: 0 | I63: 0 | J63: 0 | K63: 0 | L63: 0 | M63: 0 | N63: 0 | O63: 0 | P63: 0 | Q63: 0 | R63: 0 | S63: 0.022533694 | T63: 0.042405555 | U63: 0.04149343 | V63: 0.042875372 | W63: 0.040639032 | X63: 0.036497587
A64: Nelson, Marlborough, West Coast | B64: Total | C64: 3.1838223 | D64: 3.3246941 | E64: 3.4210448 | F64: 3.7073718 | G64: 4.3407508 | H64: 4.8182136 | I64: 6.7471536 | J64: 8.1260796 | K64: 8.5075735 | L64: 8.3277878 | M64: 8.3206468 | N64: 8.4213539 | O64: 8.5180247 | P64: 8.5805894 | Q64: 8.5647073 | R64: 8.6166188 | S64: 8.6445275 | T64: 8.7334244 | U64: 9.036091 | V64: 9.5591294 | W64: 10.028229 | X64: 10.545282
A65: Canterbury and Chatham Islands | B65: 20 Hours ECE | I65: 7.8722979 | J65: 8.9485198 | K65: 9.4703821 | L65: 9.6040317 | M65: 9.5693176 | N65: 9.6535221 | O65: 9.7579818 | P65: 9.8649416 | Q65: 9.8877105 | R65: 9.9154835 | S65: 9.9371747 | T65: 10.025478 | U65: 10.261993 | V65: 10.79014 | W65: 11.232587 | X65: 11.94329
A66: Canterbury and Chatham Islands | B66: Under 2's | C66: 5.3034245 | D66: 5.4024214 | E66: 5.5794208 | F66: 5.9215167 | G66: 7.1604375 | H66: 7.857935 | I66: 8.6000138 | J66: 9.1040186 | K66: 9.6950664 | L66: 9.535555 | M66: 9.5280484 | N66: 9.6236914 | O66: 9.7612219 | P66: 9.8961597 | Q66: 9.8792158 | R66: 9.8448829 | S66: 9.8706777 | T66: 10.027075 | U66: 10.25476 | V66: 10.750406 | W66: 11.174673 | X66: 11.997871
A67: Canterbury and Chatham Islands | B67: 2 and over - non 20 Hours ECE | C67: 2.8026391 | D67: 2.887414 | E67: 3.005514 | F67: 3.2678969 | G67: 3.9533827 | H67: 4.4022891 | I67: 4.5364189 | J67: 5.3521077 | K67: 5.5418992 | L67: 5.4468926 | M67: 5.3359509 | N67: 5.4099817 | O67: 5.4741285 | P67: 5.5719505 | Q67: 5.584271 | R67: 5.5951802 | S67: 5.6127061 | T67: 5.6774848 | U67: 5.8070281 | V67: 6.1678537 | W67: 6.49094 | X67: 6.9698817
A68: Canterbury and Chatham Islands | B68: Equity | C68: 0.015114946 | D68: 0.027654212 | E68: 0.02552189 | F68: 0.024448393 | G68: 0.025476091 | H68: 0.027071091 | I68: 0.026291562 | J68: 0.027612178 | K68: 0.024910618 | L68: 0.023827247 | M68: 0.032708026 | N68: 0.058683597 | O68: 0.086558973 | P68: 0.089067203 | Q68: 0.088829865 | R68: 0.089001578 | S68: 0.08805033 | T68: 0.084527481 | U68: 0.086460881 | V68: 0.088201787 | W68: 0.087451502 | X68: 0.087676891
A69: Canterbury and Chatham Islands | B69: Targeted Funding for Disadvantage | C69: 0 | D69: 0 | E69: 0 | F69: 0 | G69: 0 | H69: 0 | I69: 0 | J69: 0 | K69: 0 | L69: 0 | M69: 0 | N69: 0 | O69: 0 | P69: 0 | Q69: 0 | R69: 0 | S69: 0.012685891 | T69: 0.024952636 | U69: 0.026683381 | V69: 0.029291882 | W69: 0.029477016 | X69: 0.029533138
A70: Canterbury and Chatham Islands | B70: Total | C70: 3.2548382 | D70: 3.3510328 | E70: 3.4852516 | F70: 3.7751313 | G70: 4.5788638 | H70: 5.0666709 | I70: 6.6373336 | J70: 7.7550849 | K70: 8.2743231 | L70: 8.3595219 | M70: 8.3490206 | N70: 8.4377825 | O70: 8.562595 | P70: 8.6743326 | Q70: 8.6823079 | R70: 8.6550067 | S70: 8.6497627 | T70: 8.7317049 | U70: 8.9346833 | V70: 9.4387228 | W70: 9.8146498 | X70: 10.474015
A71: Otago, Southland | B71: 20 Hours ECE | I71: 7.7535031 | J71: 9.0804256 | K71: 9.6686158 | L71: 9.5852188 | M71: 9.4175338 | N71: 9.587033 | O71: 9.6879589 | P71: 9.7694493 | Q71: 9.7894828 | R71: 9.8238779 | S71: 9.8621308 | T71: 9.9588033 | U71: 10.2389 | V71: 10.868671 | W71: 11.405403 | X71: 12.064253
A72: Otago, Southland | B72: Under 2's | C72: 5.2049437 | D72: 5.3032676 | E72: 5.4774015 | F72: 5.8280711 | G72: 7.0621582 | H72: 7.6386505 | I72: 8.3424325 | J72: 8.7163944 | K72: 9.1866612 | L72: 9.2733299 | M72: 9.2356739 | N72: 9.2708299 | O72: 9.3529803 | P72: 9.3954424 | Q72: 9.4460193 | R72: 9.5290759 | S72: 9.5801582 | T72: 9.844451 | U72: 10.123464 | V72: 10.677535 | W72: 11.084183 | X72: 11.869892
A73: Otago, Southland | B73: 2 and over - non 20 Hours ECE | C73: 2.8179887 | D73: 2.9167704 | E73: 3.0353479 | F73: 3.3135607 | G73: 3.94108 | H73: 4.3363348 | I73: 4.3488843 | J73: 5.0499961 | K73: 5.3054607 | L73: 5.3225992 | M73: 5.1632217 | N73: 5.1983229 | O73: 5.3026457 | P73: 5.3742817 | Q73: 5.4063858 | R73: 5.452273 | S73: 5.4827108 | T73: 5.5942941 | U73: 5.8058274 | V73: 6.2274878 | W73: 6.6046507 | X73: 7.0422342
A74: Otago, Southland | B74: Equity | C74: 0.036243582 | D74: 0.069365249 | E74: 0.064745253 | F74: 0.061999534 | G74: 0.059215442 | H74: 0.055820391 | I74: 0.047271464 | J74: 0.046549868 | K74: 0.044724285 | L74: 0.044279226 | M74: 0.06500799 | N74: 0.091777877 | O74: 0.12606183 | P74: 0.12921235 | Q74: 0.13063791 | R74: 0.13780374 | S74: 0.14088233 | T74: 0.13944854 | U74: 0.14395587 | V74: 0.14002492 | W74: 0.13837142 | X74: 0.14357412
A75: Otago, Southland | B75: Targeted Funding for Disadvantage | C75: 0 | D75: 0 | E75: 0 | F75: 0 | G75: 0 | H75: 0 | I75: 0 | J75: 0 | K75: 0 | L75: 0 | M75: 0 | N75: 0 | O75: 0 | P75: 0 | Q75: 0 | R75: 0 | S75: 0.015663487 | T75: 0.030423027 | U75: 0.030889082 | V75: 0.032697235 | W75: 0.030064624 | X75: 0.028971072
A76: Otago, Southland | B76: Total | C76: 3.2610698 | D76: 3.3882011 | E76: 3.5240694 | F76: 3.8336772 | G76: 4.5628452 | H76: 4.9866563 | I76: 6.6423872 | J76: 7.7202019 | K76: 8.1675059 | L76: 8.2361329 | M76: 8.140941 | N76: 8.285202 | O76: 8.437659 | P76: 8.4929747 | Q76: 8.517309 | R76: 8.5526679 | S76: 8.5552003 | T76: 8.6990367 | U76: 8.9412168 | V76: 9.5145447 | W76: 9.9322288 | X76: 10.524009
A77: Not Applicable | B77: 20 Hours ECE | I77: 8.1440257 | J77: 9.0847906 | K77: 9.4710579 | L77: 9.4367728 | M77: 9.3316077 | N77: 9.3114894 | O77: 9.3817114 | P77: 9.4405876 | Q77: 9.4391603 | R77: 9.4428183 | S77: 9.4483341 | T77: 9.4822083 | U77: 9.6871246 | V77: 10.204129 | W77: 10.476829 | X77: 11.429679
A78: Not Applicable | B78: Under 2's | C78: 5.0363376 | D78: 5.1022255 | E78: 5.2918053 | F78: 5.6274462 | G78: 6.4158856 | H78: 7.0857137 | I78: 7.864911 | J78: 8.4632594 | K78: 9.1188132 | L78: 9.1310181 | M78: 8.9939717 | N78: 8.4675886 | O78: 8.0072017 | P78: 7.6706477 | Q78: 7.5874276 | R78: 7.7984155 | S78: 7.7589437 | T78: 7.7937788 | U78: 8.1852919 | V78: 8.8527303 | W78: 9.1778248 | X78: 10.668734
A79: Not Applicable | B79: 2 and over - non 20 Hours ECE | C79: 2.5766768 | D79: 2.6271808 | E79: 2.7138365 | F79: 2.8885646 | G79: 3.3669435 | H79: 3.7832089 | I79: 4.1041151 | J79: 4.8334597 | K79: 5.1706565 | L79: 5.1591804 | M79: 5.0622751 | N79: 4.9257022 | O79: 4.8841423 | P79: 4.7686374 | Q79: 4.6387569 | R79: 4.7200414 | S79: 4.6442588 | T79: 4.601847 | U79: 4.7750634 | V79: 5.0426558 | W79: 5.2454504 | X79: 5.8853855
A80: Not Applicable | B80: Equity | C80: 0.033813276 | D80: 0.065024409 | E80: 0.060332973 | F80: 0.057774439 | G80: 0.051116388 | H80: 0.048209605 | I80: 0.042072858 | J80: 0.040746441 | K80: 0.034554711 | L80: 0.031682244 | M80: 0.085512252 | N80: 0.15944216 | O80: 0.23356456 | P80: 0.21540216 | Q80: 0.22103516 | R80: 0.2435211 | S80: 0.25366532 | T80: 0.22467136 | U80: 0.22749587 | V80: 0.19036408 | W80: 0.14560138 | X80: 0.10575771
A81: Not Applicable | B81: Targeted Funding for Disadvantage | C81: 0 | D81: 0 | E81: 0 | F81: 0 | G81: 0 | H81: 0 | I81: 0 | J81: 0 | K81: 0 | L81: 0 | M81: 0 | N81: 0 | O81: 0 | P81: 0 | Q81: 0 | R81: 0 | S81: 0.018147383 | T81: 0.034074145 | U81: 0.035384191 | V81: 0.038445106 | W81: 0.031516978 | X81: 0.026996282
A82: Not Applicable | B82: Total | C82: 3.2731293 | D82: 3.3429208 | E82: 3.4852587 | F82: 3.717113 | G82: 4.3160455 | H82: 4.7935616 | I82: 6.2300126 | J82: 7.2597165 | K82: 7.8138097 | L82: 7.8506177 | M82: 7.8077587 | N82: 7.7078362 | O82: 7.7033238 | P82: 7.5031154 | Q82: 7.3250713 | R82: 7.3918268 | S82: 7.3272334 | T82: 7.2416177 | U82: 7.4975663 | V82: 7.9557921 | W82: 8.2087842 | X82: 9.0946942
A83: Total | B83: 20 Hours ECE | I83: 7.6481389 | J83: 8.8758823 | K83: 9.4360739 | L83: 9.4465298 | M83: 9.3979001 | N83: 9.4678945 | O83: 9.6149914 | P83: 9.7334845 | Q83: 9.7547013 | R83: 9.7855422 | S83: 9.8221195 | T83: 9.906903 | U83: 10.209697 | V83: 10.775285 | W83: 11.234698 | X83: 11.907835
A84: Total | B84: Under 2's | C84: 5.118562 | D84: 5.2228817 | E84: 5.3978233 | F84: 5.697 | G84: 6.6065909 | H84: 7.2696339 | I84: 8.0180439 | J84: 8.5380394 | K84: 9.0911267 | L84: 9.0861958 | M84: 9.1631898 | N84: 9.2164472 | O84: 9.282339 | P84: 9.2768902 | Q84: 9.2428356 | R84: 9.3275986 | S84: 9.3642399 | T84: 9.4987181 | U84: 9.8936739 | V84: 10.500033 | W84: 10.889875 | X84: 11.685426
A85: Total | B85: 2 and over - non 20 Hours ECE | C85: 2.7389345 | D85: 2.8184366 | E85: 2.9308143 | F85: 3.1639145 | G85: 3.696513 | H85: 4.1029699 | I85: 4.2010475 | J85: 4.9021145 | K85: 5.1475772 | L85: 5.1353563 | M85: 5.1155665 | N85: 5.1797755 | O85: 5.2604048 | P85: 5.3235968 | Q85: 5.331188 | R85: 5.3630102 | S85: 5.3821937 | T85: 5.4403753 | U85: 5.7104189 | V85: 6.1135174 | W85: 6.4274197 | X85: 6.8424631
A86: Total | B86: Equity | C86: 0.050663477 | D86: 0.0935057 | E86: 0.089973049 | F86: 0.086861312 | G86: 0.085764196 | H86: 0.083997416 | I86: 0.078110933 | J86: 0.085082938 | K86: 0.081088002 | L86: 0.078664884 | M86: 0.10167444 | N86: 0.16898393 | O86: 0.23873868 | P86: 0.24553046 | Q86: 0.24945822 | R86: 0.25571183 | S86: 0.26124895 | T86: 0.25799496 | U86: 0.26395828 | V86: 0.26073391 | W86: 0.26239115 | X86: 0.26482808
A87: Total | B87: Targeted Funding for Disadvantage | C87: 0 | D87: 0 | E87: 0 | F87: 0 | G87: 0 | H87: 0 | I87: 0 | J87: 0 | K87: 0 | L87: 0 | M87: 0 | N87: 0 | O87: 0 | P87: 0 | Q87: 0 | R87: 0 | S87: 0.023000092 | T87: 0.04398088 | U87: 0.043713002 | V87: 0.045247193 | W87: 0.045618511 | X87: 0.045270838
A88: Total | B88: Total | C88: 3.2051286 | D88: 3.3308951 | E88: 3.4569731 | F88: 3.7115714 | G88: 4.3213876 | H88: 4.7784772 | I88: 6.3149153 | J88: 7.4158631 | K88: 7.9256169 | L88: 7.9986924 | M88: 8.0437358 | N88: 8.1849709 | O88: 8.3725531 | P88: 8.4416295 | Q88: 8.4319761 | R88: 8.4284143 | S88: 8.4568308 | T88: 8.5316829 | U88: 8.8424921 | V88: 9.3905146 | W88: 9.7571172 | X88: 10.359926

Sheet EXP14
A1: ='Table Index'!J18 -> Entitlement funding, equity funding and targeted funding for disadvantage per funded child hour by New Zealand Index of Deprivation and programme ($, GST exclusive) | N1: About the data in this table | Q1: Table Index
A3: Click on arrow to select (filter) the information you need
A4: NZDep18 Index of Deprivation 17 | B4: Programme 14 | C4: 2001/02 | D4: 2002/03 | E4: 2003/04 | F4: 2004/05 | G4: 2005/06 | H4: 2006/07 | I4: 2007/08 | J4: 2008/09 | K4: 2009/10 | L4: 2010/11 | M4: 2011/12 | N4: 2012/13 | O4: 2013/14 | P4: 2014/15 | Q4: 2015/16 | R4: 2016/17 | S4: 2017/18 | T4: 2018/19 | U4: 2019/20 | V4: 2020/21 | W4: 2021/22 | X4: 2022/23
A5: NZDep decile 1 | B5: 20 Hours ECE | I5: 7.5361131 | J5: 8.7390774 | K5: 9.2868363 | L5: 9.4271275 | M5: 9.3453722 | N5: 9.4683672 | O5: 9.6389009 | P5: 9.7716489 | Q5: 9.8212018 | R5: 9.8903883 | S5: 9.9510565 | T5: 10.050847 | U5: 10.313485 | V5: 10.846374 | W5: 11.268371 | X5: 11.918881
A6: NZDep decile 1 | B6: Under 2's | C6: 5.1333258 | D6: 5.2514766 | E6: 5.410912 | F6: 5.6987526 | G6: 6.5418789 | H6: 7.2520274 | I6: 7.8456228 | J6: 8.389402 | K6: 8.8076176 | L6: 8.7937292 | M6: 8.8747855 | N6: 9.0101448 | O6: 9.1991655 | P6: 9.3481345 | Q6: 9.4500115 | R6: 9.5682393 | S6: 9.649905 | T6: 9.8785718 | U6: 10.143197 | V6: 10.612566 | W6: 10.888077 | X6: 11.769694
A7: NZDep decile 1 | B7: 2 and over - non 20 Hours ECE | C7: 2.8082443 | D7: 2.9018929 | E7: 3.0211332 | F7: 3.2863696 | G7: 3.8422482 | H7: 4.2724116 | I7: 4.3320911 | J7: 4.9746472 | K7: 5.233319 | L7: 5.1560822 | M7: 5.1035788 | N7: 5.1792422 | O7: 5.276708 | P7: 5.4051295 | Q7: 5.4369961 | R7: 5.4489348 | S7: 5.537863 | T7: 5.6331485 | U7: 5.7842802 | V7: 6.1425232 | W7: 6.4100348 | X7: 6.8413673
A8: NZDep decile 1 | B8: Equity | C8: 0.003639307 | D8: 0.007222336 | E8: 0.0070707647 | F8: 0.0065406253 | G8: 0.006475396 | H8: 0.0054490112 | I8: 0.0054490644 | J8: 0.0072584099 | K8: 0.0051337528 | L8: 0.0051015334 | M8: 0.0077560299 | N8: 0.012407205 | O8: 0.027025678 | P8: 0.028202125 | Q8: 0.028452999 | R8: 0.025706687 | S8: 0.025001974 | T8: 0.023650695 | U8: 0.025951548 | V8: 0.030910718 | W8: 0.032113742 | X8: 0.031170674
A9: NZDep decile 1 | B9: Targeted Funding for Disadvantage | C9: 0 | D9: 0 | E9: 0 | F9: 0 | G9: 0 | H9: 0 | I9: 0 | J9: 0 | K9: 0 | L9: 0 | M9: 0 | N9: 0 | O9: 0 | P9: 0 | Q9: 0 | R9: 0 | S9: 0.003866664 | T9: 0.0066687655 | U9: 0.0055482411 | V9: 0.0055824126 | W9: 0.0049582045 | X9: 0.0035713798
A10: NZDep decile 1 | B10: Total | C10: 3.1707351 | D10: 3.25625 | E10: 3.4081174 | F10: 3.7249551 | G10: 4.3068431 | H10: 4.7879612 | I10: 6.2739542 | J10: 7.3113896 | K10: 7.8281487 | L10: 7.9687545 | M10: 8.0008613 | N10: 8.1381287 | O10: 8.2907215 | P10: 8.3955092 | Q10: 8.4395911 | R10: 8.4699457 | S10: 8.4969829 | T10: 8.5975376 | U10: 8.8398938 | V10: 9.3291748 | W10: 9.6339241 | X10: 10.237532
A11: NZDep decile 2 | B11: 20 Hours ECE | I11: 7.674656 | J11: 8.9547573 | K11: 9.6933743 | L11: 9.6713482 | M11: 9.5310883 | N11: 9.5343791 | O11: 9.633198 | P11: 9.7395674 | Q11: 9.7638672 | R11: 9.8004364 | S11: 9.8357548 | T11: 9.9150973 | U11: 10.134699 | V11: 10.652359 | W11: 11.086194 | X11: 11.826752
A12: NZDep decile 2 | B12: Under 2's | C12: 5.1482777 | D12: 5.2455551 | E12: 5.4375067 | F12: 5.7860565 | G12: 6.775251 | H12: 7.4329487 | I12: 8.1743788 | J12: 8.7935549 | K12: 9.5293723 | L12: 9.4840783 | M12: 9.3694502 | N12: 9.3460872 | O12: 9.4209465 | P12: 9.508969 | Q12: 9.3530724 | R12: 9.3295835 | S12: 9.1723096 | T12: 9.2496802 | U12: 9.5998187 | V12: 10.184635 | W12: 10.535376 | X12: 11.358077
A13: NZDep decile 2 | B13: 2 and over - non 20 Hours ECE | C13: 2.7010254 | D13: 2.7766002 | E13: 2.8871907 | F13: 3.1270179 | G13: 3.7649341 | H13: 4.1822773 | I13: 4.3327852 | J13: 5.1703076 | K13: 5.4192544 | L13: 5.3388583 | M13: 5.2652703 | N13: 5.2607648 | O13: 5.2813533 | P13: 5.3573752 | Q13: 5.3502717 | R13: 5.3712296 | S13: 5.3349401 | T13: 5.3089893 | U13: 5.5107578 | V13: 5.8481779 | W13: 6.1649812 | X13: 6.5915562
A14: NZDep decile 2 | B14: Equity | C14: 0.006850587 | D14: 0.013047702 | E14: 0.011406212 | F14: 0.010221491 | G14: 0.0085707939 | H14: 0.0071965876 | I14: 0.0075442323 | J14: 0.008987681 | K14: 0.008623863 | L14: 0.0086013781 | M14: 0.015334632 | N14: 0.025053408 | O14: 0.034636873 | P14: 0.033313658 | Q14: 0.038976786 | R14: 0.036345466 | S14: 0.036120777 | T14: 0.033979308 | U14: 0.033662669 | V14: 0.032076265 | W14: 0.028741875 | X14: 0.027676655
A15: NZDep decile 2 | B15: Targeted Funding for Disadvantage | C15: 0 | D15: 0 | E15: 0 | F15: 0 | G15: 0 | H15: 0 | I15: 0 | J15: 0 | K15: 0 | L15: 0 | M15: 0 | N15: 0 | O15: 0 | P15: 0 | Q15: 0 | R15: 0 | S15: 0.0066284833 | T15: 0.011422505 | U15: 0.0092797089 | V15: 0.010341879 | W15: 0.010855595 | X15: 0.012025294
A16: NZDep decile 2 | B16: Total | C16: 3.2228878 | D16: 3.2715968 | E16: 3.4106029 | F16: 3.6705542 | G16: 4.3848837 | H16: 4.8535591 | I16: 6.3096897 | J16: 7.5610683 | K16: 8.2440469 | L16: 8.273724 | M16: 8.2012224 | N16: 8.1872539 | O16: 8.2794807 | P16: 8.3605866 | Q16: 8.3340068 | R16: 8.2972335 | S16: 8.2621435 | T16: 8.2776525 | U16: 8.5267405 | V16: 9.0588608 | W16: 9.399835 | X16: 10.033074
A17: NZDep decile 3 | B17: 20 Hours ECE | I17: 7.5798056 | J17: 8.9091286 | K17: 9.406056 | L17: 9.4584242 | M17: 9.389147 | N17: 9.4727367 | O17: 9.7082773 | P17: 9.8367569 | Q17: 9.8582897 | R17: 9.8962111 | S17: 9.9203324 | T17: 10.009842 | U17: 10.255112 | V17: 10.798807 | W17: 11.265463 | X17: 11.955768
A18: NZDep decile 3 | B18: Under 2's | C18: 5.1273512 | D18: 5.2299702 | E18: 5.4206411 | F18: 5.7132385 | G18: 6.6817072 | H18: 7.3460487 | I18: 8.2230588 | J18: 8.8248432 | K18: 9.5666731 | L18: 9.603816 | M18: 9.6420602 | N18: 9.6762609 | O18: 9.7599886 | P18: 9.4888383 | Q18: 9.253297 | R18: 9.2639366 | S18: 9.2850307 | T18: 9.450342 | U18: 9.725085 | V18: 10.089709 | W18: 10.334113 | X18: 11.104302
A19: NZDep decile 3 | B19: 2 and over - non 20 Hours ECE | C19: 2.7339277 | D19: 2.8212848 | E19: 2.9396446 | F19: 3.1750114 | G19: 3.7405398 | H19: 4.1542172 | I19: 4.3414883 | J19: 5.1227275 | K19: 5.3828905 | L19: 5.4376379 | M19: 5.3978586 | N19: 5.4422454 | O19: 5.5219537 | P19: 5.5402901 | Q19: 5.4980303 | R19: 5.4663337 | S19: 5.4580948 | T19: 5.497341 | U19: 5.6164102 | V19: 5.9035505 | W19: 6.1834248 | X19: 6.5756982
A20: NZDep decile 3 | B20: Equity | C20: 0.014140983 | D20: 0.02621994 | E20: 0.025936394 | F20: 0.025140933 | G20: 0.024419258 | H20: 0.023581426 | I20: 0.020584269 | J20: 0.02108461 | K20: 0.021479942 | L20: 0.019403283 | M20: 0.024186058 | N20: 0.032859804 | O20: 0.041928621 | P20: 0.041790774 | Q20: 0.044398483 | R20: 0.046791096 | S20: 0.044133451 | T20: 0.046560636 | U20: 0.048995663 | V20: 0.044592111 | W20: 0.043187403 | X20: 0.045212761
A21: NZDep decile 3 | B21: Targeted Funding for Disadvantage | C21: 0 | D21: 0 | E21: 0 | F21: 0 | G21: 0 | H21: 0 | I21: 0 | J21: 0 | K21: 0 | L21: 0 | M21: 0 | N21: 0 | O21: 0 | P21: 0 | Q21: 0 | R21: 0 | S21: 0.0060428287 | T21: 0.011106396 | U21: 0.011082209 | V21: 0.01164962 | W21: 0.010690741 | X21: 0.0099852042
A22: NZDep decile 3 | B22: Total | C22: 3.1600652 | D22: 3.2433197 | E22: 3.387954 | F22: 3.6400497 | G22: 4.279775 | H22: 4.7386615 | I22: 6.2963742 | J22: 7.495824 | K22: 8.0709696 | L22: 8.1812801 | M22: 8.160746 | N22: 8.2413012 | O22: 8.4481744 | P22: 8.475969 | Q22: 8.4094497 | R22: 8.3867792 | S22: 8.3684195 | T22: 8.4210547 | U22: 8.6186624 | V22: 9.0732283 | W22: 9.3824394 | X22: 9.9609551
A23: NZDep decile 4 | B23: 20 Hours ECE | I23: 7.3674794 | J23: 8.7059609 | K23: 9.4225086 | L23: 9.5228149 | M23: 9.4619974 | N23: 9.5530381 | O23: 9.7771094 | P23: 9.8843756 | Q23: 9.9214941 | R23: 9.9662667 | S23: 9.9975268 | T23: 10.075008 | U23: 10.332362 | V23: 10.880876 | W23: 11.360245 | X23: 12.039769
A24: NZDep decile 4 | B24: Under 2's | C24: 5.1758251 | D24: 5.2616019 | E24: 5.4503042 | F24: 5.7548829 | G24: 6.8190082 | H24: 7.6178828 | I24: 8.4404848 | J24: 9.0781238 | K24: 9.656218 | L24: 9.7157697 | M24: 9.8015343 | N24: 9.86258 | O24: 9.972767 | P24: 10.061113 | Q24: 10.038022 | R24: 10.054498 | S24: 9.9218763 | T24: 9.8486498 | U24: 10.132159 | V24: 10.507258 | W24: 10.827255 | X24: 11.663141
A25: NZDep decile 4 | B25: 2 and over - non 20 Hours ECE | C25: 2.7722254 | D25: 2.8747801 | E25: 3.0017822 | F25: 3.2535637 | G25: 3.8199091 | H25: 4.2562613 | I25: 4.3625938 | J25: 5.1714254 | K25: 5.4214884 | L25: 5.4517796 | M25: 5.4201992 | N25: 5.4670514 | O25: 5.5474983 | P25: 5.634136 | Q25: 5.6485776 | R25: 5.6736639 | S25: 5.664929 | T25: 5.663759 | U25: 5.8298398 | V25: 6.1119314 | W25: 6.3706171 | X25: 6.7733455
A26: NZDep decile 4 | B26: Equity | C26: 0.010362867 | D26: 0.0174118 | E26: 0.018268411 | F26: 0.020580163 | G26: 0.021957749 | H26: 0.021393572 | I26: 0.019619504 | J26: 0.020294342 | K26: 0.019212406 | L26: 0.019907873 | M26: 0.024628185 | N26: 0.035758051 | O26: 0.049322068 | P26: 0.049000171 | Q26: 0.04980212 | R26: 0.051429398 | S26: 0.055022249 | T26: 0.04699426 | U26: 0.048250634 | V26: 0.04922577 | W26: 0.052784527 | X26: 0.053862332
A27: NZDep decile 4 | B27: Targeted Funding for Disadvantage | C27: 0 | D27: 0 | E27: 0 | F27: 0 | G27: 0 | H27: 0 | I27: 0 | J27: 0 | K27: 0 | L27: 0 | M27: 0 | N27: 0 | O27: 0 | P27: 0 | Q27: 0 | R27: 0 | S27: 0.0058987046 | T27: 0.011937712 | U27: 0.012775325 | V27: 0.013556077 | W27: 0.015383839 | X27: 0.017254202
A28: NZDep decile 4 | B28: Total | C28: 3.1040937 | D28: 3.2146619 | E28: 3.3757261 | F28: 3.6550241 | G28: 4.317607 | H28: 4.8234068 | I28: 6.2994827 | J28: 7.5334087 | K28: 8.1596446 | L28: 8.3245546 | M28: 8.3079423 | N28: 8.3784222 | O28: 8.5639738 | P28: 8.6471796 | Q28: 8.6670466 | R28: 8.6499216 | S28: 8.6397487 | T28: 8.6257529 | U28: 8.8322973 | V28: 9.2929267 | W28: 9.6323215 | X28: 10.228962
A29: NZDep decile 5 | B29: 20 Hours ECE | I29: 7.5141969 | J29: 8.6640312 | K29: 9.3554219 | L29: 9.441271 | M29: 9.351209 | N29: 9.427136 | O29: 9.6252731 | P29: 9.7762922 | Q29: 9.8164778 | R29: 9.8498654 | S29: 9.8876059 | T29: 9.9618637 | U29: 10.223423 | V29: 10.800269 | W29: 11.262499 | X29: 11.955926
A30: NZDep decile 5 | B30: Under 2's | C30: 5.186593 | D30: 5.3041137 | E30: 5.4794809 | F30: 5.7422171 | G30: 6.6358271 | H30: 7.2698055 | I30: 7.9187886 | J30: 8.4389187 | K30: 8.9560002 | L30: 9.0370072 | M30: 9.1980075 | N30: 9.3329992 | O30: 9.4901173 | P30: 9.5498258 | Q30: 9.5573182 | R30: 9.50535 | S30: 9.3335469 | T30: 9.3999137 | U30: 9.7757641 | V30: 10.31921 | W30: 10.637209 | X30: 11.372219
A31: NZDep decile 5 | B31: 2 and over - non 20 Hours ECE | C31: 2.7683918 | D31: 2.8501102 | E31: 2.9681046 | F31: 3.212982 | G31: 3.7723299 | H31: 4.1772415 | I31: 4.2813786 | J31: 5.0224034 | K31: 5.2931374 | L31: 5.2679606 | M31: 5.224471 | N31: 5.2896353 | O31: 5.3806873 | P31: 5.4567167 | Q31: 5.4744466 | R31: 5.469682 | S31: 5.4333192 | T31: 5.4737401 | U31: 5.6537813 | V31: 6.0189268 | W31: 6.3131932 | X31: 6.747147
A32: NZDep decile 5 | B32: Equity | C32: 0.013993619 | D32: 0.025480999 | E32: 0.024157451 | F32: 0.023781358 | G32: 0.024650969 | H32: 0.025783463 | I32: 0.024799864 | J32: 0.02679633 | K32: 0.024641313 | L32: 0.024092091 | M32: 0.030516493 | N32: 0.052137266 | O32: 0.07778128 | P32: 0.08667221 | Q32: 0.087665967 | R32: 0.090464948 | S32: 0.10058447 | T32: 0.10264015 | U32: 0.1071247 | V32: 0.10548865 | W32: 0.10366277 | X32: 0.10212378
A33: NZDep decile 5 | B33: Targeted Funding for Disadvantage | C33: 0 | D33: 0 | E33: 0 | F33: 0 | G33: 0 | H33: 0 | I33: 0 | J33: 0 | K33: 0 | L33: 0 | M33: 0 | N33: 0 | O33: 0 | P33: 0 | Q33: 0 | R33: 0 | S33: 0.013429236 | T33: 0.025675085 | U33: 0.026667506 | V33: 0.029257669 | W33: 0.029123757 | X33: 0.029598607
A34: NZDep decile 5 | B34: Total | C34: 3.1664887 | D34: 3.2757808 | E34: 3.4096529 | F34: 3.6621631 | G34: 4.2978115 | H34: 4.7602267 | I34: 6.2869303 | J34: 7.3449593 | K34: 7.9076604 | L34: 7.991282 | M34: 8.0096646 | N34: 8.1463358 | O34: 8.3272702 | P34: 8.4492379 | Q34: 8.4866859 | R34: 8.4398853 | S34: 8.3995878 | T34: 8.4410924 | U34: 8.7085433 | V34: 9.2290563 | W34: 9.5759668 | X34: 10.160211
A35: NZDep decile 6 | B35: 20 Hours ECE | I35: 7.6622787 | J35: 8.9203528 | K35: 9.4535225 | L35: 9.4478525 | M35: 9.3825867 | N35: 9.4672152 | O35: 9.625432 | P35: 9.7621094 | Q35: 9.7862863 | R35: 9.8120722 | S35: 9.8522014 | T35: 9.9522153 | U35: 10.236227 | V35: 10.781025 | W35: 11.237614 | X35: 11.929317
A36: NZDep decile 6 | B36: Under 2's | C36: 5.0401098 | D36: 5.1544147 | E36: 5.3236552 | F36: 5.6121533 | G36: 6.5012803 | H36: 7.2396466 | I36: 7.9634541 | J36: 8.4027177 | K36: 8.9349804 | L36: 8.9719261 | M36: 9.0968872 | N36: 9.2819108 | O36: 9.3923388 | P36: 9.3012624 | Q36: 9.2006506 | R36: 9.3205787 | S36: 9.4702112 | T36: 9.6576381 | U36: 10.032778 | V36: 10.644952 | W36: 11.090707 | X36: 11.885053
A37: NZDep decile 6 | B37: 2 and over - non 20 Hours ECE | C37: 2.7198491 | D37: 2.8089466 | E37: 2.9143762 | F37: 3.1393418 | G37: 3.6987491 | H37: 4.1265365 | I37: 4.214982 | J37: 4.9218086 | K37: 5.2124205 | L37: 5.1825746 | M37: 5.1277957 | N37: 5.230548 | O37: 5.3245192 | P37: 5.3578351 | Q37: 5.3324542 | R37: 5.394157 | S37: 5.4515954 | T37: 5.5425442 | U37: 5.7623663 | V37: 6.1417206 | W37: 6.466693 | X37: 6.9110647
A38: NZDep decile 6 | B38: Equity | C38: 0.018032407 | D38: 0.030766637 | E38: 0.028469706 | F38: 0.028632583 | G38: 0.029192517 | H38: 0.030335323 | I38: 0.027393598 | J38: 0.029359864 | K38: 0.028080327 | L38: 0.02684802 | M38: 0.036540487 | N38: 0.055997981 | O38: 0.077242355 | P38: 0.083137694 | Q38: 0.098671145 | R38: 0.10343496 | S38: 0.10531171 | T38: 0.11113685 | U38: 0.11642109 | V38: 0.1153935 | W38: 0.1076484 | X38: 0.10352618
A39: NZDep decile 6 | B39: Targeted Funding for Disadvantage | C39: 0 | D39: 0 | E39: 0 | F39: 0 | G39: 0 | H39: 0 | I39: 0 | J39: 0 | K39: 0 | L39: 0 | M39: 0 | N39: 0 | O39: 0 | P39: 0 | Q39: 0 | R39: 0 | S39: 0.011354807 | T39: 0.021448554 | U39: 0.021723309 | V39: 0.023130459 | W39: 0.022252912 | X39: 0.023879493
A40: NZDep decile 6 | B40: Total | C40: 3.159503 | D40: 3.2699958 | E40: 3.4125591 | F40: 3.6698538 | G40: 4.3095865 | H40: 4.7915593 | I40: 6.2851456 | J40: 7.4000522 | K40: 7.9011767 | L40: 7.9747474 | M40: 7.9803778 | N40: 8.1332104 | O40: 8.3078297 | P40: 8.3601079 | Q40: 8.3461646 | R40: 8.3687522 | S40: 8.4001432 | T40: 8.5312056 | U40: 8.8261208 | V40: 9.3390064 | W40: 9.7176306 | X40: 10.320034
A41: NZDep decile 7 | B41: 20 Hours ECE | I41: 7.7365087 | J41: 8.9623955 | K41: 9.5438147 | L41: 9.5010717 | M41: 9.4544134 | N41: 9.5001108 | O41: 9.6036511 | P41: 9.697907 | Q41: 9.7201203 | R41: 9.7499093 | S41: 9.7871874 | T41: 9.8862787 | U41: 10.192314 | V41: 10.761163 | W41: 11.211001 | X41: 11.924356
A42: NZDep decile 7 | B42: Under 2's | C42: 5.1461213 | D42: 5.2651136 | E42: 5.4443404 | F42: 5.7296853 | G42: 6.6815535 | H42: 7.405003 | I42: 8.2216989 | J42: 8.7473971 | K42: 9.3322036 | L42: 9.2725611 | M42: 9.2895663 | N42: 9.1672659 | O42: 9.0166184 | P42: 8.806027 | Q42: 8.9575159 | R42: 9.4412153 | S42: 9.5035759 | T42: 9.6258 | U42: 9.9747354 | V42: 10.627045 | W42: 11.012778 | X42: 11.929694
A43: NZDep decile 7 | B43: 2 and over - non 20 Hours ECE | C43: 2.7229763 | D43: 2.8003187 | E43: 2.9097969 | F43: 3.137009 | G43: 3.6700908 | H43: 4.0877244 | I43: 4.239519 | J43: 4.9718541 | K43: 5.2024077 | L43: 5.197855 | M43: 5.1735235 | N43: 5.2085641 | O43: 5.2434448 | P43: 5.2375623 | Q43: 5.2333029 | R43: 5.3599472 | S43: 5.3885316 | T43: 5.4753312 | U43: 5.7414704 | V43: 6.1295543 | W43: 6.4277984 | X43: 6.9118006
A44: NZDep decile 7 | B44: Equity | C44: 0.031488675 | D44: 0.055708815 | E44: 0.053553696 | F44: 0.051608098 | G44: 0.048285524 | H44: 0.047107578 | I44: 0.041500541 | J44: 0.043980245 | K44: 0.043787261 | L44: 0.042263018 | M44: 0.060910686 | N44: 0.099473713 | O44: 0.13647121 | P44: 0.14366047 | Q44: 0.14608382 | R44: 0.15837884 | S44: 0.16368404 | T44: 0.15595749 | U44: 0.15990217 | V44: 0.15965335 | W44: 0.16114102 | X44: 0.16712687
A45: NZDep decile 7 | B45: Targeted Funding for Disadvantage | C45: 0 | D45: 0 | E45: 0 | F45: 0 | G45: 0 | H45: 0 | I45: 0 | J45: 0 | K45: 0 | L45: 0 | M45: 0 | N45: 0 | O45: 0 | P45: 0 | Q45: 0 | R45: 0 | S45: 0.016657657 | T45: 0.032511575 | U45: 0.033735605 | V45: 0.035758311 | W45: 0.035602369 | X45: 0.035933687
A46: NZDep decile 7 | B46: Total | C46: 3.2239994 | D46: 3.3286652 | E46: 3.4392192 | F46: 3.6881909 | G46: 4.3090496 | H46: 4.7843097 | I46: 6.3366218 | J46: 7.4728268 | K46: 7.9841287 | L46: 8.0230331 | M46: 8.0558271 | N46: 8.1123765 | O46: 8.191014 | P46: 8.171863 | Q46: 8.1988198 | R46: 8.3321102 | S46: 8.3901063 | T46: 8.4558623 | U46: 8.7478788 | V46: 9.3332654 | W46: 9.6712139 | X46: 10.345088
A47: NZDep decile 8 | B47: 20 Hours ECE | I47: 7.787161 | J47: 8.9885995 | K47: 9.5282132 | L47: 9.5157908 | M47: 9.4752381 | N47: 9.552982 | O47: 9.6707258 | P47: 9.7667847 | Q47: 9.7636654 | R47: 9.7918912 | S47: 9.8172077 | T47: 9.9050499 | U47: 10.189559 | V47: 10.757961 | W47: 11.226597 | X47: 11.881872
A48: NZDep decile 8 | B48: Under 2's | C48: 5.118216 | D48: 5.2209403 | E48: 5.3913866 | F48: 5.7256057 | G48: 6.7735451 | H48: 7.4689213 | I48: 8.2069082 | J48: 8.6970679 | K48: 9.2336982 | L48: 9.1963912 | M48: 9.2786781 | N48: 9.3533212 | O48: 9.3743452 | P48: 9.4302889 | Q48: 9.3692306 | R48: 9.386463 | S48: 9.4683653 | T48: 9.6622053 | U48: 10.029436 | V48: 10.722929 | W48: 11.143239 | X48: 11.896949
A49: NZDep decile 8 | B49: 2 and over - non 20 Hours ECE | C49: 2.7283277 | D49: 2.8057404 | E49: 2.918847 | F49: 3.1546614 | G49: 3.7447004 | H49: 4.1541684 | I49: 4.2591153 | J49: 4.9599823 | K49: 5.1991227 | L49: 5.1760455 | M49: 5.1788548 | N49: 5.2457466 | O49: 5.298757 | P49: 5.3445246 | Q49: 5.3565701 | R49: 5.3698831 | S49: 5.3788763 | T49: 5.4665103 | U49: 5.733232 | V49: 6.1509395 | W49: 6.4845787 | X49: 6.8885073
A50: NZDep decile 8 | B50: Equity | C50: 0.039437964 | D50: 0.070490695 | E50: 0.067512309 | F50: 0.065720916 | G50: 0.064659911 | H50: 0.061451027 | I50: 0.05642825 | J50: 0.060010874 | K50: 0.05708727 | L50: 0.054602313 | M50: 0.082355137 | N50: 0.14679699 | O50: 0.21201191 | P50: 0.21721013 | Q50: 0.23401633 | R50: 0.25055381 | S50: 0.25498445 | T50: 0.24817578 | U50: 0.2533252 | V50: 0.25254696 | W50: 0.25582169 | X50: 0.25794743
A51: NZDep decile 8 | B51: Targeted Funding for Disadvantage | C51: 0 | D51: 0 | E51: 0 | F51: 0 | G51: 0 | H51: 0 | I51: 0 | J51: 0 | K51: 0 | L51: 0 | M51: 0 | N51: 0 | O51: 0 | P51: 0 | Q51: 0 | R51: 0 | S51: 0.024050195 | T51: 0.045000116 | U51: 0.043516116 | V51: 0.045429192 | W51: 0.046672477 | X51: 0.046568874
A52: NZDep decile 8 | B52: Total | C52: 3.1836292 | D52: 3.3049799 | E52: 3.4225849 | F52: 3.6955102 | G52: 4.384369 | H52: 4.8453338 | I52: 6.3981549 | J52: 7.4767182 | K52: 7.9694434 | L52: 8.0223447 | M52: 8.1129623 | N52: 8.2603474 | O52: 8.3853075 | P52: 8.4543427 | Q52: 8.4329843 | R52: 8.4175625 | S52: 8.4459974 | T52: 8.5478194 | U52: 8.8473932 | V52: 9.4193562 | W52: 9.8134042 | X52: 10.402293
A53: NZDep decile 9 | B53: 20 Hours ECE | I53: 7.7512558 | J53: 8.9550878 | K53: 9.4241881 | L53: 9.3906813 | M53: 9.3506455 | N53: 9.4290109 | O53: 9.5485696 | P53: 9.6847033 | Q53: 9.7168814 | R53: 9.7493912 | S53: 9.8007537 | T53: 9.8726535 | U53: 10.196119 | V53: 10.758032 | W53: 11.245829 | X53: 11.895462
A54: NZDep decile 9 | B54: Under 2's | C54: 5.1279571 | D54: 5.2116142 | E54: 5.3730487 | F54: 5.6812701 | G54: 6.5338219 | H54: 7.1475006 | I54: 7.8407991 | J54: 8.3530978 | K54: 8.8105614 | L54: 8.7680425 | M54: 8.8284741 | N54: 8.8867419 | O54: 9.0648049 | P54: 9.2309682 | Q54: 9.3668862 | R54: 9.423865 | S54: 9.5175439 | T54: 9.6226258 | U54: 10.049911 | V54: 10.644058 | W54: 11.121835 | X54: 11.829437
A55: NZDep decile 9 | B55: 2 and over - non 20 Hours ECE | C55: 2.7488089 | D55: 2.8212514 | E55: 2.9243809 | F55: 3.1552206 | G55: 3.658087 | H55: 4.0521017 | I55: 4.1142238 | J55: 4.7888415 | K55: 5.0147377 | L55: 4.9810036 | M55: 4.9509096 | N55: 5.017725 | O55: 5.1100939 | P55: 5.2241886 | Q55: 5.3065555 | R55: 5.3484201 | S55: 5.4051889 | T55: 5.4544121 | U55: 5.7657181 | V55: 6.2010776 | W55: 6.553741 | X55: 6.9514502
A56: NZDep decile 9 | B56: Equity | C56: 0.067945337 | D56: 0.12550454 | E56: 0.11848821 | F56: 0.11414827 | G56: 0.11305422 | H56: 0.11324476 | I56: 0.10546897 | J56: 0.11189899 | K56: 0.104618 | L56: 0.10078084 | M56: 0.15033137 | N56: 0.25988236 | O56: 0.38216804 | P56: 0.39546429 | Q56: 0.39240859 | R56: 0.39165016 | S56: 0.3973441 | T56: 0.39948225 | U56: 0.40642985 | V56: 0.40360039 | W56: 0.40853591 | X56: 0.41315037
